Workbook

Sheet Instructions
B1: FOUR CORNERS COMMERCIAL QUOTE TEMPLATE
B2: For multifamily and commercial Div 6 / 8 / 10 bids (trim, doors, frames, hardware, specialties). Built from the Carter Lumber proposal format GCs already know.
B4: HOW TO USE
B5: 1. Save As | C5: Save a copy per job: [Job Name] - [GC] - Proposal [#].xlsx. Never type in the master template.
B6: 2. Job Info | C6: Fill every yellow cell: GC, job, plans date, estimator, tax rate (VERIFY the county), margins, bond, dates, and area names.
B7: 3. Line Detail | C7: One row per takeoff item. Pick a Bid Group (Base / Alt 1-5 / Optional / Excluded), CSI Section, Area, Qty, UOM, and enter COST. Sell price, tax, and extensions calculate. Red cells = missing required info.
C8: Per-line margin overrides go in the two 'Override' columns (blank = Job Info default). Delete the 4 blue-italic EXAMPLE rows first.
B9: 4. Alternates | C9: Describe each alternate. Amounts total automatically from Line Detail lines tagged Alt 1-5. Use negative quantities for deducts.
B10: 5. Scope Terms | C10: Set each inclusion, exclusion, qualification, and term to Yes/No for this job. Only 'Yes' items print, auto-numbered. Edit wording as needed.
B11: 6. Review | C11: Check the JOB MARGIN CHECK block at the bottom of Job Info: unassigned $ and missing Bid Group count must both be zero. Look at GP% and labor %.
B12: 7. Send | C12: Print to PDF: Proposal + Area Breakout + Bid Summary (in that order). NEVER send Line Detail or Job Info; they show cost and margin.
C13: Bid Summary's print area grows with the number of lines automatically in Excel. If it ever prints blank pages, select the filled rows and use Page Layout > Print Area > Set Print Area.
B14: 8. VE / Revisions | C14: Before re-pricing, copy the current section totals into 'Bid Comparison' prior columns, then make changes. The sheet shows the deltas for the GC.
B16: COLOR KEY
B17: Yellow + blue text | C17: Input - type here.
B18: Green text | C18: Pulls from another sheet - don't overwrite unless you mean to.
B19: Black text | C19: Formula - don't touch.
B20: Blue italic | C20: Example data - delete before use.
B22: SHEETS
B23: Proposal | C23: CUSTOMER. Cover letter, CSI summary, bond, base total, alternates, inclusions/exclusions/qualifications/terms, signature block.
B24: Area Breakout | C24: CUSTOMER. Section x area matrix plus material/labor by area (Carter's 'Apartments / Clubhouse / Pool Cabana' pages).
B25: Bid Summary | C25: CUSTOMER. Numbered line items with unit and extended price, compacted automatically (no blank rows, Excluded lines removed).
B26: Bid Comparison | C26: CUSTOMER (optional). VE or revision delta sheet.
B27: Line Detail | C27: INTERNAL. Takeoff with cost, margin, and sell.
B28: Job Info | C28: INTERNAL. Inputs and margin check.
B29: Scope Terms | C29: INTERNAL. Library of scope language.
B30: Alternates / Lists | C30: INTERNAL. Supporting tables. Add custom CSI sections in the yellow rows on Lists.
B32: BEFORE FIRST USE | C32: Have Wesley (company attorney) review the Terms & Conditions and Qualifications on 'Scope Terms', especially the finance charge, lien, warranty, and escalation language.

Sheet Job Info
A1: JOB INFO & PRICING INPUTS
A2: Yellow cells with blue text are inputs. Everything else calculates.
A4: COMPANY
A5: Company Name | B5: Four Corners Building Supply
A6: Address | B6: 4349 Corporate Road
A7: City / State / Zip | B7: North Charleston, SC 29405
A8: Office Phone | B8: (843) 970-3812
A9: Website | B9: www.buildfcbs.com
A11: CUSTOMER / GENERAL CONTRACTOR
A12: General Contractor
A13: Attention
A14: Address
A15: City / State / Zip
A16: Phone
A17: Email
A19: PROJECT
A20: Job Name
A21: Four Corners Job #
A22: Job Address
A23: Job City / State / Zip
A24: Project Type | B24: Multifamily
A25: Plans / Specs Dated | C25: Leave blank to print '[date TBD]'.
A26: Addenda Acknowledged | B26: None
A27: Proposal Date
A28: Proposal # | C28: Suggest: FC-YYMM-### (e.g. FC-2610-001).
A29: Revision | B29: 0
A31: ESTIMATOR
A32: Estimator Name
A33: Estimator Phone
A34: Estimator Email
A36: PRICING & COMMERCIAL TERMS
A37: Sales Tax Rate on Material | B37: 0.09 | C37: 9% = Charleston/Berkeley Co. (Carter used 9% on Goose Creek, 7% on Bluffton). VERIFY the county rate for every job.
A38: Include Tax in Material Prices? | B38: Yes
A39: Default Material Margin (GP %) | B39: 0.2 | C39: Gross margin: sell = cost / (1 - margin). Can be overridden per line on Line Detail.
A40: Default Labor Margin (GP %) | B40: 0.15 | C40: Gross margin on installer cost. Can be overridden per line on Line Detail.
A41: Payment & Performance Bond Required? | B41: No
A42: Bond Rate (% of base bid) | B42: 0.015 | C42: 1.5% matches the bond Carter carried on Pepper Hall ($36,008 on ~$2.40M). Get a real quote from the surety on bonded jobs.
A43: Proposal Valid (days) | B43: 30 | C43: Carter used 30 days.
A44: Escalation Threshold Before Pass-Through | B44: 0.03 | C44: Material increases above this % get passed to the GC (Qualification #3).
A45: Contract & Approved Submittals By
A46: Substantial Completion Date
A47: Payment Terms | B47: Monthly progress billing, Net 30 from invoice date
A48: Max Retainage | B48: 0.05 | C48: Shows up in the payment qualification.
A49: Mobilizations Included (per bldg/phase, per scope) | B49: 2 | C49: Carter: 'reasonable number of units per mobilization'. We name a number instead.
A50: Additional Mobilization Charge ($/trip) | B50: 350 | C50: Placeholder; set your own trip charge.
A52: AREAS (used for the Area Breakout - rename to fit the job)
A53: Area 1 | B53: Units / Apartments
A54: Area 2 | B54: Clubhouse
A55: Area 3 | B55: Leasing / Amenity
A56: Area 4 | B56: Corridors / Common
A57: Area 5 | B57: Maintenance
A58: Area 6 | B58: Garages
A59: Area 7 | B59: Pool Cabana
A60: Area 8
A62: JOB MARGIN CHECK (INTERNAL - DO NOT SEND)
A63: Base Material Cost (pre-tax) | B63: =SUMIFS('Line Detail'!$U$6:$U$505,'Line Detail'!$B$6:$B$505,"Base") -> 3285
A64: Base Labor Cost | B64: =SUMIFS('Line Detail'!$V$6:$V$505,'Line Detail'!$B$6:$B$505,"Base") -> 1575
A65: Sales Tax in Base Bid | B65: =SUMIFS('Line Detail'!$X$6:$X$505,'Line Detail'!$B$6:$B$505,"Base") -> 369.5625
A66: Base Sell (before bond) | B66: =SUMIFS('Line Detail'!$R$6:$R$505,'Line Detail'!$B$6:$B$505,"Base") -> 6328.7537
A67: Gross Profit $ (excl. tax) | B67: =B66-B63-B64-B65 -> 1099.1912
A68: Gross Profit % (excl. tax) | B68: =IF(B66-B65=0,0,B67/(B66-B65)) -> 0.18445308
A69: Labor % of Base Sell | B69: =IF(B66=0,0,SUMIFS('Line Detail'!$Q$6:$Q$505,'Line Detail'!$B$6:$B$505,"Base")/B66) -> 0.29278137 | C69: Carter's bids ran 24-29% labor. Useful sanity check.
A70: Base lines with no CSI section ($) | B70: =SUMIFS('Line Detail'!$R$6:$R$505,'Line Detail'!$B$6:$B$505,"Base",'Line Detail'!$C$6:$C$505,"") -> 0 | C70: Should be $0. Anything here is missing from the proposal section list.
A71: Lines with a description but no Bid Group (count) | B71: =COUNTIFS('Line Detail'!$F$6:$F$505,"?*",'Line Detail'!$B$6:$B$505,"") -> 0 | C71: Should be 0. Lines without a Bid Group are NOT priced anywhere.
A72: CSI sections carrying $ (Proposal fits 16) | B72: =Lists!$J$2 -> 3 | C72: If over 16, combine sections - extras won't show on the Proposal summary.

Sheet Line Detail
A1: LINE DETAIL / TAKEOFF (INTERNAL - contains cost)
A2: ="Job: "&IF('Job Info'!$B$20="","[Job Name]",'Job Info'!$B$20)&" | Tax on material: "&IF('Job Info'!$B$38="Yes",TEXT('Job Info'!$B$37,"0.00%"),"not included")&" | Default margins: Mat "&TEXT('Job Info'!$B$39,"0.0%")&" / Labor "&TEXT('Job Info'!$B$40,"0.0%") -> Job: [Job Name] | Tax on material: 9.00% | Default margins: Mat 20.0% / Labor 15.0%
A3: Enter lines grouped by CSI section, then by area, so the Bid Summary prints in a sensible order. Put each hardware set's components in the Description (one line per set, like Carter does).
A4: WHAT | I4: COST INPUTS | M4: SELL (calculated) | S4: NOTES | U4: HELPERS
A5: Line # | B5: Bid Group | C5: CSI Section | D5: Area | E5: Mark / Tag | F5: Description / Specification | G5: Qty | H5: UOM | I5: Mat Unit Cost | J5: Labor Unit Cost | K5: Mat Margin Override | L5: Labor Margin Override | M5: Mat Unit Sell (incl. tax) | N5: Labor Unit Sell | O5: Unit Price (Mat + Labor) | P5: Material Ext. | Q5: Labor Ext. | R5: Total Ext. | S5: Customer Note (prints) | T5: Internal Note (does not print) | U5: Mat Cost Ext. | V5: Labor Cost Ext. | W5: Print Seq | X5: Tax $
A6: =IF(F6="","",ROW()-5) -> 1 | B6: Base | C6: 06 20 00 Interior Trim / Finish Carpentry | D6: Units / Apartments | F6: Base FJ Primed 1x6 | G6: 1000 | H6: LF | I6: 1.45 | J6: 1.1 | M6: =IF(F6="","",N(I6)/(1-IF(K6="",'Job Info'!$B$39,K6))*(1+IF('Job Info'!$B$38="Yes",'Job Info'!$B$37,0))) -> 1.975625 | N6: =IF(F6="","",N(J6)/(1-IF(L6="",'Job Info'!$B$40,L6))) -> 1.2941176 | O6: =IF(F6="","",M6+N6) -> 3.2697426 | P6: =IF(F6="","",N(G6)*M6) -> 1975.625 | Q6: =IF(F6="","",N(G6)*N6) -> 1294.1176 | R6: =IF(F6="","",P6+Q6) -> 3269.7426 | T6: EXAMPLE - delete before use | U6: =IF(F6="","",N(G6)*N(I6)) -> 1450 | V6: =IF(F6="","",N(G6)*N(J6)) -> 1100 | W6: =IF(F6="","",IF(B6="Excluded","",COUNTIFS($F$6:F6,"?*",$B$6:B6,"<>Excluded"))) -> 1 | X6: =IF(F6="","",N(G6)*N(I6)/(1-IF(K6="",'Job Info'!$B$39,K6))*IF('Job Info'!$B$38="Yes",'Job Info'!$B$37,0)) -> 163.125
A7: =IF(F7="","",ROW()-5) -> 2 | B7: Base | C7: 08 17 43 Interior Pre-Hung Doors | D7: Units / Apartments | E7: Type 4 | F7: 3068 Hollow Core Hardboard 2-Panel Shaker 1-3/8", FJ split jamb 4-7/8" w/ FJ 1x4 casing, 3 ea US15 hinges, 2-3/8" backset single bore | G7: 10 | H7: EA | I7: 165 | J7: 38 | M7: =IF(F7="","",N(I7)/(1-IF(K7="",'Job Info'!$B$39,K7))*(1+IF('Job Info'!$B$38="Yes",'Job Info'!$B$37,0))) -> 224.8125 | N7: =IF(F7="","",N(J7)/(1-IF(L7="",'Job Info'!$B$40,L7))) -> 44.705882 | O7: =IF(F7="","",M7+N7) -> 269.51838 | P7: =IF(F7="","",N(G7)*M7) -> 2248.125 | Q7: =IF(F7="","",N(G7)*N7) -> 447.05882 | R7: =IF(F7="","",P7+Q7) -> 2695.1838 | T7: EXAMPLE - delete before use | U7: =IF(F7="","",N(G7)*N(I7)) -> 1650 | V7: =IF(F7="","",N(G7)*N(J7)) -> 380 | W7: =IF(F7="","",IF(B7="Excluded","",COUNTIFS($F$6:F7,"?*",$B$6:B7,"<>Excluded"))) -> 2 | X7: =IF(F7="","",N(G7)*N(I7)/(1-IF(K7="",'Job Info'!$B$39,K7))*IF('Job Info'!$B$38="Yes",'Job Info'!$B$37,0)) -> 185.625
A8: =IF(F8="","",ROW()-5) -> 3 | B8: Base | C8: 08 71 00 Door Hardware | D8: Units / Apartments | E8: HW Set Bed/Bath | F8: 1 ea privacy lever US15; 1 ea door stop US15 | G8: 10 | H8: SET | I8: 18.5 | J8: 9.5 | M8: =IF(F8="","",N(I8)/(1-IF(K8="",'Job Info'!$B$39,K8))*(1+IF('Job Info'!$B$38="Yes",'Job Info'!$B$37,0))) -> 25.20625 | N8: =IF(F8="","",N(J8)/(1-IF(L8="",'Job Info'!$B$40,L8))) -> 11.176471 | O8: =IF(F8="","",M8+N8) -> 36.382721 | P8: =IF(F8="","",N(G8)*M8) -> 252.0625 | Q8: =IF(F8="","",N(G8)*N8) -> 111.76471 | R8: =IF(F8="","",P8+Q8) -> 363.82721 | T8: EXAMPLE - delete before use | U8: =IF(F8="","",N(G8)*N(I8)) -> 185 | V8: =IF(F8="","",N(G8)*N(J8)) -> 95 | W8: =IF(F8="","",IF(B8="Excluded","",COUNTIFS($F$6:F8,"?*",$B$6:B8,"<>Excluded"))) -> 3 | X8: =IF(F8="","",N(G8)*N(I8)/(1-IF(K8="",'Job Info'!$B$39,K8))*IF('Job Info'!$B$38="Yes",'Job Info'!$B$37,0)) -> 20.8125
A9: =IF(F9="","",ROW()-5) -> 4 | B9: Alt 1 | C9: 08 71 00 Door Hardware | D9: Units / Apartments | E9: HW Set Entry | F9: ADD: battery-powered keypad deadbolt in lieu of keyed deadbolt | G9: 10 | H9: EA | I9: 240 | J9: 25 | M9: =IF(F9="","",N(I9)/(1-IF(K9="",'Job Info'!$B$39,K9))*(1+IF('Job Info'!$B$38="Yes",'Job Info'!$B$37,0))) -> 327 | N9: =IF(F9="","",N(J9)/(1-IF(L9="",'Job Info'!$B$40,L9))) -> 29.411765 | O9: =IF(F9="","",M9+N9) -> 356.41176 | P9: =IF(F9="","",N(G9)*M9) -> 3270 | Q9: =IF(F9="","",N(G9)*N9) -> 294.11765 | R9: =IF(F9="","",P9+Q9) -> 3564.1176 | S9: Add alternate | T9: EXAMPLE - delete before use | U9: =IF(F9="","",N(G9)*N(I9)) -> 2400 | V9: =IF(F9="","",N(G9)*N(J9)) -> 250 | W9: =IF(F9="","",IF(B9="Excluded","",COUNTIFS($F$6:F9,"?*",$B$6:B9,"<>Excluded"))) -> 4 | X9: =IF(F9="","",N(G9)*N(I9)/(1-IF(K9="",'Job Info'!$B$39,K9))*IF('Job Info'!$B$38="Yes",'Job Info'!$B$37,0)) -> 270
A10: =IF(F10="","",ROW()-5) | M10: =IF(F10="","",N(I10)/(1-IF(K10="",'Job Info'!$B$39,K10))*(1+IF('Job Info'!$B$38="Yes",'Job Info'!$B$37,0))) | N10: =IF(F10="","",N(J10)/(1-IF(L10="",'Job Info'!$B$40,L10))) | O10: =IF(F10="","",M10+N10) | P10: =IF(F10="","",N(G10)*M10) | Q10: =IF(F10="","",N(G10)*N10) | R10: =IF(F10="","",P10+Q10) | U10: =IF(F10="","",N(G10)*N(I10)) | V10: =IF(F10="","",N(G10)*N(J10)) | W10: =IF(F10="","",IF(B10="Excluded","",COUNTIFS($F$6:F10,"?*",$B$6:B10,"<>Excluded"))) | X10: =IF(F10="","",N(G10)*N(I10)/(1-IF(K10="",'Job Info'!$B$39,K10))*IF('Job Info'!$B$38="Yes",'Job Info'!$B$37,0))
A11: =IF(F11="","",ROW()-5) | M11: =IF(F11="","",N(I11)/(1-IF(K11="",'Job Info'!$B$39,K11))*(1+IF('Job Info'!$B$38="Yes",'Job Info'!$B$37,0))) | N11: =IF(F11="","",N(J11)/(1-IF(L11="",'Job Info'!$B$40,L11))) | O11: =IF(F11="","",M11+N11) | P11: =IF(F11="","",N(G11)*M11) | Q11: =IF(F11="","",N(G11)*N11) | R11: =IF(F11="","",P11+Q11) | U11: =IF(F11="","",N(G11)*N(I11)) | V11: =IF(F11="","",N(G11)*N(J11)) | W11: =IF(F11="","",IF(B11="Excluded","",COUNTIFS($F$6:F11,"?*",$B$6:B11,"<>Excluded"))) | X11: =IF(F11="","",N(G11)*N(I11)/(1-IF(K11="",'Job Info'!$B$39,K11))*IF('Job Info'!$B$38="Yes",'Job Info'!$B$37,0))
A12: =IF(F12="","",ROW()-5) | M12: =IF(F12="","",N(I12)/(1-IF(K12="",'Job Info'!$B$39,K12))*(1+IF('Job Info'!$B$38="Yes",'Job Info'!$B$37,0))) | N12: =IF(F12="","",N(J12)/(1-IF(L12="",'Job Info'!$B$40,L12))) | O12: =IF(F12="","",M12+N12) | P12: =IF(F12="","",N(G12)*M12) | Q12: =IF(F12="","",N(G12)*N12) | R12: =IF(F12="","",P12+Q12) | U12: =IF(F12="","",N(G12)*N(I12)) | V12: =IF(F12="","",N(G12)*N(J12)) | W12: =IF(F12="","",IF(B12="Excluded","",COUNTIFS($F$6:F12,"?*",$B$6:B12,"<>Excluded"))) | X12: =IF(F12="","",N(G12)*N(I12)/(1-IF(K12="",'Job Info'!$B$39,K12))*IF('Job Info'!$B$38="Yes",'Job Info'!$B$37,0))
A13: =IF(F13="","",ROW()-5) | M13: =IF(F13="","",N(I13)/(1-IF(K13="",'Job Info'!$B$39,K13))*(1+IF('Job Info'!$B$38="Yes",'Job Info'!$B$37,0))) | N13: =IF(F13="","",N(J13)/(1-IF(L13="",'Job Info'!$B$40,L13))) | O13: =IF(F13="","",M13+N13) | P13: =IF(F13="","",N(G13)*M13) | Q13: =IF(F13="","",N(G13)*N13) | R13: =IF(F13="","",P13+Q13) | U13: =IF(F13="","",N(G13)*N(I13)) | V13: =IF(F13="","",N(G13)*N(J13)) | W13: =IF(F13="","",IF(B13="Excluded","",COUNTIFS($F$6:F13,"?*",$B$6:B13,"<>Excluded"))) | X13: =IF(F13="","",N(G13)*N(I13)/(1-IF(K13="",'Job Info'!$B$39,K13))*IF('Job Info'!$B$38="Yes",'Job Info'!$B$37,0))
A14: =IF(F14="","",ROW()-5) | M14: =IF(F14="","",N(I14)/(1-IF(K14="",'Job Info'!$B$39,K14))*(1+IF('Job Info'!$B$38="Yes",'Job Info'!$B$37,0))) | N14: =IF(F14="","",N(J14)/(1-IF(L14="",'Job Info'!$B$40,L14))) | O14: =IF(F14="","",M14+N14) | P14: =IF(F14="","",N(G14)*M14) | Q14: =IF(F14="","",N(G14)*N14) | R14: =IF(F14="","",P14+Q14) | U14: =IF(F14="","",N(G14)*N(I14)) | V14: =IF(F14="","",N(G14)*N(J14)) | W14: =IF(F14="","",IF(B14="Excluded","",COUNTIFS($F$6:F14,"?*",$B$6:B14,"<>Excluded"))) | X14: =IF(F14="","",N(G14)*N(I14)/(1-IF(K14="",'Job Info'!$B$39,K14))*IF('Job Info'!$B$38="Yes",'Job Info'!$B$37,0))
A15: =IF(F15="","",ROW()-5) | M15: =IF(F15="","",N(I15)/(1-IF(K15="",'Job Info'!$B$39,K15))*(1+IF('Job Info'!$B$38="Yes",'Job Info'!$B$37,0))) | N15: =IF(F15="","",N(J15)/(1-IF(L15="",'Job Info'!$B$40,L15))) | O15: =IF(F15="","",M15+N15) | P15: =IF(F15="","",N(G15)*M15) | Q15: =IF(F15="","",N(G15)*N15) | R15: =IF(F15="","",P15+Q15) | U15: =IF(F15="","",N(G15)*N(I15)) | V15: =IF(F15="","",N(G15)*N(J15)) | W15: =IF(F15="","",IF(B15="Excluded","",COUNTIFS($F$6:F15,"?*",$B$6:B15,"<>Excluded"))) | X15: =IF(F15="","",N(G15)*N(I15)/(1-IF(K15="",'Job Info'!$B$39,K15))*IF('Job Info'!$B$38="Yes",'Job Info'!$B$37,0))
A16: =IF(F16="","",ROW()-5) | M16: =IF(F16="","",N(I16)/(1-IF(K16="",'Job Info'!$B$39,K16))*(1+IF('Job Info'!$B$38="Yes",'Job Info'!$B$37,0))) | N16: =IF(F16="","",N(J16)/(1-IF(L16="",'Job Info'!$B$40,L16))) | O16: =IF(F16="","",M16+N16) | P16: =IF(F16="","",N(G16)*M16) | Q16: =IF(F16="","",N(G16)*N16) | R16: =IF(F16="","",P16+Q16) | U16: =IF(F16="","",N(G16)*N(I16)) | V16: =IF(F16="","",N(G16)*N(J16)) | W16: =IF(F16="","",IF(B16="Excluded","",COUNTIFS($F$6:F16,"?*",$B$6:B16,"<>Excluded"))) | X16: =IF(F16="","",N(G16)*N(I16)/(1-IF(K16="",'Job Info'!$B$39,K16))*IF('Job Info'!$B$38="Yes",'Job Info'!$B$37,0))
A17: =IF(F17="","",ROW()-5) | M17: =IF(F17="","",N(I17)/(1-IF(K17="",'Job Info'!$B$39,K17))*(1+IF('Job Info'!$B$38="Yes",'Job Info'!$B$37,0))) | N17: =IF(F17="","",N(J17)/(1-IF(L17="",'Job Info'!$B$40,L17))) | O17: =IF(F17="","",M17+N17) | P17: =IF(F17="","",N(G17)*M17) | Q17: =IF(F17="","",N(G17)*N17) | R17: =IF(F17="","",P17+Q17) | U17: =IF(F17="","",N(G17)*N(I17)) | V17: =IF(F17="","",N(G17)*N(J17)) | W17: =IF(F17="","",IF(B17="Excluded","",COUNTIFS($F$6:F17,"?*",$B$6:B17,"<>Excluded"))) | X17: =IF(F17="","",N(G17)*N(I17)/(1-IF(K17="",'Job Info'!$B$39,K17))*IF('Job Info'!$B$38="Yes",'Job Info'!$B$37,0))
A18: =IF(F18="","",ROW()-5) | M18: =IF(F18="","",N(I18)/(1-IF(K18="",'Job Info'!$B$39,K18))*(1+IF('Job Info'!$B$38="Yes",'Job Info'!$B$37,0))) | N18: =IF(F18="","",N(J18)/(1-IF(L18="",'Job Info'!$B$40,L18))) | O18: =IF(F18="","",M18+N18) | P18: =IF(F18="","",N(G18)*M18) | Q18: =IF(F18="","",N(G18)*N18) | R18: =IF(F18="","",P18+Q18) | U18: =IF(F18="","",N(G18)*N(I18)) | V18: =IF(F18="","",N(G18)*N(J18)) | W18: =IF(F18="","",IF(B18="Excluded","",COUNTIFS($F$6:F18,"?*",$B$6:B18,"<>Excluded"))) | X18: =IF(F18="","",N(G18)*N(I18)/(1-IF(K18="",'Job Info'!$B$39,K18))*IF('Job Info'!$B$38="Yes",'Job Info'!$B$37,0))
A19: =IF(F19="","",ROW()-5) | M19: =IF(F19="","",N(I19)/(1-IF(K19="",'Job Info'!$B$39,K19))*(1+IF('Job Info'!$B$38="Yes",'Job Info'!$B$37,0))) | N19: =IF(F19="","",N(J19)/(1-IF(L19="",'Job Info'!$B$40,L19))) | O19: =IF(F19="","",M19+N19) | P19: =IF(F19="","",N(G19)*M19) | Q19: =IF(F19="","",N(G19)*N19) | R19: =IF(F19="","",P19+Q19) | U19: =IF(F19="","",N(G19)*N(I19)) | V19: =IF(F19="","",N(G19)*N(J19)) | W19: =IF(F19="","",IF(B19="Excluded","",COUNTIFS($F$6:F19,"?*",$B$6:B19,"<>Excluded"))) | X19: =IF(F19="","",N(G19)*N(I19)/(1-IF(K19="",'Job Info'!$B$39,K19))*IF('Job Info'!$B$38="Yes",'Job Info'!$B$37,0))
A20: =IF(F20="","",ROW()-5) | M20: =IF(F20="","",N(I20)/(1-IF(K20="",'Job Info'!$B$39,K20))*(1+IF('Job Info'!$B$38="Yes",'Job Info'!$B$37,0))) | N20: =IF(F20="","",N(J20)/(1-IF(L20="",'Job Info'!$B$40,L20))) | O20: =IF(F20="","",M20+N20) | P20: =IF(F20="","",N(G20)*M20) | Q20: =IF(F20="","",N(G20)*N20) | R20: =IF(F20="","",P20+Q20) | U20: =IF(F20="","",N(G20)*N(I20)) | V20: =IF(F20="","",N(G20)*N(J20)) | W20: =IF(F20="","",IF(B20="Excluded","",COUNTIFS($F$6:F20,"?*",$B$6:B20,"<>Excluded"))) | X20: =IF(F20="","",N(G20)*N(I20)/(1-IF(K20="",'Job Info'!$B$39,K20))*IF('Job Info'!$B$38="Yes",'Job Info'!$B$37,0))
A21: =IF(F21="","",ROW()-5) | M21: =IF(F21="","",N(I21)/(1-IF(K21="",'Job Info'!$B$39,K21))*(1+IF('Job Info'!$B$38="Yes",'Job Info'!$B$37,0))) | N21: =IF(F21="","",N(J21)/(1-IF(L21="",'Job Info'!$B$40,L21))) | O21: =IF(F21="","",M21+N21) | P21: =IF(F21="","",N(G21)*M21) | Q21: =IF(F21="","",N(G21)*N21) | R21: =IF(F21="","",P21+Q21) | U21: =IF(F21="","",N(G21)*N(I21)) | V21: =IF(F21="","",N(G21)*N(J21)) | W21: =IF(F21="","",IF(B21="Excluded","",COUNTIFS($F$6:F21,"?*",$B$6:B21,"<>Excluded"))) | X21: =IF(F21="","",N(G21)*N(I21)/(1-IF(K21="",'Job Info'!$B$39,K21))*IF('Job Info'!$B$38="Yes",'Job Info'!$B$37,0))
... A505: =IF(F505="","",ROW()-5) | M505: =IF(F505="","",N(I505)/(1-IF(K505="",'Job Info'!$B$39,K505))*(1+IF('Job Info'!$B$38="Yes",'Job Info'!$B$37,0))) | N505: =IF(F505="","",N(J505)/(1-IF(L505="",'Job Info'!$B$40,L505))) | O505: =IF(F505="","",M505+N505) | P505: =IF(F505="","",N(G505)*M505) | Q505: =IF(F505="","",N(G505)*N505) | R505: =IF(F505="","",P505+Q505) | U505: =IF(F505="","",N(G505)*N(I505)) | V505: =IF(F505="","",N(G505)*N(J505)) | W505: =IF(F505="","",IF(B505="Excluded","",COUNTIFS($F$6:F505,"?*",$B$6:B505,"<>Excluded"))) | X505: =IF(F505="","",N(G505)*N(I505)/(1-IF(K505="",'Job Info'!$B$39,K505))*IF('Job Info'!$B$38="Yes",'Job Info'!$B$37,0))
F506: TOTAL - BASE BID LINES | P506: =SUMIFS(P6:P505,$B$6:$B$505,"Base") -> 4475.8125 | Q506: =SUMIFS(Q6:Q505,$B$6:$B$505,"Base") -> 1852.9412 | R506: =SUMIFS(R6:R505,$B$6:$B$505,"Base") -> 6328.7537 | U506: =SUMIFS(U6:U505,$B$6:$B$505,"Base") -> 3285 | V506: =SUMIFS(V6:V505,$B$6:$B$505,"Base") -> 1575

Sheet Alternates
A1: ALTERNATES & OPTIONS
A2: Alternate amounts total automatically from Line Detail lines tagged Alt 1-Alt 5. Enter deducts as negative quantities. Describe each alternate in column B; it only prints if it has a description or an amount.
A4: Alt # | B4: Description (prints on proposal) | C4: Add / (Deduct) | D4: Material | E4: Labor
A5: Alt 1 | B5: Battery-powered keypad deadbolts at unit entries in lieu of keyed deadbolts (EXAMPLE) | C5: =SUMIFS('Line Detail'!$R$6:$R$505,'Line Detail'!$B$6:$B$505,A5) -> 3564.1176 | D5: =SUMIFS('Line Detail'!$P$6:$P$505,'Line Detail'!$B$6:$B$505,A5) -> 3270 | E5: =SUMIFS('Line Detail'!$Q$6:$Q$505,'Line Detail'!$B$6:$B$505,A5) -> 294.11765
A6: Alt 2 | C6: =SUMIFS('Line Detail'!$R$6:$R$505,'Line Detail'!$B$6:$B$505,A6) -> 0 | D6: =SUMIFS('Line Detail'!$P$6:$P$505,'Line Detail'!$B$6:$B$505,A6) -> 0 | E6: =SUMIFS('Line Detail'!$Q$6:$Q$505,'Line Detail'!$B$6:$B$505,A6) -> 0
A7: Alt 3 | C7: =SUMIFS('Line Detail'!$R$6:$R$505,'Line Detail'!$B$6:$B$505,A7) -> 0 | D7: =SUMIFS('Line Detail'!$P$6:$P$505,'Line Detail'!$B$6:$B$505,A7) -> 0 | E7: =SUMIFS('Line Detail'!$Q$6:$Q$505,'Line Detail'!$B$6:$B$505,A7) -> 0
A8: Alt 4 | C8: =SUMIFS('Line Detail'!$R$6:$R$505,'Line Detail'!$B$6:$B$505,A8) -> 0 | D8: =SUMIFS('Line Detail'!$P$6:$P$505,'Line Detail'!$B$6:$B$505,A8) -> 0 | E8: =SUMIFS('Line Detail'!$Q$6:$Q$505,'Line Detail'!$B$6:$B$505,A8) -> 0
A9: Alt 5 | C9: =SUMIFS('Line Detail'!$R$6:$R$505,'Line Detail'!$B$6:$B$505,A9) -> 0 | D9: =SUMIFS('Line Detail'!$P$6:$P$505,'Line Detail'!$B$6:$B$505,A9) -> 0 | E9: =SUMIFS('Line Detail'!$Q$6:$Q$505,'Line Detail'!$B$6:$B$505,A9) -> 0
A11: Optional | B11: Optional items, priced individually in the attached Bid Summary | C11: =SUMIFS('Line Detail'!$R$6:$R$505,'Line Detail'!$B$6:$B$505,"Optional") -> 0 | D11: =SUMIFS('Line Detail'!$P$6:$P$505,'Line Detail'!$B$6:$B$505,"Optional") -> 0 | E11: =SUMIFS('Line Detail'!$Q$6:$Q$505,'Line Detail'!$B$6:$B$505,"Optional") -> 0

Sheet Scope Terms
A1: INCLUSIONS / EXCLUSIONS / QUALIFICATIONS / TERMS
A2: Set column B to Yes/No per job. 'Yes' items print on the Proposal, auto-numbered. Edit wording freely; add your own items in the blank rows at the end of each group (set the Category).
A3: Items in green are formulas that pull from Job Info - overwrite them only if you need custom wording.
A4: Category | B4: Print? | C4: Text | D4: Seq | E4: Key
A5: Inclusion | B5: Yes | C5: All items listed in the attached Bid Summary, which is part of this proposal. | D5: =IF(AND(B5="Yes",LEN(C5)>0),COUNTIFS($A$5:A5,A5,$B$5:B5,"Yes",$C$5:C5,"?*"),"") -> 1 | E5: =IF(D5="","",A5&"|"&D5) -> Inclusion|1
A6: Inclusion | B6: Yes | C6: =IF('Job Info'!$B$38="Yes","All material pricing includes "&TEXT('Job Info'!$B$37,"0.0%")&" sales tax.","Sales tax is NOT included in material pricing and will be added at invoicing.") -> All material pricing includes 9.0% sales tax. | D6: =IF(AND(B6="Yes",LEN(C6)>0),COUNTIFS($A$5:A6,A6,$B$5:B6,"Yes",$C$5:C6,"?*"),"") -> 2 | E6: =IF(D6="","",A6&"|"&D6) -> Inclusion|2
A7: Inclusion | B7: Yes | C7: ="Pricing is based on plans and specifications dated "&IF('Job Info'!$B$25="","[date TBD]",TEXT('Job Info'!$B$25,"mmmm d, yyyy"))&", and addenda: "&'Job Info'!$B$26&"." -> Pricing is based on plans and specifications dated [date TBD], and addenda: None. | D7: =IF(AND(B7="Yes",LEN(C7)>0),COUNTIFS($A$5:A7,A7,$B$5:B7,"Yes",$C$5:C7,"?*"),"") -> 3 | E7: =IF(D7="","",A7&"|"&D7) -> Inclusion|3
A8: Inclusion | B8: Yes | C8: Delivery of all materials to the jobsite, ground level, at each building. | D8: =IF(AND(B8="Yes",LEN(C8)>0),COUNTIFS($A$5:A8,A8,$B$5:B8,"Yes",$C$5:C8,"?*"),"") -> 4 | E8: =IF(D8="","",A8&"|"&D8) -> Inclusion|4
A9: Inclusion | B9: Yes | C9: Installation labor for every line item that shows a labor price in the Bid Summary. | D9: =IF(AND(B9="Yes",LEN(C9)>0),COUNTIFS($A$5:A9,A9,$B$5:B9,"Yes",$C$5:C9,"?*"),"") -> 5 | E9: =IF(D9="","",A9&"|"&D9) -> Inclusion|5
A10: Inclusion | B10: Yes | C10: Interior and exterior pre-hung doors with hinges installed and bored or prepped for the scheduled hardware. | D10: =IF(AND(B10="Yes",LEN(C10)>0),COUNTIFS($A$5:A10,A10,$B$5:B10,"Yes",$C$5:C10,"?*"),"") -> 6 | E10: =IF(D10="","",A10&"|"&D10) -> Inclusion|6
A11: Inclusion | B11: Yes | C11: Fire-rated doors and frames with factory labels as scheduled. | D11: =IF(AND(B11="Yes",LEN(C11)>0),COUNTIFS($A$5:A11,A11,$B$5:B11,"Yes",$C$5:C11,"?*"),"") -> 7 | E11: =IF(D11="","",A11&"|"&D11) -> Inclusion|7
A12: Inclusion | B12: Yes | C12: Product data, door and hardware schedules, and submittals; warranty and O&M documents at closeout. | D12: =IF(AND(B12="Yes",LEN(C12)>0),COUNTIFS($A$5:A12,A12,$B$5:B12,"Yes",$C$5:C12,"?*"),"") -> 8 | E12: =IF(D12="","",A12&"|"&D12) -> Inclusion|8
A13: Inclusion | B13: Yes | C13: Removal of our packaging and debris to the GC-provided on-site dumpster. | D13: =IF(AND(B13="Yes",LEN(C13)>0),COUNTIFS($A$5:A13,A13,$B$5:B13,"Yes",$C$5:C13,"?*"),"") -> 9 | E13: =IF(D13="","",A13&"|"&D13) -> Inclusion|9
A14: Inclusion | B14: No | D14: =IF(AND(B14="Yes",LEN(C14)>0),COUNTIFS($A$5:A14,A14,$B$5:B14,"Yes",$C$5:C14,"?*"),"") | E14: =IF(D14="","",A14&"|"&D14)
A15: Inclusion | B15: No | D15: =IF(AND(B15="Yes",LEN(C15)>0),COUNTIFS($A$5:A15,A15,$B$5:B15,"Yes",$C$5:C15,"?*"),"") | E15: =IF(D15="","",A15&"|"&D15)
A16: Inclusion | B16: No | D16: =IF(AND(B16="Yes",LEN(C16)>0),COUNTIFS($A$5:A16,A16,$B$5:B16,"Yes",$C$5:C16,"?*"),"") | E16: =IF(D16="","",A16&"|"&D16)
A17: Inclusion | B17: No | D17: =IF(AND(B17="Yes",LEN(C17)>0),COUNTIFS($A$5:A17,A17,$B$5:B17,"Yes",$C$5:C17,"?*"),"") | E17: =IF(D17="","",A17&"|"&D17)
A18: Exclusion | B18: Yes | C18: Chair rail and crown moulding in units | D18: =IF(AND(B18="Yes",LEN(C18)>0),COUNTIFS($A$5:A18,A18,$B$5:B18,"Yes",$C$5:C18,"?*"),"") -> 1 | E18: =IF(D18="","",A18&"|"&D18) -> Exclusion|1
A19: Exclusion | B19: Yes | C19: Cased openings and interior columns | D19: =IF(AND(B19="Yes",LEN(C19)>0),COUNTIFS($A$5:A19,A19,$B$5:B19,"Yes",$C$5:C19,"?*"),"") -> 2 | E19: =IF(D19="","",A19&"|"&D19) -> Exclusion|2
A20: Exclusion | B20: Yes | C20: Cabinets, countertops, vanities, desks, and built-ins unless listed | D20: =IF(AND(B20="Yes",LEN(C20)>0),COUNTIFS($A$5:A20,A20,$B$5:B20,"Yes",$C$5:C20,"?*"),"") -> 3 | E20: =IF(D20="","",A20&"|"&D20) -> Exclusion|3
A21: Exclusion | B21: Yes | C21: Stair parts and railings | D21: =IF(AND(B21="Yes",LEN(C21)>0),COUNTIFS($A$5:A21,A21,$B$5:B21,"Yes",$C$5:C21,"?*"),"") -> 4 | E21: =IF(D21="","",A21&"|"&D21) -> Exclusion|4
A22: Exclusion | B22: Yes | C22: Toilet partitions, shower doors, and shower enclosures unless listed | D22: =IF(AND(B22="Yes",LEN(C22)>0),COUNTIFS($A$5:A22,A22,$B$5:B22,"Yes",$C$5:C22,"?*"),"") -> 5 | E22: =IF(D22="","",A22&"|"&D22) -> Exclusion|5
A23: Exclusion | B23: Yes | C23: Garage doors, overhead doors, and draft-stop or attic access doors | D23: =IF(AND(B23="Yes",LEN(C23)>0),COUNTIFS($A$5:A23,A23,$B$5:B23,"Yes",$C$5:C23,"?*"),"") -> 6 | E23: =IF(D23="","",A23&"|"&D23) -> Exclusion|6
A24: Exclusion | B24: Yes | C24: Aluminum storefront, curtain wall, and associated door hardware | D24: =IF(AND(B24="Yes",LEN(C24)>0),COUNTIFS($A$5:A24,A24,$B$5:B24,"Yes",$C$5:C24,"?*"),"") -> 7 | E24: =IF(D24="","",A24&"|"&D24) -> Exclusion|7
A25: Exclusion | B25: Yes | C25: Glass and glazing for hollow metal doors and frames unless listed | D25: =IF(AND(B25="Yes",LEN(C25)>0),COUNTIFS($A$5:A25,A25,$B$5:B25,"Yes",$C$5:C25,"?*"),"") -> 8 | E25: =IF(D25="","",A25&"|"&D25) -> Exclusion|8
A26: Exclusion | B26: Yes | C26: Flashing, sealants, and weatherproofing for windows and doors | D26: =IF(AND(B26="Yes",LEN(C26)>0),COUNTIFS($A$5:A26,A26,$B$5:B26,"Yes",$C$5:C26,"?*"),"") -> 9 | E26: =IF(D26="","",A26&"|"&D26) -> Exclusion|9
A27: Exclusion | B27: Yes | C27: Painting, staining, caulking, and nail-hole fill (trim and doors are primed or prefinished as noted) | D27: =IF(AND(B27="Yes",LEN(C27)>0),COUNTIFS($A$5:A27,A27,$B$5:B27,"Yes",$C$5:C27,"?*"),"") -> 10 | E27: =IF(D27="","",A27&"|"&D27) -> Exclusion|10
A28: Exclusion | B28: Yes | C28: Wood blocking, backing, and framing | D28: =IF(AND(B28="Yes",LEN(C28)>0),COUNTIFS($A$5:A28,A28,$B$5:B28,"Yes",$C$5:C28,"?*"),"") -> 11 | E28: =IF(D28="","",A28&"|"&D28) -> Exclusion|11
A29: Exclusion | B29: Yes | C29: Grouting of hollow metal frames (material and labor) | D29: =IF(AND(B29="Yes",LEN(C29)>0),COUNTIFS($A$5:A29,A29,$B$5:B29,"Yes",$C$5:C29,"?*"),"") -> 12 | E29: =IF(D29="","",A29&"|"&D29) -> Exclusion|12
... A37: Exclusion | B37: Yes | C37: OCIP / CCIP insurance programs and related costs | D37: =IF(AND(B37="Yes",LEN(C37)>0),COUNTIFS($A$5:A37,A37,$B$5:B37,"Yes",$C$5:C37,"?*"),"") -> 20 | E37: =IF(D37="","",A37&"|"&D37) -> Exclusion|20
A38: Exclusion | B38: Yes | C38: =IF('Job Info'!$B$41="Yes","Bonds other than the payment and performance bond shown in the Proposal Summary","Payment and performance bonds") -> Payment and performance bonds | D38: =IF(AND(B38="Yes",LEN(C38)>0),COUNTIFS($A$5:A38,A38,$B$5:B38,"Yes",$C$5:C38,"?*"),"") -> 21 | E38: =IF(D38="","",A38&"|"&D38) -> Exclusion|21
A39: Exclusion | B39: Yes | C39: Builder's risk insurance, permits, inspection fees, and testing | D39: =IF(AND(B39="Yes",LEN(C39)>0),COUNTIFS($A$5:A39,A39,$B$5:B39,"Yes",$C$5:C39,"?*"),"") -> 22 | E39: =IF(D39="","",A39&"|"&D39) -> Exclusion|22
A40: Exclusion | B40: Yes | C40: Liquidated and consequential damages | D40: =IF(AND(B40="Yes",LEN(C40)>0),COUNTIFS($A$5:A40,A40,$B$5:B40,"Yes",$C$5:C40,"?*"),"") -> 23 | E40: =IF(D40="","",A40&"|"&D40) -> Exclusion|23
A41: Exclusion | B41: Yes | C41: Prevailing wage / Davis-Bacon labor rates unless stated | D41: =IF(AND(B41="Yes",LEN(C41)>0),COUNTIFS($A$5:A41,A41,$B$5:B41,"Yes",$C$5:C41,"?*"),"") -> 24 | E41: =IF(D41="","",A41&"|"&D41) -> Exclusion|24
A42: Exclusion | B42: Yes | C42: Attic stock and overage material | D42: =IF(AND(B42="Yes",LEN(C42)>0),COUNTIFS($A$5:A42,A42,$B$5:B42,"Yes",$C$5:C42,"?*"),"") -> 25 | E42: =IF(D42="","",A42&"|"&D42) -> Exclusion|25
A43: Exclusion | B43: Yes | C43: Protection of installed work from damage by other trades | D43: =IF(AND(B43="Yes",LEN(C43)>0),COUNTIFS($A$5:A43,A43,$B$5:B43,"Yes",$C$5:C43,"?*"),"") -> 26 | E43: =IF(D43="","",A43&"|"&D43) -> Exclusion|26
A44: Exclusion | B44: Yes | C44: Engineering, delegated design, and sealed shop drawings | D44: =IF(AND(B44="Yes",LEN(C44)>0),COUNTIFS($A$5:A44,A44,$B$5:B44,"Yes",$C$5:C44,"?*"),"") -> 27 | E44: =IF(D44="","",A44&"|"&D44) -> Exclusion|27
A45: Exclusion | B45: No | C45: Window blinds and window treatments | D45: =IF(AND(B45="Yes",LEN(C45)>0),COUNTIFS($A$5:A45,A45,$B$5:B45,"Yes",$C$5:C45,"?*"),"") | E45: =IF(D45="","",A45&"|"&D45)
A46: Exclusion | B46: No | C46: Postal boxes and mail kiosks | D46: =IF(AND(B46="Yes",LEN(C46)>0),COUNTIFS($A$5:A46,A46,$B$5:B46,"Yes",$C$5:C46,"?*"),"") | E46: =IF(D46="","",A46&"|"&D46)
A47: Exclusion | B47: No | C47: Wire shelving | D47: =IF(AND(B47="Yes",LEN(C47)>0),COUNTIFS($A$5:A47,A47,$B$5:B47,"Yes",$C$5:C47,"?*"),"") | E47: =IF(D47="","",A47&"|"&D47)
A48: Exclusion | B48: No | C48: Bath accessories | D48: =IF(AND(B48="Yes",LEN(C48)>0),COUNTIFS($A$5:A48,A48,$B$5:B48,"Yes",$C$5:C48,"?*"),"") | E48: =IF(D48="","",A48&"|"&D48)
A49: Exclusion | B49: No | C49: Fire extinguishers and cabinets | D49: =IF(AND(B49="Yes",LEN(C49)>0),COUNTIFS($A$5:A49,A49,$B$5:B49,"Yes",$C$5:C49,"?*"),"") | E49: =IF(D49="","",A49&"|"&D49)
A50: Exclusion | B50: No | D50: =IF(AND(B50="Yes",LEN(C50)>0),COUNTIFS($A$5:A50,A50,$B$5:B50,"Yes",$C$5:C50,"?*"),"") | E50: =IF(D50="","",A50&"|"&D50)
A51: Exclusion | B51: No | D51: =IF(AND(B51="Yes",LEN(C51)>0),COUNTIFS($A$5:A51,A51,$B$5:B51,"Yes",$C$5:C51,"?*"),"") | E51: =IF(D51="","",A51&"|"&D51)
A52: Exclusion | B52: No | D52: =IF(AND(B52="Yes",LEN(C52)>0),COUNTIFS($A$5:A52,A52,$B$5:B52,"Yes",$C$5:C52,"?*"),"") | E52: =IF(D52="","",A52&"|"&D52)
A53: Exclusion | B53: No | D53: =IF(AND(B53="Yes",LEN(C53)>0),COUNTIFS($A$5:A53,A53,$B$5:B53,"Yes",$C$5:C53,"?*"),"") | E53: =IF(D53="","",A53&"|"&D53)
A54: Qualification | B54: Yes | C54: ="This proposal is valid for "&'Job Info'!$B$43&" days from the proposal date." -> This proposal is valid for 30 days from the proposal date. | D54: =IF(AND(B54="Yes",LEN(C54)>0),COUNTIFS($A$5:A54,A54,$B$5:B54,"Yes",$C$5:C54,"?*"),"") -> 1 | E54: =IF(D54="","",A54&"|"&D54) -> Qualification|1
A55: Qualification | B55: Yes | C55: ="Pricing is based on an executed contract and approved submittals by "&IF('Job Info'!$B$45="","[date TBD]",TEXT('Job Info'!$B$45,"mmmm d, yyyy"))&", and substantial completion by "&IF('Job Info'!$B$46="","[date TBD]",TEXT('Job Info'!$B$46,"mmmm d, yyyy"))&". If the schedule moves past these dates, Four Corners may revise pricing." -> Pricing is based on an executed contract and approved submittals by [date TBD], and substantial completion by [date TBD]. If the schedule moves past these dates, Four Corners may revise pricing. | D55: =IF(AND(B55="Yes",LEN(C55)>0),COUNTIFS($A$5:A55,A55,$B$5:B55,"Yes",$C$5:C55,"?*"),"") -> 2 | E55: =IF(D55="","",A55&"|"&D55) -> Qualification|2
A56: Qualification | B56: Yes | C56: ="Material pricing reflects current market conditions. If a material cost goes up more than "&TEXT('Job Info'!$B$44,"0%")&" from proposal pricing before procurement, Four Corners will submit the increase to the GC with supporting documentation before ordering." -> Material pricing reflects current market conditions. If a material cost goes up more than 3% from proposal pricing before procurement, Four Corners will submit the increase to the GC with supporting documentation before ordering. | D56: =IF(AND(B56="Yes",LEN(C56)>0),COUNTIFS($A$5:A56,A56,$B$5:B56,"Yes",$C$5:C56,"?*"),"") -> 3 | E56: =IF(D56="","",A56&"|"&D56) -> Qualification|3
A57: Qualification | B57: Yes | C57: Lead times come from current manufacturer quotes and are confirmed at release. Special-order items need approved submittals and a written release before ordering, and can't be cancelled or returned once released. | D57: =IF(AND(B57="Yes",LEN(C57)>0),COUNTIFS($A$5:A57,A57,$B$5:B57,"Yes",$C$5:C57,"?*"),"") -> 4 | E57: =IF(D57="","",A57&"|"&D57) -> Qualification|4
A58: Qualification | B58: Yes | C58: ="Payment terms: "&'Job Info'!$B$47&". Retainage may not exceed "&TEXT('Job Info'!$B$48,"0%")&" and is released at substantial completion of our scope." -> Payment terms: Monthly progress billing, Net 30 from invoice date. Retainage may not exceed 5% and is released at substantial completion of our scope. | D58: =IF(AND(B58="Yes",LEN(C58)>0),COUNTIFS($A$5:A58,A58,$B$5:B58,"Yes",$C$5:C58,"?*"),"") -> 5 | E58: =IF(D58="","",A58&"|"&D58) -> Qualification|5
A59: Qualification | B59: Yes | C59: GC provides hoisting and material stocking for buildings over four stories, unless hoisting is listed in this proposal. | D59: =IF(AND(B59="Yes",LEN(C59)>0),COUNTIFS($A$5:A59,A59,$B$5:B59,"Yes",$C$5:C59,"?*"),"") -> 6 | E59: =IF(D59="","",A59&"|"&D59) -> Qualification|6
A60: Qualification | B60: Yes | C60: GC provides all-weather access and temporary roads to each building for deliveries. | D60: =IF(AND(B60="Yes",LEN(C60)>0),COUNTIFS($A$5:A60,A60,$B$5:B60,"Yes",$C$5:C60,"?*"),"") -> 7 | E60: =IF(D60="","",A60&"|"&D60) -> Qualification|7
A61: Qualification | B61: Yes | C61: GC provides secure, dry on-site storage. If on-site storage isn't available, storage charges will apply. | D61: =IF(AND(B61="Yes",LEN(C61)>0),COUNTIFS($A$5:A61,A61,$B$5:B61,"Yes",$C$5:C61,"?*"),"") -> 8 | E61: =IF(D61="","",A61&"|"&D61) -> Qualification|8
A62: Qualification | B62: Yes | C62: Work follows a mutually agreed construction schedule. Areas must be dried in, and conditioned where specified, before interior trim and doors are installed. | D62: =IF(AND(B62="Yes",LEN(C62)>0),COUNTIFS($A$5:A62,A62,$B$5:B62,"Yes",$C$5:C62,"?*"),"") -> 9 | E62: =IF(D62="","",A62&"|"&D62) -> Qualification|9
A63: Qualification | B63: Yes | C63: ="Pricing includes "&'Job Info'!$B$49&" mobilization(s) per building or phase for each scope. Extra mobilizations caused by others will be billed at "&TEXT('Job Info'!$B$50,"$#,##0")&" per trip." -> Pricing includes 2 mobilization(s) per building or phase for each scope. Extra mobilizations caused by others will be billed at $350 per trip. | D63: =IF(AND(B63="Yes",LEN(C63)>0),COUNTIFS($A$5:A63,A63,$B$5:B63,"Yes",$C$5:C63,"?*"),"") -> 10 | E63: =IF(D63="","",A63&"|"&D63) -> Qualification|10
A64: Qualification | B64: Yes | C64: Supervision is provided as needed; it's not full-time on site unless stated. | D64: =IF(AND(B64="Yes",LEN(C64)>0),COUNTIFS($A$5:A64,A64,$B$5:B64,"Yes",$C$5:C64,"?*"),"") -> 11 | E64: =IF(D64="","",A64&"|"&D64) -> Qualification|11
A65: Qualification | B65: Yes | C65: This is a lump-sum proposal, broken out by section for the GC's convenience. If less than the full scope is awarded, Four Corners may revise pricing. | D65: =IF(AND(B65="Yes",LEN(C65)>0),COUNTIFS($A$5:A65,A65,$B$5:B65,"Yes",$C$5:C65,"?*"),"") -> 12 | E65: =IF(D65="","",A65&"|"&D65) -> Qualification|12
A66: Qualification | B66: Yes | C66: Quantities are our takeoff from the documents provided and aren't guaranteed. Please review the attached Bid Summary and let us know right away about any discrepancy. Changes in quantity, scope, or product will be priced as a change order. | D66: =IF(AND(B66="Yes",LEN(C66)>0),COUNTIFS($A$5:A66,A66,$B$5:B66,"Yes",$C$5:C66,"?*"),"") -> 13 | E66: =IF(D66="","",A66&"|"&D66) -> Qualification|13
A67: Qualification | B67: Yes | C67: Where the drawings and specifications conflict, pricing is based on the product described in the attached Bid Summary. Please flag any conflict before award. | D67: =IF(AND(B67="Yes",LEN(C67)>0),COUNTIFS($A$5:A67,A67,$B$5:B67,"Yes",$C$5:C67,"?*"),"") -> 14 | E67: =IF(D67="","",A67&"|"&D67) -> Qualification|14
A68: Qualification | B68: Yes | C68: Fees for third-party payment management or compliance systems (such as Textura or GCPay) are not included. | D68: =IF(AND(B68="Yes",LEN(C68)>0),COUNTIFS($A$5:A68,A68,$B$5:B68,"Yes",$C$5:C68,"?*"),"") -> 15 | E68: =IF(D68="","",A68&"|"&D68) -> Qualification|15
A69: Qualification | B69: Yes | C69: Changes require a written change order signed by both parties before the work proceeds. | D69: =IF(AND(B69="Yes",LEN(C69)>0),COUNTIFS($A$5:A69,A69,$B$5:B69,"Yes",$C$5:C69,"?*"),"") -> 16 | E69: =IF(D69="","",A69&"|"&D69) -> Qualification|16
A70: Qualification | B70: Yes | C70: Back charges won't be accepted without prior written notice and an opportunity to correct. | D70: =IF(AND(B70="Yes",LEN(C70)>0),COUNTIFS($A$5:A70,A70,$B$5:B70,"Yes",$C$5:C70,"?*"),"") -> 17 | E70: =IF(D70="","",A70&"|"&D70) -> Qualification|17
A71: Qualification | B71: Yes | C71: Repairs to installed work damaged by other trades will be billed as extra work. | D71: =IF(AND(B71="Yes",LEN(C71)>0),COUNTIFS($A$5:A71,A71,$B$5:B71,"Yes",$C$5:C71,"?*"),"") -> 18 | E71: =IF(D71="","",A71&"|"&D71) -> Qualification|18
A72: Qualification | B72: Yes | C72: Manufacturer warranties apply to all products. Four Corners warrants its installation workmanship for one (1) year from substantial completion. | D72: =IF(AND(B72="Yes",LEN(C72)>0),COUNTIFS($A$5:A72,A72,$B$5:B72,"Yes",$C$5:C72,"?*"),"") -> 19 | E72: =IF(D72="","",A72&"|"&D72) -> Qualification|19
A73: Qualification | B73: Yes | C73: Four Corners carries standard insurance and will provide a certificate of insurance. Additional insured and waiver of subrogation are provided per a mutually agreed subcontract. | D73: =IF(AND(B73="Yes",LEN(C73)>0),COUNTIFS($A$5:A73,A73,$B$5:B73,"Yes",$C$5:C73,"?*"),"") -> 20 | E73: =IF(D73="","",A73&"|"&D73) -> Qualification|20
A74: Qualification | B74: No | D74: =IF(AND(B74="Yes",LEN(C74)>0),COUNTIFS($A$5:A74,A74,$B$5:B74,"Yes",$C$5:C74,"?*"),"") | E74: =IF(D74="","",A74&"|"&D74)
A75: Qualification | B75: No | D75: =IF(AND(B75="Yes",LEN(C75)>0),COUNTIFS($A$5:A75,A75,$B$5:B75,"Yes",$C$5:C75,"?*"),"") | E75: =IF(D75="","",A75&"|"&D75)
A76: Qualification | B76: No | D76: =IF(AND(B76="Yes",LEN(C76)>0),COUNTIFS($A$5:A76,A76,$B$5:B76,"Yes",$C$5:C76,"?*"),"") | E76: =IF(D76="","",A76&"|"&D76)
A77: Qualification | B77: No | D77: =IF(AND(B77="Yes",LEN(C77)>0),COUNTIFS($A$5:A77,A77,$B$5:B77,"Yes",$C$5:C77,"?*"),"") | E77: =IF(D77="","",A77&"|"&D77)
A78: Term | B78: Yes | C78: This proposal assumes Four Corners and the Customer can agree on contract terms. If the subcontract contains terms Four Corners can't accept, this proposal is null and void. | D78: =IF(AND(B78="Yes",LEN(C78)>0),COUNTIFS($A$5:A78,A78,$B$5:B78,"Yes",$C$5:C78,"?*"),"") -> 1 | E78: =IF(D78="","",A78&"|"&D78) -> Term|1
A79: Term | B79: Yes | C79: All work is subject to credit approval. Four Corners may decline any project for credit reasons. | D79: =IF(AND(B79="Yes",LEN(C79)>0),COUNTIFS($A$5:A79,A79,$B$5:B79,"Yes",$C$5:C79,"?*"),"") -> 2 | E79: =IF(D79="","",A79&"|"&D79) -> Term|2
A80: Term | B80: Yes | C80: Customer pays according to the Four Corners credit agreement, unless Four Corners accepts alternate terms in writing. | D80: =IF(AND(B80="Yes",LEN(C80)>0),COUNTIFS($A$5:A80,A80,$B$5:B80,"Yes",$C$5:C80,"?*"),"") -> 3 | E80: =IF(D80="","",A80&"|"&D80) -> Term|3
A81: Term | B81: Yes | C81: Past-due balances accrue a finance charge of 1.5% per month. Customer is responsible for collection costs and reasonable attorney's fees. | D81: =IF(AND(B81="Yes",LEN(C81)>0),COUNTIFS($A$5:A81,A81,$B$5:B81,"Yes",$C$5:C81,"?*"),"") -> 4 | E81: =IF(D81="","",A81&"|"&D81) -> Term|4
A82: Term | B82: Yes | C82: Customer is responsible for all permits and inspections required by local agencies. | D82: =IF(AND(B82="Yes",LEN(C82)>0),COUNTIFS($A$5:A82,A82,$B$5:B82,"Yes",$C$5:C82,"?*"),"") -> 5 | E82: =IF(D82="","",A82&"|"&D82) -> Term|5
A83: Term | B83: Yes | C83: If work can't start within a reasonable time of the projected start date, Four Corners may revise this proposal. | D83: =IF(AND(B83="Yes",LEN(C83)>0),COUNTIFS($A$5:A83,A83,$B$5:B83,"Yes",$C$5:C83,"?*"),"") -> 6 | E83: =IF(D83="","",A83&"|"&D83) -> Term|6
A84: Term | B84: Yes | C84: Four Corners keeps all lien rights under South Carolina law. | D84: =IF(AND(B84="Yes",LEN(C84)>0),COUNTIFS($A$5:A84,A84,$B$5:B84,"Yes",$C$5:C84,"?*"),"") -> 7 | E84: =IF(D84="","",A84&"|"&D84) -> Term|7
A85: Term | B85: No | D85: =IF(AND(B85="Yes",LEN(C85)>0),COUNTIFS($A$5:A85,A85,$B$5:B85,"Yes",$C$5:C85,"?*"),"") | E85: =IF(D85="","",A85&"|"&D85)
A86: Term | B86: No | D86: =IF(AND(B86="Yes",LEN(C86)>0),COUNTIFS($A$5:A86,A86,$B$5:B86,"Yes",$C$5:C86,"?*"),"") | E86: =IF(D86="","",A86&"|"&D86)
A87: Term | B87: No | D87: =IF(AND(B87="Yes",LEN(C87)>0),COUNTIFS($A$5:A87,A87,$B$5:B87,"Yes",$C$5:C87,"?*"),"") | E87: =IF(D87="","",A87&"|"&D87)
A88: Term | B88: No | D88: =IF(AND(B88="Yes",LEN(C88)>0),COUNTIFS($A$5:A88,A88,$B$5:B88,"Yes",$C$5:C88,"?*"),"") | E88: =IF(D88="","",A88&"|"&D88)

Sheet Proposal
A1: ='Job Info'!$B$5 -> Four Corners Building Supply
A2: ='Job Info'!$B$6&" | "&'Job Info'!$B$7&" | "&'Job Info'!$B$8&" | "&'Job Info'!$B$9 -> 4349 Corporate Road | North Charleston, SC 29405 | (843) 970-3812 | www.buildfcbs.com
A5: PROPOSAL
A7: To: | B7: ='Job Info'!$B$12&"" | D7: Date: | E7: =IF('Job Info'!$B$27="","",'Job Info'!$B$27)
A8: Attn: | B8: ='Job Info'!$B$13&"" | D8: Proposal #: | E8: ='Job Info'!$B$28&IF('Job Info'!$B$29&""="0",""," Rev "&'Job Info'!$B$29)
A9: Address: | B9: ='Job Info'!$B$14&"" | D9: From: | E9: ='Job Info'!$B$32&""
B10: ='Job Info'!$B$15&"" | D10: Phone: | E10: ='Job Info'!$B$33&""
A11: Phone: | B11: ='Job Info'!$B$16&"" | D11: Email: | E11: ='Job Info'!$B$34&""
A13: JOB NAME | D13: JOB # | E13: JOB ADDRESS
A14: ='Job Info'!$B$20&"" | D14: ='Job Info'!$B$21&"" | E14: ='Job Info'!$B$22&IF('Job Info'!$B$23="","",", "&'Job Info'!$B$23)
A16: PROPOSAL SUMMARY (BY CSI SECTION) | F16: AMOUNT
B17: =IF(1<=Lists!$J$2,INDEX(Lists!$B$2:$B$26,MATCH(1,Lists!$D$2:$D$26,0)),IF(1=Lists!$J$2+1,"Subtotal",IF(1=Lists!$J$2+2,Lists!$J$6,IF(1=Lists!$J$2+3,"BASE BID TOTAL","")))) -> 06 20 00 Interior Trim / Finish Carpentry | F17: =IF(1<=Lists!$J$2,INDEX(Lists!$C$2:$C$26,MATCH(1,Lists!$D$2:$D$26,0)),IF(1=Lists!$J$2+1,Lists!$J$3,IF(1=Lists!$J$2+2,Lists!$J$4,IF(1=Lists!$J$2+3,Lists!$J$5,"")))) -> 3269.7426
B18: =IF(2<=Lists!$J$2,INDEX(Lists!$B$2:$B$26,MATCH(2,Lists!$D$2:$D$26,0)),IF(2=Lists!$J$2+1,"Subtotal",IF(2=Lists!$J$2+2,Lists!$J$6,IF(2=Lists!$J$2+3,"BASE BID TOTAL","")))) -> 08 17 43 Interior Pre-Hung Doors | F18: =IF(2<=Lists!$J$2,INDEX(Lists!$C$2:$C$26,MATCH(2,Lists!$D$2:$D$26,0)),IF(2=Lists!$J$2+1,Lists!$J$3,IF(2=Lists!$J$2+2,Lists!$J$4,IF(2=Lists!$J$2+3,Lists!$J$5,"")))) -> 2695.1838
B19: =IF(3<=Lists!$J$2,INDEX(Lists!$B$2:$B$26,MATCH(3,Lists!$D$2:$D$26,0)),IF(3=Lists!$J$2+1,"Subtotal",IF(3=Lists!$J$2+2,Lists!$J$6,IF(3=Lists!$J$2+3,"BASE BID TOTAL","")))) -> 08 71 00 Door Hardware | F19: =IF(3<=Lists!$J$2,INDEX(Lists!$C$2:$C$26,MATCH(3,Lists!$D$2:$D$26,0)),IF(3=Lists!$J$2+1,Lists!$J$3,IF(3=Lists!$J$2+2,Lists!$J$4,IF(3=Lists!$J$2+3,Lists!$J$5,"")))) -> 363.82721
B20: =IF(4<=Lists!$J$2,INDEX(Lists!$B$2:$B$26,MATCH(4,Lists!$D$2:$D$26,0)),IF(4=Lists!$J$2+1,"Subtotal",IF(4=Lists!$J$2+2,Lists!$J$6,IF(4=Lists!$J$2+3,"BASE BID TOTAL","")))) -> Subtotal | F20: =IF(4<=Lists!$J$2,INDEX(Lists!$C$2:$C$26,MATCH(4,Lists!$D$2:$D$26,0)),IF(4=Lists!$J$2+1,Lists!$J$3,IF(4=Lists!$J$2+2,Lists!$J$4,IF(4=Lists!$J$2+3,Lists!$J$5,"")))) -> 6328.7537
B21: =IF(5<=Lists!$J$2,INDEX(Lists!$B$2:$B$26,MATCH(5,Lists!$D$2:$D$26,0)),IF(5=Lists!$J$2+1,"Subtotal",IF(5=Lists!$J$2+2,Lists!$J$6,IF(5=Lists!$J$2+3,"BASE BID TOTAL","")))) -> Payment & Performance Bond - Not Included | F21: =IF(5<=Lists!$J$2,INDEX(Lists!$C$2:$C$26,MATCH(5,Lists!$D$2:$D$26,0)),IF(5=Lists!$J$2+1,Lists!$J$3,IF(5=Lists!$J$2+2,Lists!$J$4,IF(5=Lists!$J$2+3,Lists!$J$5,"")))) -> 0
B22: =IF(6<=Lists!$J$2,INDEX(Lists!$B$2:$B$26,MATCH(6,Lists!$D$2:$D$26,0)),IF(6=Lists!$J$2+1,"Subtotal",IF(6=Lists!$J$2+2,Lists!$J$6,IF(6=Lists!$J$2+3,"BASE BID TOTAL","")))) -> BASE BID TOTAL | F22: =IF(6<=Lists!$J$2,INDEX(Lists!$C$2:$C$26,MATCH(6,Lists!$D$2:$D$26,0)),IF(6=Lists!$J$2+1,Lists!$J$3,IF(6=Lists!$J$2+2,Lists!$J$4,IF(6=Lists!$J$2+3,Lists!$J$5,"")))) -> 6328.7537
B23: =IF(7<=Lists!$J$2,INDEX(Lists!$B$2:$B$26,MATCH(7,Lists!$D$2:$D$26,0)),IF(7=Lists!$J$2+1,"Subtotal",IF(7=Lists!$J$2+2,Lists!$J$6,IF(7=Lists!$J$2+3,"BASE BID TOTAL","")))) | F23: =IF(7<=Lists!$J$2,INDEX(Lists!$C$2:$C$26,MATCH(7,Lists!$D$2:$D$26,0)),IF(7=Lists!$J$2+1,Lists!$J$3,IF(7=Lists!$J$2+2,Lists!$J$4,IF(7=Lists!$J$2+3,Lists!$J$5,""))))
B24: =IF(8<=Lists!$J$2,INDEX(Lists!$B$2:$B$26,MATCH(8,Lists!$D$2:$D$26,0)),IF(8=Lists!$J$2+1,"Subtotal",IF(8=Lists!$J$2+2,Lists!$J$6,IF(8=Lists!$J$2+3,"BASE BID TOTAL","")))) | F24: =IF(8<=Lists!$J$2,INDEX(Lists!$C$2:$C$26,MATCH(8,Lists!$D$2:$D$26,0)),IF(8=Lists!$J$2+1,Lists!$J$3,IF(8=Lists!$J$2+2,Lists!$J$4,IF(8=Lists!$J$2+3,Lists!$J$5,""))))
B25: =IF(9<=Lists!$J$2,INDEX(Lists!$B$2:$B$26,MATCH(9,Lists!$D$2:$D$26,0)),IF(9=Lists!$J$2+1,"Subtotal",IF(9=Lists!$J$2+2,Lists!$J$6,IF(9=Lists!$J$2+3,"BASE BID TOTAL","")))) | F25: =IF(9<=Lists!$J$2,INDEX(Lists!$C$2:$C$26,MATCH(9,Lists!$D$2:$D$26,0)),IF(9=Lists!$J$2+1,Lists!$J$3,IF(9=Lists!$J$2+2,Lists!$J$4,IF(9=Lists!$J$2+3,Lists!$J$5,""))))
B26: =IF(10<=Lists!$J$2,INDEX(Lists!$B$2:$B$26,MATCH(10,Lists!$D$2:$D$26,0)),IF(10=Lists!$J$2+1,"Subtotal",IF(10=Lists!$J$2+2,Lists!$J$6,IF(10=Lists!$J$2+3,"BASE BID TOTAL","")))) | F26: =IF(10<=Lists!$J$2,INDEX(Lists!$C$2:$C$26,MATCH(10,Lists!$D$2:$D$26,0)),IF(10=Lists!$J$2+1,Lists!$J$3,IF(10=Lists!$J$2+2,Lists!$J$4,IF(10=Lists!$J$2+3,Lists!$J$5,""))))
B27: =IF(11<=Lists!$J$2,INDEX(Lists!$B$2:$B$26,MATCH(11,Lists!$D$2:$D$26,0)),IF(11=Lists!$J$2+1,"Subtotal",IF(11=Lists!$J$2+2,Lists!$J$6,IF(11=Lists!$J$2+3,"BASE BID TOTAL","")))) | F27: =IF(11<=Lists!$J$2,INDEX(Lists!$C$2:$C$26,MATCH(11,Lists!$D$2:$D$26,0)),IF(11=Lists!$J$2+1,Lists!$J$3,IF(11=Lists!$J$2+2,Lists!$J$4,IF(11=Lists!$J$2+3,Lists!$J$5,""))))
B28: =IF(12<=Lists!$J$2,INDEX(Lists!$B$2:$B$26,MATCH(12,Lists!$D$2:$D$26,0)),IF(12=Lists!$J$2+1,"Subtotal",IF(12=Lists!$J$2+2,Lists!$J$6,IF(12=Lists!$J$2+3,"BASE BID TOTAL","")))) | F28: =IF(12<=Lists!$J$2,INDEX(Lists!$C$2:$C$26,MATCH(12,Lists!$D$2:$D$26,0)),IF(12=Lists!$J$2+1,Lists!$J$3,IF(12=Lists!$J$2+2,Lists!$J$4,IF(12=Lists!$J$2+3,Lists!$J$5,""))))
B29: =IF(13<=Lists!$J$2,INDEX(Lists!$B$2:$B$26,MATCH(13,Lists!$D$2:$D$26,0)),IF(13=Lists!$J$2+1,"Subtotal",IF(13=Lists!$J$2+2,Lists!$J$6,IF(13=Lists!$J$2+3,"BASE BID TOTAL","")))) | F29: =IF(13<=Lists!$J$2,INDEX(Lists!$C$2:$C$26,MATCH(13,Lists!$D$2:$D$26,0)),IF(13=Lists!$J$2+1,Lists!$J$3,IF(13=Lists!$J$2+2,Lists!$J$4,IF(13=Lists!$J$2+3,Lists!$J$5,""))))
B30: =IF(14<=Lists!$J$2,INDEX(Lists!$B$2:$B$26,MATCH(14,Lists!$D$2:$D$26,0)),IF(14=Lists!$J$2+1,"Subtotal",IF(14=Lists!$J$2+2,Lists!$J$6,IF(14=Lists!$J$2+3,"BASE BID TOTAL","")))) | F30: =IF(14<=Lists!$J$2,INDEX(Lists!$C$2:$C$26,MATCH(14,Lists!$D$2:$D$26,0)),IF(14=Lists!$J$2+1,Lists!$J$3,IF(14=Lists!$J$2+2,Lists!$J$4,IF(14=Lists!$J$2+3,Lists!$J$5,""))))
B31: =IF(15<=Lists!$J$2,INDEX(Lists!$B$2:$B$26,MATCH(15,Lists!$D$2:$D$26,0)),IF(15=Lists!$J$2+1,"Subtotal",IF(15=Lists!$J$2+2,Lists!$J$6,IF(15=Lists!$J$2+3,"BASE BID TOTAL","")))) | F31: =IF(15<=Lists!$J$2,INDEX(Lists!$C$2:$C$26,MATCH(15,Lists!$D$2:$D$26,0)),IF(15=Lists!$J$2+1,Lists!$J$3,IF(15=Lists!$J$2+2,Lists!$J$4,IF(15=Lists!$J$2+3,Lists!$J$5,""))))
B32: =IF(16<=Lists!$J$2,INDEX(Lists!$B$2:$B$26,MATCH(16,Lists!$D$2:$D$26,0)),IF(16=Lists!$J$2+1,"Subtotal",IF(16=Lists!$J$2+2,Lists!$J$6,IF(16=Lists!$J$2+3,"BASE BID TOTAL","")))) | F32: =IF(16<=Lists!$J$2,INDEX(Lists!$C$2:$C$26,MATCH(16,Lists!$D$2:$D$26,0)),IF(16=Lists!$J$2+1,Lists!$J$3,IF(16=Lists!$J$2+2,Lists!$J$4,IF(16=Lists!$J$2+3,Lists!$J$5,""))))
B33: =IF(17<=Lists!$J$2,INDEX(Lists!$B$2:$B$26,MATCH(17,Lists!$D$2:$D$26,0)),IF(17=Lists!$J$2+1,"Subtotal",IF(17=Lists!$J$2+2,Lists!$J$6,IF(17=Lists!$J$2+3,"BASE BID TOTAL","")))) | F33: =IF(17<=Lists!$J$2,INDEX(Lists!$C$2:$C$26,MATCH(17,Lists!$D$2:$D$26,0)),IF(17=Lists!$J$2+1,Lists!$J$3,IF(17=Lists!$J$2+2,Lists!$J$4,IF(17=Lists!$J$2+3,Lists!$J$5,""))))
B34: =IF(18<=Lists!$J$2,INDEX(Lists!$B$2:$B$26,MATCH(18,Lists!$D$2:$D$26,0)),IF(18=Lists!$J$2+1,"Subtotal",IF(18=Lists!$J$2+2,Lists!$J$6,IF(18=Lists!$J$2+3,"BASE BID TOTAL","")))) | F34: =IF(18<=Lists!$J$2,INDEX(Lists!$C$2:$C$26,MATCH(18,Lists!$D$2:$D$26,0)),IF(18=Lists!$J$2+1,Lists!$J$3,IF(18=Lists!$J$2+2,Lists!$J$4,IF(18=Lists!$J$2+3,Lists!$J$5,""))))
B35: =IF(19<=Lists!$J$2,INDEX(Lists!$B$2:$B$26,MATCH(19,Lists!$D$2:$D$26,0)),IF(19=Lists!$J$2+1,"Subtotal",IF(19=Lists!$J$2+2,Lists!$J$6,IF(19=Lists!$J$2+3,"BASE BID TOTAL","")))) | F35: =IF(19<=Lists!$J$2,INDEX(Lists!$C$2:$C$26,MATCH(19,Lists!$D$2:$D$26,0)),IF(19=Lists!$J$2+1,Lists!$J$3,IF(19=Lists!$J$2+2,Lists!$J$4,IF(19=Lists!$J$2+3,Lists!$J$5,""))))
A38: ALTERNATES & OPTIONS (NOT INCLUDED IN BASE BID) | F38: ADD / (DEDUCT)
A39: =IF(OR(Alternates!$B$5<>"",Alternates!$C$5<>0),Alternates!$A$5,"") -> Alt 1 | B39: =IF(OR(Alternates!$B$5<>"",Alternates!$C$5<>0),Alternates!$B$5&"","") -> Battery-powered keypad deadbolts at unit entries in lieu of keyed deadbolts (EXAMPLE) | F39: =IF(OR(Alternates!$B$5<>"",Alternates!$C$5<>0),Alternates!$C$5,"") -> 3564.1176
A40: =IF(OR(Alternates!$B$6<>"",Alternates!$C$6<>0),Alternates!$A$6,"") | B40: =IF(OR(Alternates!$B$6<>"",Alternates!$C$6<>0),Alternates!$B$6&"","") | F40: =IF(OR(Alternates!$B$6<>"",Alternates!$C$6<>0),Alternates!$C$6,"")
A41: =IF(OR(Alternates!$B$7<>"",Alternates!$C$7<>0),Alternates!$A$7,"") | B41: =IF(OR(Alternates!$B$7<>"",Alternates!$C$7<>0),Alternates!$B$7&"","") | F41: =IF(OR(Alternates!$B$7<>"",Alternates!$C$7<>0),Alternates!$C$7,"")
A42: =IF(OR(Alternates!$B$8<>"",Alternates!$C$8<>0),Alternates!$A$8,"") | B42: =IF(OR(Alternates!$B$8<>"",Alternates!$C$8<>0),Alternates!$B$8&"","") | F42: =IF(OR(Alternates!$B$8<>"",Alternates!$C$8<>0),Alternates!$C$8,"")
A43: =IF(OR(Alternates!$B$9<>"",Alternates!$C$9<>0),Alternates!$A$9,"") | B43: =IF(OR(Alternates!$B$9<>"",Alternates!$C$9<>0),Alternates!$B$9&"","") | F43: =IF(OR(Alternates!$B$9<>"",Alternates!$C$9<>0),Alternates!$C$9,"")
A44: =IF(Alternates!$C$11<>0,Alternates!$A$11,"") | B44: =IF(Alternates!$C$11<>0,Alternates!$B$11&"","") | F44: =IF(Alternates!$C$11<>0,Alternates!$C$11,"")
A46: ='Job Info'!$B$5&" is pleased to present this proposal for "&IF('Job Info'!$B$20="","[Job Name]",'Job Info'!$B$20)&", based on plans and specifications dated "&IF('Job Info'!$B$25="","[date TBD]",TEXT('Job Info'!$B$25,"mmmm d, yyyy"))&", subject to the inclusions, exclusions, qualifications, and terms below. The attached Bid Summary is part of this proposal." -> Four Corners Building Supply is pleased to present this proposal for [Job Name], based on plans and specifications dated [date TBD], subject to the inclusions, exclusions, qualifications, and terms below. The attached Bid Summary is part of this proposal.
A48: INCLUSIONS
A49: =IF(ISNA(MATCH("Inclusion|1",'Scope Terms'!$E$5:$E$88,0)),"",1&".") -> 1. | B49: =IFERROR(INDEX('Scope Terms'!$C$5:$C$88,MATCH("Inclusion|1",'Scope Terms'!$E$5:$E$88,0)),"") -> All items listed in the attached Bid Summary, which is part of this proposal.
A50: =IF(ISNA(MATCH("Inclusion|2",'Scope Terms'!$E$5:$E$88,0)),"",2&".") -> 2. | B50: =IFERROR(INDEX('Scope Terms'!$C$5:$C$88,MATCH("Inclusion|2",'Scope Terms'!$E$5:$E$88,0)),"") -> All material pricing includes 9.0% sales tax.
A51: =IF(ISNA(MATCH("Inclusion|3",'Scope Terms'!$E$5:$E$88,0)),"",3&".") -> 3. | B51: =IFERROR(INDEX('Scope Terms'!$C$5:$C$88,MATCH("Inclusion|3",'Scope Terms'!$E$5:$E$88,0)),"") -> Pricing is based on plans and specifications dated [date TBD], and addenda: None.
A52: =IF(ISNA(MATCH("Inclusion|4",'Scope Terms'!$E$5:$E$88,0)),"",4&".") -> 4. | B52: =IFERROR(INDEX('Scope Terms'!$C$5:$C$88,MATCH("Inclusion|4",'Scope Terms'!$E$5:$E$88,0)),"") -> Delivery of all materials to the jobsite, ground level, at each building.
A53: =IF(ISNA(MATCH("Inclusion|5",'Scope Terms'!$E$5:$E$88,0)),"",5&".") -> 5. | B53: =IFERROR(INDEX('Scope Terms'!$C$5:$C$88,MATCH("Inclusion|5",'Scope Terms'!$E$5:$E$88,0)),"") -> Installation labor for every line item that shows a labor price in the Bid Summary.
A54: =IF(ISNA(MATCH("Inclusion|6",'Scope Terms'!$E$5:$E$88,0)),"",6&".") -> 6. | B54: =IFERROR(INDEX('Scope Terms'!$C$5:$C$88,MATCH("Inclusion|6",'Scope Terms'!$E$5:$E$88,0)),"") -> Interior and exterior pre-hung doors with hinges installed and bored or prepped for the scheduled hardware.
A55: =IF(ISNA(MATCH("Inclusion|7",'Scope Terms'!$E$5:$E$88,0)),"",7&".") -> 7. | B55: =IFERROR(INDEX('Scope Terms'!$C$5:$C$88,MATCH("Inclusion|7",'Scope Terms'!$E$5:$E$88,0)),"") -> Fire-rated doors and frames with factory labels as scheduled.
A56: =IF(ISNA(MATCH("Inclusion|8",'Scope Terms'!$E$5:$E$88,0)),"",8&".") -> 8. | B56: =IFERROR(INDEX('Scope Terms'!$C$5:$C$88,MATCH("Inclusion|8",'Scope Terms'!$E$5:$E$88,0)),"") -> Product data, door and hardware schedules, and submittals; warranty and O&M documents at closeout.
A57: =IF(ISNA(MATCH("Inclusion|9",'Scope Terms'!$E$5:$E$88,0)),"",9&".") -> 9. | B57: =IFERROR(INDEX('Scope Terms'!$C$5:$C$88,MATCH("Inclusion|9",'Scope Terms'!$E$5:$E$88,0)),"") -> Removal of our packaging and debris to the GC-provided on-site dumpster.
A58: =IF(ISNA(MATCH("Inclusion|10",'Scope Terms'!$E$5:$E$88,0)),"",10&".") | B58: =IFERROR(INDEX('Scope Terms'!$C$5:$C$88,MATCH("Inclusion|10",'Scope Terms'!$E$5:$E$88,0)),"")
A59: =IF(ISNA(MATCH("Inclusion|11",'Scope Terms'!$E$5:$E$88,0)),"",11&".") | B59: =IFERROR(INDEX('Scope Terms'!$C$5:$C$88,MATCH("Inclusion|11",'Scope Terms'!$E$5:$E$88,0)),"")
A61: EXCLUSIONS
A62: =IF(ISNA(MATCH("Exclusion|1",'Scope Terms'!$E$5:$E$88,0)),"",1&".") -> 1. | B62: =IFERROR(INDEX('Scope Terms'!$C$5:$C$88,MATCH("Exclusion|1",'Scope Terms'!$E$5:$E$88,0)),"") -> Chair rail and crown moulding in units
A63: =IF(ISNA(MATCH("Exclusion|2",'Scope Terms'!$E$5:$E$88,0)),"",2&".") -> 2. | B63: =IFERROR(INDEX('Scope Terms'!$C$5:$C$88,MATCH("Exclusion|2",'Scope Terms'!$E$5:$E$88,0)),"") -> Cased openings and interior columns
A64: =IF(ISNA(MATCH("Exclusion|3",'Scope Terms'!$E$5:$E$88,0)),"",3&".") -> 3. | B64: =IFERROR(INDEX('Scope Terms'!$C$5:$C$88,MATCH("Exclusion|3",'Scope Terms'!$E$5:$E$88,0)),"") -> Cabinets, countertops, vanities, desks, and built-ins unless listed
A65: =IF(ISNA(MATCH("Exclusion|4",'Scope Terms'!$E$5:$E$88,0)),"",4&".") -> 4. | B65: =IFERROR(INDEX('Scope Terms'!$C$5:$C$88,MATCH("Exclusion|4",'Scope Terms'!$E$5:$E$88,0)),"") -> Stair parts and railings
A66: =IF(ISNA(MATCH("Exclusion|5",'Scope Terms'!$E$5:$E$88,0)),"",5&".") -> 5. | B66: =IFERROR(INDEX('Scope Terms'!$C$5:$C$88,MATCH("Exclusion|5",'Scope Terms'!$E$5:$E$88,0)),"") -> Toilet partitions, shower doors, and shower enclosures unless listed
A67: =IF(ISNA(MATCH("Exclusion|6",'Scope Terms'!$E$5:$E$88,0)),"",6&".") -> 6. | B67: =IFERROR(INDEX('Scope Terms'!$C$5:$C$88,MATCH("Exclusion|6",'Scope Terms'!$E$5:$E$88,0)),"") -> Garage doors, overhead doors, and draft-stop or attic access doors
A68: =IF(ISNA(MATCH("Exclusion|7",'Scope Terms'!$E$5:$E$88,0)),"",7&".") -> 7. | B68: =IFERROR(INDEX('Scope Terms'!$C$5:$C$88,MATCH("Exclusion|7",'Scope Terms'!$E$5:$E$88,0)),"") -> Aluminum storefront, curtain wall, and associated door hardware
A69: =IF(ISNA(MATCH("Exclusion|8",'Scope Terms'!$E$5:$E$88,0)),"",8&".") -> 8. | B69: =IFERROR(INDEX('Scope Terms'!$C$5:$C$88,MATCH("Exclusion|8",'Scope Terms'!$E$5:$E$88,0)),"") -> Glass and glazing for hollow metal doors and frames unless listed
A70: =IF(ISNA(MATCH("Exclusion|9",'Scope Terms'!$E$5:$E$88,0)),"",9&".") -> 9. | B70: =IFERROR(INDEX('Scope Terms'!$C$5:$C$88,MATCH("Exclusion|9",'Scope Terms'!$E$5:$E$88,0)),"") -> Flashing, sealants, and weatherproofing for windows and doors
A71: =IF(ISNA(MATCH("Exclusion|10",'Scope Terms'!$E$5:$E$88,0)),"",10&".") -> 10. | B71: =IFERROR(INDEX('Scope Terms'!$C$5:$C$88,MATCH("Exclusion|10",'Scope Terms'!$E$5:$E$88,0)),"") -> Painting, staining, caulking, and nail-hole fill (trim and doors are primed or prefinished as noted)
A72: =IF(ISNA(MATCH("Exclusion|11",'Scope Terms'!$E$5:$E$88,0)),"",11&".") -> 11. | B72: =IFERROR(INDEX('Scope Terms'!$C$5:$C$88,MATCH("Exclusion|11",'Scope Terms'!$E$5:$E$88,0)),"") -> Wood blocking, backing, and framing
A73: =IF(ISNA(MATCH("Exclusion|12",'Scope Terms'!$E$5:$E$88,0)),"",12&".") -> 12. | B73: =IFERROR(INDEX('Scope Terms'!$C$5:$C$88,MATCH("Exclusion|12",'Scope Terms'!$E$5:$E$88,0)),"") -> Grouting of hollow metal frames (material and labor)
A74: =IF(ISNA(MATCH("Exclusion|13",'Scope Terms'!$E$5:$E$88,0)),"",13&".") -> 13. | B74: =IFERROR(INDEX('Scope Terms'!$C$5:$C$88,MATCH("Exclusion|13",'Scope Terms'!$E$5:$E$88,0)),"") -> Electrified hardware, access control, power supplies, wiring, and low-voltage work (Division 28)
A75: =IF(ISNA(MATCH("Exclusion|14",'Scope Terms'!$E$5:$E$88,0)),"",14&".") -> 14. | B75: =IFERROR(INDEX('Scope Terms'!$C$5:$C$88,MATCH("Exclusion|14",'Scope Terms'!$E$5:$E$88,0)),"") -> Final keying, permanent cores, and master key systems unless listed
A76: =IF(ISNA(MATCH("Exclusion|15",'Scope Terms'!$E$5:$E$88,0)),"",15&".") -> 15. | B76: =IFERROR(INDEX('Scope Terms'!$C$5:$C$88,MATCH("Exclusion|15",'Scope Terms'!$E$5:$E$88,0)),"") -> Grab bars installed in tile or solid surface (price on request)
A77: =IF(ISNA(MATCH("Exclusion|16",'Scope Terms'!$E$5:$E$88,0)),"",16&".") -> 16. | B77: =IFERROR(INDEX('Scope Terms'!$C$5:$C$88,MATCH("Exclusion|16",'Scope Terms'!$E$5:$E$88,0)),"") -> Reclaimed or specialty-species wood trim unless listed
A78: =IF(ISNA(MATCH("Exclusion|17",'Scope Terms'!$E$5:$E$88,0)),"",17&".") -> 17. | B78: =IFERROR(INDEX('Scope Terms'!$C$5:$C$88,MATCH("Exclusion|17",'Scope Terms'!$E$5:$E$88,0)),"") -> Hoisting and stocking above ground level unless listed under 01 54 16
A79: =IF(ISNA(MATCH("Exclusion|18",'Scope Terms'!$E$5:$E$88,0)),"",18&".") -> 18. | B79: =IFERROR(INDEX('Scope Terms'!$C$5:$C$88,MATCH("Exclusion|18",'Scope Terms'!$E$5:$E$88,0)),"") -> Off-site trash removal and dumpsters
A80: =IF(ISNA(MATCH("Exclusion|19",'Scope Terms'!$E$5:$E$88,0)),"",19&".") -> 19. | B80: =IFERROR(INDEX('Scope Terms'!$C$5:$C$88,MATCH("Exclusion|19",'Scope Terms'!$E$5:$E$88,0)),"") -> Composite clean-up participation and clean-up back charges
A81: =IF(ISNA(MATCH("Exclusion|20",'Scope Terms'!$E$5:$E$88,0)),"",20&".") -> 20. | B81: =IFERROR(INDEX('Scope Terms'!$C$5:$C$88,MATCH("Exclusion|20",'Scope Terms'!$E$5:$E$88,0)),"") -> OCIP / CCIP insurance programs and related costs
A82: =IF(ISNA(MATCH("Exclusion|21",'Scope Terms'!$E$5:$E$88,0)),"",21&".") -> 21. | B82: =IFERROR(INDEX('Scope Terms'!$C$5:$C$88,MATCH("Exclusion|21",'Scope Terms'!$E$5:$E$88,0)),"") -> Payment and performance bonds
A83: =IF(ISNA(MATCH("Exclusion|22",'Scope Terms'!$E$5:$E$88,0)),"",22&".") -> 22. | B83: =IFERROR(INDEX('Scope Terms'!$C$5:$C$88,MATCH("Exclusion|22",'Scope Terms'!$E$5:$E$88,0)),"") -> Builder's risk insurance, permits, inspection fees, and testing
A84: =IF(ISNA(MATCH("Exclusion|23",'Scope Terms'!$E$5:$E$88,0)),"",23&".") -> 23. | B84: =IFERROR(INDEX('Scope Terms'!$C$5:$C$88,MATCH("Exclusion|23",'Scope Terms'!$E$5:$E$88,0)),"") -> Liquidated and consequential damages
A85: =IF(ISNA(MATCH("Exclusion|24",'Scope Terms'!$E$5:$E$88,0)),"",24&".") -> 24. | B85: =IFERROR(INDEX('Scope Terms'!$C$5:$C$88,MATCH("Exclusion|24",'Scope Terms'!$E$5:$E$88,0)),"") -> Prevailing wage / Davis-Bacon labor rates unless stated
A86: =IF(ISNA(MATCH("Exclusion|25",'Scope Terms'!$E$5:$E$88,0)),"",25&".") -> 25. | B86: =IFERROR(INDEX('Scope Terms'!$C$5:$C$88,MATCH("Exclusion|25",'Scope Terms'!$E$5:$E$88,0)),"") -> Attic stock and overage material
A87: =IF(ISNA(MATCH("Exclusion|26",'Scope Terms'!$E$5:$E$88,0)),"",26&".") -> 26. | B87: =IFERROR(INDEX('Scope Terms'!$C$5:$C$88,MATCH("Exclusion|26",'Scope Terms'!$E$5:$E$88,0)),"") -> Protection of installed work from damage by other trades
A88: =IF(ISNA(MATCH("Exclusion|27",'Scope Terms'!$E$5:$E$88,0)),"",27&".") -> 27. | B88: =IFERROR(INDEX('Scope Terms'!$C$5:$C$88,MATCH("Exclusion|27",'Scope Terms'!$E$5:$E$88,0)),"") -> Engineering, delegated design, and sealed shop drawings
A89: =IF(ISNA(MATCH("Exclusion|28",'Scope Terms'!$E$5:$E$88,0)),"",28&".") | B89: =IFERROR(INDEX('Scope Terms'!$C$5:$C$88,MATCH("Exclusion|28",'Scope Terms'!$E$5:$E$88,0)),"")
A90: =IF(ISNA(MATCH("Exclusion|29",'Scope Terms'!$E$5:$E$88,0)),"",29&".") | B90: =IFERROR(INDEX('Scope Terms'!$C$5:$C$88,MATCH("Exclusion|29",'Scope Terms'!$E$5:$E$88,0)),"")
A91: =IF(ISNA(MATCH("Exclusion|30",'Scope Terms'!$E$5:$E$88,0)),"",30&".") | B91: =IFERROR(INDEX('Scope Terms'!$C$5:$C$88,MATCH("Exclusion|30",'Scope Terms'!$E$5:$E$88,0)),"")
A92: =IF(ISNA(MATCH("Exclusion|31",'Scope Terms'!$E$5:$E$88,0)),"",31&".") | B92: =IFERROR(INDEX('Scope Terms'!$C$5:$C$88,MATCH("Exclusion|31",'Scope Terms'!$E$5:$E$88,0)),"")
A93: =IF(ISNA(MATCH("Exclusion|32",'Scope Terms'!$E$5:$E$88,0)),"",32&".") | B93: =IFERROR(INDEX('Scope Terms'!$C$5:$C$88,MATCH("Exclusion|32",'Scope Terms'!$E$5:$E$88,0)),"")
A94: =IF(ISNA(MATCH("Exclusion|33",'Scope Terms'!$E$5:$E$88,0)),"",33&".") | B94: =IFERROR(INDEX('Scope Terms'!$C$5:$C$88,MATCH("Exclusion|33",'Scope Terms'!$E$5:$E$88,0)),"")
A95: =IF(ISNA(MATCH("Exclusion|34",'Scope Terms'!$E$5:$E$88,0)),"",34&".") | B95: =IFERROR(INDEX('Scope Terms'!$C$5:$C$88,MATCH("Exclusion|34",'Scope Terms'!$E$5:$E$88,0)),"")
A97: QUALIFICATIONS
A98: =IF(ISNA(MATCH("Qualification|1",'Scope Terms'!$E$5:$E$88,0)),"",1&".") -> 1. | B98: =IFERROR(INDEX('Scope Terms'!$C$5:$C$88,MATCH("Qualification|1",'Scope Terms'!$E$5:$E$88,0)),"") -> This proposal is valid for 30 days from the proposal date.
A99: =IF(ISNA(MATCH("Qualification|2",'Scope Terms'!$E$5:$E$88,0)),"",2&".") -> 2. | B99: =IFERROR(INDEX('Scope Terms'!$C$5:$C$88,MATCH("Qualification|2",'Scope Terms'!$E$5:$E$88,0)),"") -> Pricing is based on an executed contract and approved submittals by [date TBD], and substantial completion by [date TBD]. If the schedule moves past these dates, Four Corners may revise pricing.
A100: =IF(ISNA(MATCH("Qualification|3",'Scope Terms'!$E$5:$E$88,0)),"",3&".") -> 3. | B100: =IFERROR(INDEX('Scope Terms'!$C$5:$C$88,MATCH("Qualification|3",'Scope Terms'!$E$5:$E$88,0)),"") -> Material pricing reflects current market conditions. If a material cost goes up more than 3% from proposal pricing before procurement, Four Corners will submit the increase to the GC with supporting documentation before ordering.
A101: =IF(ISNA(MATCH("Qualification|4",'Scope Terms'!$E$5:$E$88,0)),"",4&".") -> 4. | B101: =IFERROR(INDEX('Scope Terms'!$C$5:$C$88,MATCH("Qualification|4",'Scope Terms'!$E$5:$E$88,0)),"") -> Lead times come from current manufacturer quotes and are confirmed at release. Special-order items need approved submittals and a written release before ordering, and can't be cancelled or returned once released.
A102: =IF(ISNA(MATCH("Qualification|5",'Scope Terms'!$E$5:$E$88,0)),"",5&".") -> 5. | B102: =IFERROR(INDEX('Scope Terms'!$C$5:$C$88,MATCH("Qualification|5",'Scope Terms'!$E$5:$E$88,0)),"") -> Payment terms: Monthly progress billing, Net 30 from invoice date. Retainage may not exceed 5% and is released at substantial completion of our scope.
A103: =IF(ISNA(MATCH("Qualification|6",'Scope Terms'!$E$5:$E$88,0)),"",6&".") -> 6. | B103: =IFERROR(INDEX('Scope Terms'!$C$5:$C$88,MATCH("Qualification|6",'Scope Terms'!$E$5:$E$88,0)),"") -> GC provides hoisting and material stocking for buildings over four stories, unless hoisting is listed in this proposal.
A104: =IF(ISNA(MATCH("Qualification|7",'Scope Terms'!$E$5:$E$88,0)),"",7&".") -> 7. | B104: =IFERROR(INDEX('Scope Terms'!$C$5:$C$88,MATCH("Qualification|7",'Scope Terms'!$E$5:$E$88,0)),"") -> GC provides all-weather access and temporary roads to each building for deliveries.
A105: =IF(ISNA(MATCH("Qualification|8",'Scope Terms'!$E$5:$E$88,0)),"",8&".") -> 8. | B105: =IFERROR(INDEX('Scope Terms'!$C$5:$C$88,MATCH("Qualification|8",'Scope Terms'!$E$5:$E$88,0)),"") -> GC provides secure, dry on-site storage. If on-site storage isn't available, storage charges will apply.
A106: =IF(ISNA(MATCH("Qualification|9",'Scope Terms'!$E$5:$E$88,0)),"",9&".") -> 9. | B106: =IFERROR(INDEX('Scope Terms'!$C$5:$C$88,MATCH("Qualification|9",'Scope Terms'!$E$5:$E$88,0)),"") -> Work follows a mutually agreed construction schedule. Areas must be dried in, and conditioned where specified, before interior trim and doors are installed.
A107: =IF(ISNA(MATCH("Qualification|10",'Scope Terms'!$E$5:$E$88,0)),"",10&".") -> 10. | B107: =IFERROR(INDEX('Scope Terms'!$C$5:$C$88,MATCH("Qualification|10",'Scope Terms'!$E$5:$E$88,0)),"") -> Pricing includes 2 mobilization(s) per building or phase for each scope. Extra mobilizations caused by others will be billed at $350 per trip.
A108: =IF(ISNA(MATCH("Qualification|11",'Scope Terms'!$E$5:$E$88,0)),"",11&".") -> 11. | B108: =IFERROR(INDEX('Scope Terms'!$C$5:$C$88,MATCH("Qualification|11",'Scope Terms'!$E$5:$E$88,0)),"") -> Supervision is provided as needed; it's not full-time on site unless stated.
A109: =IF(ISNA(MATCH("Qualification|12",'Scope Terms'!$E$5:$E$88,0)),"",12&".") -> 12. | B109: =IFERROR(INDEX('Scope Terms'!$C$5:$C$88,MATCH("Qualification|12",'Scope Terms'!$E$5:$E$88,0)),"") -> This is a lump-sum proposal, broken out by section for the GC's convenience. If less than the full scope is awarded, Four Corners may revise pricing.
A110: =IF(ISNA(MATCH("Qualification|13",'Scope Terms'!$E$5:$E$88,0)),"",13&".") -> 13. | B110: =IFERROR(INDEX('Scope Terms'!$C$5:$C$88,MATCH("Qualification|13",'Scope Terms'!$E$5:$E$88,0)),"") -> Quantities are our takeoff from the documents provided and aren't guaranteed. Please review the attached Bid Summary and let us know right away about any discrepancy. Changes in quantity, scope, or product will be priced as a change order.
A111: =IF(ISNA(MATCH("Qualification|14",'Scope Terms'!$E$5:$E$88,0)),"",14&".") -> 14. | B111: =IFERROR(INDEX('Scope Terms'!$C$5:$C$88,MATCH("Qualification|14",'Scope Terms'!$E$5:$E$88,0)),"") -> Where the drawings and specifications conflict, pricing is based on the product described in the attached Bid Summary. Please flag any conflict before award.
...

Sheet Area Breakout
A1: ='Job Info'!$B$5&" - AREA BREAKOUT" -> Four Corners Building Supply - AREA BREAKOUT
A2: ="Job: "&'Job Info'!$B$20&" | Proposal "&'Job Info'!$B$28&" | "&IF('Job Info'!$B$38="Yes",TEXT('Job Info'!$B$37,"0.0%")&" sales tax included in all material prices","Sales tax not included") -> Job: | Proposal | 9.0% sales tax included in all material prices
A3: Base bid only. This is a lump-sum bid, broken out for the GC's convenience.
A5: CSI SECTION | B5: =IF('Job Info'!$B$53="","",'Job Info'!$B$53) -> Units / Apartments | C5: =IF('Job Info'!$B$54="","",'Job Info'!$B$54) -> Clubhouse | D5: =IF('Job Info'!$B$55="","",'Job Info'!$B$55) -> Leasing / Amenity | E5: =IF('Job Info'!$B$56="","",'Job Info'!$B$56) -> Corridors / Common | F5: =IF('Job Info'!$B$57="","",'Job Info'!$B$57) -> Maintenance | G5: =IF('Job Info'!$B$58="","",'Job Info'!$B$58) -> Garages | H5: =IF('Job Info'!$B$59="","",'Job Info'!$B$59) -> Pool Cabana | I5: =IF('Job Info'!$B$60="","",'Job Info'!$B$60) | J5: Unassigned | K5: TOTAL
A6: =IFERROR(INDEX(Lists!$B$2:$B$26,MATCH(1,Lists!$D$2:$D$26,0)),"") -> 06 20 00 Interior Trim / Finish Carpentry | B6: =IF($A6="","",IF('Job Info'!$B$53="",0,SUMIFS('Line Detail'!$R$6:$R$505,'Line Detail'!$C$6:$C$505,$A6,'Line Detail'!$D$6:$D$505,'Job Info'!$B$53,'Line Detail'!$B$6:$B$505,"Base"))) -> 3269.7426 | C6: =IF($A6="","",IF('Job Info'!$B$54="",0,SUMIFS('Line Detail'!$R$6:$R$505,'Line Detail'!$C$6:$C$505,$A6,'Line Detail'!$D$6:$D$505,'Job Info'!$B$54,'Line Detail'!$B$6:$B$505,"Base"))) -> 0 | D6: =IF($A6="","",IF('Job Info'!$B$55="",0,SUMIFS('Line Detail'!$R$6:$R$505,'Line Detail'!$C$6:$C$505,$A6,'Line Detail'!$D$6:$D$505,'Job Info'!$B$55,'Line Detail'!$B$6:$B$505,"Base"))) -> 0 | E6: =IF($A6="","",IF('Job Info'!$B$56="",0,SUMIFS('Line Detail'!$R$6:$R$505,'Line Detail'!$C$6:$C$505,$A6,'Line Detail'!$D$6:$D$505,'Job Info'!$B$56,'Line Detail'!$B$6:$B$505,"Base"))) -> 0 | F6: =IF($A6="","",IF('Job Info'!$B$57="",0,SUMIFS('Line Detail'!$R$6:$R$505,'Line Detail'!$C$6:$C$505,$A6,'Line Detail'!$D$6:$D$505,'Job Info'!$B$57,'Line Detail'!$B$6:$B$505,"Base"))) -> 0 | G6: =IF($A6="","",IF('Job Info'!$B$58="",0,SUMIFS('Line Detail'!$R$6:$R$505,'Line Detail'!$C$6:$C$505,$A6,'Line Detail'!$D$6:$D$505,'Job Info'!$B$58,'Line Detail'!$B$6:$B$505,"Base"))) -> 0 | H6: =IF($A6="","",IF('Job Info'!$B$59="",0,SUMIFS('Line Detail'!$R$6:$R$505,'Line Detail'!$C$6:$C$505,$A6,'Line Detail'!$D$6:$D$505,'Job Info'!$B$59,'Line Detail'!$B$6:$B$505,"Base"))) -> 0 | I6: =IF($A6="","",IF('Job Info'!$B$60="",0,SUMIFS('Line Detail'!$R$6:$R$505,'Line Detail'!$C$6:$C$505,$A6,'Line Detail'!$D$6:$D$505,'Job Info'!$B$60,'Line Detail'!$B$6:$B$505,"Base"))) -> 0 | J6: =IF($A6="","",K6-SUM(B6:I6)) -> 0 | K6: =IFERROR(INDEX(Lists!$C$2:$C$26,MATCH(1,Lists!$D$2:$D$26,0)),"") -> 3269.7426
A7: =IFERROR(INDEX(Lists!$B$2:$B$26,MATCH(2,Lists!$D$2:$D$26,0)),"") -> 08 17 43 Interior Pre-Hung Doors | B7: =IF($A7="","",IF('Job Info'!$B$53="",0,SUMIFS('Line Detail'!$R$6:$R$505,'Line Detail'!$C$6:$C$505,$A7,'Line Detail'!$D$6:$D$505,'Job Info'!$B$53,'Line Detail'!$B$6:$B$505,"Base"))) -> 2695.1838 | C7: =IF($A7="","",IF('Job Info'!$B$54="",0,SUMIFS('Line Detail'!$R$6:$R$505,'Line Detail'!$C$6:$C$505,$A7,'Line Detail'!$D$6:$D$505,'Job Info'!$B$54,'Line Detail'!$B$6:$B$505,"Base"))) -> 0 | D7: =IF($A7="","",IF('Job Info'!$B$55="",0,SUMIFS('Line Detail'!$R$6:$R$505,'Line Detail'!$C$6:$C$505,$A7,'Line Detail'!$D$6:$D$505,'Job Info'!$B$55,'Line Detail'!$B$6:$B$505,"Base"))) -> 0 | E7: =IF($A7="","",IF('Job Info'!$B$56="",0,SUMIFS('Line Detail'!$R$6:$R$505,'Line Detail'!$C$6:$C$505,$A7,'Line Detail'!$D$6:$D$505,'Job Info'!$B$56,'Line Detail'!$B$6:$B$505,"Base"))) -> 0 | F7: =IF($A7="","",IF('Job Info'!$B$57="",0,SUMIFS('Line Detail'!$R$6:$R$505,'Line Detail'!$C$6:$C$505,$A7,'Line Detail'!$D$6:$D$505,'Job Info'!$B$57,'Line Detail'!$B$6:$B$505,"Base"))) -> 0 | G7: =IF($A7="","",IF('Job Info'!$B$58="",0,SUMIFS('Line Detail'!$R$6:$R$505,'Line Detail'!$C$6:$C$505,$A7,'Line Detail'!$D$6:$D$505,'Job Info'!$B$58,'Line Detail'!$B$6:$B$505,"Base"))) -> 0 | H7: =IF($A7="","",IF('Job Info'!$B$59="",0,SUMIFS('Line Detail'!$R$6:$R$505,'Line Detail'!$C$6:$C$505,$A7,'Line Detail'!$D$6:$D$505,'Job Info'!$B$59,'Line Detail'!$B$6:$B$505,"Base"))) -> 0 | I7: =IF($A7="","",IF('Job Info'!$B$60="",0,SUMIFS('Line Detail'!$R$6:$R$505,'Line Detail'!$C$6:$C$505,$A7,'Line Detail'!$D$6:$D$505,'Job Info'!$B$60,'Line Detail'!$B$6:$B$505,"Base"))) -> 0 | J7: =IF($A7="","",K7-SUM(B7:I7)) -> 0 | K7: =IFERROR(INDEX(Lists!$C$2:$C$26,MATCH(2,Lists!$D$2:$D$26,0)),"") -> 2695.1838
A8: =IFERROR(INDEX(Lists!$B$2:$B$26,MATCH(3,Lists!$D$2:$D$26,0)),"") -> 08 71 00 Door Hardware | B8: =IF($A8="","",IF('Job Info'!$B$53="",0,SUMIFS('Line Detail'!$R$6:$R$505,'Line Detail'!$C$6:$C$505,$A8,'Line Detail'!$D$6:$D$505,'Job Info'!$B$53,'Line Detail'!$B$6:$B$505,"Base"))) -> 363.82721 | C8: =IF($A8="","",IF('Job Info'!$B$54="",0,SUMIFS('Line Detail'!$R$6:$R$505,'Line Detail'!$C$6:$C$505,$A8,'Line Detail'!$D$6:$D$505,'Job Info'!$B$54,'Line Detail'!$B$6:$B$505,"Base"))) -> 0 | D8: =IF($A8="","",IF('Job Info'!$B$55="",0,SUMIFS('Line Detail'!$R$6:$R$505,'Line Detail'!$C$6:$C$505,$A8,'Line Detail'!$D$6:$D$505,'Job Info'!$B$55,'Line Detail'!$B$6:$B$505,"Base"))) -> 0 | E8: =IF($A8="","",IF('Job Info'!$B$56="",0,SUMIFS('Line Detail'!$R$6:$R$505,'Line Detail'!$C$6:$C$505,$A8,'Line Detail'!$D$6:$D$505,'Job Info'!$B$56,'Line Detail'!$B$6:$B$505,"Base"))) -> 0 | F8: =IF($A8="","",IF('Job Info'!$B$57="",0,SUMIFS('Line Detail'!$R$6:$R$505,'Line Detail'!$C$6:$C$505,$A8,'Line Detail'!$D$6:$D$505,'Job Info'!$B$57,'Line Detail'!$B$6:$B$505,"Base"))) -> 0 | G8: =IF($A8="","",IF('Job Info'!$B$58="",0,SUMIFS('Line Detail'!$R$6:$R$505,'Line Detail'!$C$6:$C$505,$A8,'Line Detail'!$D$6:$D$505,'Job Info'!$B$58,'Line Detail'!$B$6:$B$505,"Base"))) -> 0 | H8: =IF($A8="","",IF('Job Info'!$B$59="",0,SUMIFS('Line Detail'!$R$6:$R$505,'Line Detail'!$C$6:$C$505,$A8,'Line Detail'!$D$6:$D$505,'Job Info'!$B$59,'Line Detail'!$B$6:$B$505,"Base"))) -> 0 | I8: =IF($A8="","",IF('Job Info'!$B$60="",0,SUMIFS('Line Detail'!$R$6:$R$505,'Line Detail'!$C$6:$C$505,$A8,'Line Detail'!$D$6:$D$505,'Job Info'!$B$60,'Line Detail'!$B$6:$B$505,"Base"))) -> 0 | J8: =IF($A8="","",K8-SUM(B8:I8)) -> 0 | K8: =IFERROR(INDEX(Lists!$C$2:$C$26,MATCH(3,Lists!$D$2:$D$26,0)),"") -> 363.82721
A9: =IFERROR(INDEX(Lists!$B$2:$B$26,MATCH(4,Lists!$D$2:$D$26,0)),"") | B9: =IF($A9="","",IF('Job Info'!$B$53="",0,SUMIFS('Line Detail'!$R$6:$R$505,'Line Detail'!$C$6:$C$505,$A9,'Line Detail'!$D$6:$D$505,'Job Info'!$B$53,'Line Detail'!$B$6:$B$505,"Base"))) | C9: =IF($A9="","",IF('Job Info'!$B$54="",0,SUMIFS('Line Detail'!$R$6:$R$505,'Line Detail'!$C$6:$C$505,$A9,'Line Detail'!$D$6:$D$505,'Job Info'!$B$54,'Line Detail'!$B$6:$B$505,"Base"))) | D9: =IF($A9="","",IF('Job Info'!$B$55="",0,SUMIFS('Line Detail'!$R$6:$R$505,'Line Detail'!$C$6:$C$505,$A9,'Line Detail'!$D$6:$D$505,'Job Info'!$B$55,'Line Detail'!$B$6:$B$505,"Base"))) | E9: =IF($A9="","",IF('Job Info'!$B$56="",0,SUMIFS('Line Detail'!$R$6:$R$505,'Line Detail'!$C$6:$C$505,$A9,'Line Detail'!$D$6:$D$505,'Job Info'!$B$56,'Line Detail'!$B$6:$B$505,"Base"))) | F9: =IF($A9="","",IF('Job Info'!$B$57="",0,SUMIFS('Line Detail'!$R$6:$R$505,'Line Detail'!$C$6:$C$505,$A9,'Line Detail'!$D$6:$D$505,'Job Info'!$B$57,'Line Detail'!$B$6:$B$505,"Base"))) | G9: =IF($A9="","",IF('Job Info'!$B$58="",0,SUMIFS('Line Detail'!$R$6:$R$505,'Line Detail'!$C$6:$C$505,$A9,'Line Detail'!$D$6:$D$505,'Job Info'!$B$58,'Line Detail'!$B$6:$B$505,"Base"))) | H9: =IF($A9="","",IF('Job Info'!$B$59="",0,SUMIFS('Line Detail'!$R$6:$R$505,'Line Detail'!$C$6:$C$505,$A9,'Line Detail'!$D$6:$D$505,'Job Info'!$B$59,'Line Detail'!$B$6:$B$505,"Base"))) | I9: =IF($A9="","",IF('Job Info'!$B$60="",0,SUMIFS('Line Detail'!$R$6:$R$505,'Line Detail'!$C$6:$C$505,$A9,'Line Detail'!$D$6:$D$505,'Job Info'!$B$60,'Line Detail'!$B$6:$B$505,"Base"))) | J9: =IF($A9="","",K9-SUM(B9:I9)) | K9: =IFERROR(INDEX(Lists!$C$2:$C$26,MATCH(4,Lists!$D$2:$D$26,0)),"")
A10: =IFERROR(INDEX(Lists!$B$2:$B$26,MATCH(5,Lists!$D$2:$D$26,0)),"") | B10: =IF($A10="","",IF('Job Info'!$B$53="",0,SUMIFS('Line Detail'!$R$6:$R$505,'Line Detail'!$C$6:$C$505,$A10,'Line Detail'!$D$6:$D$505,'Job Info'!$B$53,'Line Detail'!$B$6:$B$505,"Base"))) | C10: =IF($A10="","",IF('Job Info'!$B$54="",0,SUMIFS('Line Detail'!$R$6:$R$505,'Line Detail'!$C$6:$C$505,$A10,'Line Detail'!$D$6:$D$505,'Job Info'!$B$54,'Line Detail'!$B$6:$B$505,"Base"))) | D10: =IF($A10="","",IF('Job Info'!$B$55="",0,SUMIFS('Line Detail'!$R$6:$R$505,'Line Detail'!$C$6:$C$505,$A10,'Line Detail'!$D$6:$D$505,'Job Info'!$B$55,'Line Detail'!$B$6:$B$505,"Base"))) | E10: =IF($A10="","",IF('Job Info'!$B$56="",0,SUMIFS('Line Detail'!$R$6:$R$505,'Line Detail'!$C$6:$C$505,$A10,'Line Detail'!$D$6:$D$505,'Job Info'!$B$56,'Line Detail'!$B$6:$B$505,"Base"))) | F10: =IF($A10="","",IF('Job Info'!$B$57="",0,SUMIFS('Line Detail'!$R$6:$R$505,'Line Detail'!$C$6:$C$505,$A10,'Line Detail'!$D$6:$D$505,'Job Info'!$B$57,'Line Detail'!$B$6:$B$505,"Base"))) | G10: =IF($A10="","",IF('Job Info'!$B$58="",0,SUMIFS('Line Detail'!$R$6:$R$505,'Line Detail'!$C$6:$C$505,$A10,'Line Detail'!$D$6:$D$505,'Job Info'!$B$58,'Line Detail'!$B$6:$B$505,"Base"))) | H10: =IF($A10="","",IF('Job Info'!$B$59="",0,SUMIFS('Line Detail'!$R$6:$R$505,'Line Detail'!$C$6:$C$505,$A10,'Line Detail'!$D$6:$D$505,'Job Info'!$B$59,'Line Detail'!$B$6:$B$505,"Base"))) | I10: =IF($A10="","",IF('Job Info'!$B$60="",0,SUMIFS('Line Detail'!$R$6:$R$505,'Line Detail'!$C$6:$C$505,$A10,'Line Detail'!$D$6:$D$505,'Job Info'!$B$60,'Line Detail'!$B$6:$B$505,"Base"))) | J10: =IF($A10="","",K10-SUM(B10:I10)) | K10: =IFERROR(INDEX(Lists!$C$2:$C$26,MATCH(5,Lists!$D$2:$D$26,0)),"")
A11: =IFERROR(INDEX(Lists!$B$2:$B$26,MATCH(6,Lists!$D$2:$D$26,0)),"") | B11: =IF($A11="","",IF('Job Info'!$B$53="",0,SUMIFS('Line Detail'!$R$6:$R$505,'Line Detail'!$C$6:$C$505,$A11,'Line Detail'!$D$6:$D$505,'Job Info'!$B$53,'Line Detail'!$B$6:$B$505,"Base"))) | C11: =IF($A11="","",IF('Job Info'!$B$54="",0,SUMIFS('Line Detail'!$R$6:$R$505,'Line Detail'!$C$6:$C$505,$A11,'Line Detail'!$D$6:$D$505,'Job Info'!$B$54,'Line Detail'!$B$6:$B$505,"Base"))) | D11: =IF($A11="","",IF('Job Info'!$B$55="",0,SUMIFS('Line Detail'!$R$6:$R$505,'Line Detail'!$C$6:$C$505,$A11,'Line Detail'!$D$6:$D$505,'Job Info'!$B$55,'Line Detail'!$B$6:$B$505,"Base"))) | E11: =IF($A11="","",IF('Job Info'!$B$56="",0,SUMIFS('Line Detail'!$R$6:$R$505,'Line Detail'!$C$6:$C$505,$A11,'Line Detail'!$D$6:$D$505,'Job Info'!$B$56,'Line Detail'!$B$6:$B$505,"Base"))) | F11: =IF($A11="","",IF('Job Info'!$B$57="",0,SUMIFS('Line Detail'!$R$6:$R$505,'Line Detail'!$C$6:$C$505,$A11,'Line Detail'!$D$6:$D$505,'Job Info'!$B$57,'Line Detail'!$B$6:$B$505,"Base"))) | G11: =IF($A11="","",IF('Job Info'!$B$58="",0,SUMIFS('Line Detail'!$R$6:$R$505,'Line Detail'!$C$6:$C$505,$A11,'Line Detail'!$D$6:$D$505,'Job Info'!$B$58,'Line Detail'!$B$6:$B$505,"Base"))) | H11: =IF($A11="","",IF('Job Info'!$B$59="",0,SUMIFS('Line Detail'!$R$6:$R$505,'Line Detail'!$C$6:$C$505,$A11,'Line Detail'!$D$6:$D$505,'Job Info'!$B$59,'Line Detail'!$B$6:$B$505,"Base"))) | I11: =IF($A11="","",IF('Job Info'!$B$60="",0,SUMIFS('Line Detail'!$R$6:$R$505,'Line Detail'!$C$6:$C$505,$A11,'Line Detail'!$D$6:$D$505,'Job Info'!$B$60,'Line Detail'!$B$6:$B$505,"Base"))) | J11: =IF($A11="","",K11-SUM(B11:I11)) | K11: =IFERROR(INDEX(Lists!$C$2:$C$26,MATCH(6,Lists!$D$2:$D$26,0)),"")
A12: =IFERROR(INDEX(Lists!$B$2:$B$26,MATCH(7,Lists!$D$2:$D$26,0)),"") | B12: =IF($A12="","",IF('Job Info'!$B$53="",0,SUMIFS('Line Detail'!$R$6:$R$505,'Line Detail'!$C$6:$C$505,$A12,'Line Detail'!$D$6:$D$505,'Job Info'!$B$53,'Line Detail'!$B$6:$B$505,"Base"))) | C12: =IF($A12="","",IF('Job Info'!$B$54="",0,SUMIFS('Line Detail'!$R$6:$R$505,'Line Detail'!$C$6:$C$505,$A12,'Line Detail'!$D$6:$D$505,'Job Info'!$B$54,'Line Detail'!$B$6:$B$505,"Base"))) | D12: =IF($A12="","",IF('Job Info'!$B$55="",0,SUMIFS('Line Detail'!$R$6:$R$505,'Line Detail'!$C$6:$C$505,$A12,'Line Detail'!$D$6:$D$505,'Job Info'!$B$55,'Line Detail'!$B$6:$B$505,"Base"))) | E12: =IF($A12="","",IF('Job Info'!$B$56="",0,SUMIFS('Line Detail'!$R$6:$R$505,'Line Detail'!$C$6:$C$505,$A12,'Line Detail'!$D$6:$D$505,'Job Info'!$B$56,'Line Detail'!$B$6:$B$505,"Base"))) | F12: =IF($A12="","",IF('Job Info'!$B$57="",0,SUMIFS('Line Detail'!$R$6:$R$505,'Line Detail'!$C$6:$C$505,$A12,'Line Detail'!$D$6:$D$505,'Job Info'!$B$57,'Line Detail'!$B$6:$B$505,"Base"))) | G12: =IF($A12="","",IF('Job Info'!$B$58="",0,SUMIFS('Line Detail'!$R$6:$R$505,'Line Detail'!$C$6:$C$505,$A12,'Line Detail'!$D$6:$D$505,'Job Info'!$B$58,'Line Detail'!$B$6:$B$505,"Base"))) | H12: =IF($A12="","",IF('Job Info'!$B$59="",0,SUMIFS('Line Detail'!$R$6:$R$505,'Line Detail'!$C$6:$C$505,$A12,'Line Detail'!$D$6:$D$505,'Job Info'!$B$59,'Line Detail'!$B$6:$B$505,"Base"))) | I12: =IF($A12="","",IF('Job Info'!$B$60="",0,SUMIFS('Line Detail'!$R$6:$R$505,'Line Detail'!$C$6:$C$505,$A12,'Line Detail'!$D$6:$D$505,'Job Info'!$B$60,'Line Detail'!$B$6:$B$505,"Base"))) | J12: =IF($A12="","",K12-SUM(B12:I12)) | K12: =IFERROR(INDEX(Lists!$C$2:$C$26,MATCH(7,Lists!$D$2:$D$26,0)),"")
A13: =IFERROR(INDEX(Lists!$B$2:$B$26,MATCH(8,Lists!$D$2:$D$26,0)),"") | B13: =IF($A13="","",IF('Job Info'!$B$53="",0,SUMIFS('Line Detail'!$R$6:$R$505,'Line Detail'!$C$6:$C$505,$A13,'Line Detail'!$D$6:$D$505,'Job Info'!$B$53,'Line Detail'!$B$6:$B$505,"Base"))) | C13: =IF($A13="","",IF('Job Info'!$B$54="",0,SUMIFS('Line Detail'!$R$6:$R$505,'Line Detail'!$C$6:$C$505,$A13,'Line Detail'!$D$6:$D$505,'Job Info'!$B$54,'Line Detail'!$B$6:$B$505,"Base"))) | D13: =IF($A13="","",IF('Job Info'!$B$55="",0,SUMIFS('Line Detail'!$R$6:$R$505,'Line Detail'!$C$6:$C$505,$A13,'Line Detail'!$D$6:$D$505,'Job Info'!$B$55,'Line Detail'!$B$6:$B$505,"Base"))) | E13: =IF($A13="","",IF('Job Info'!$B$56="",0,SUMIFS('Line Detail'!$R$6:$R$505,'Line Detail'!$C$6:$C$505,$A13,'Line Detail'!$D$6:$D$505,'Job Info'!$B$56,'Line Detail'!$B$6:$B$505,"Base"))) | F13: =IF($A13="","",IF('Job Info'!$B$57="",0,SUMIFS('Line Detail'!$R$6:$R$505,'Line Detail'!$C$6:$C$505,$A13,'Line Detail'!$D$6:$D$505,'Job Info'!$B$57,'Line Detail'!$B$6:$B$505,"Base"))) | G13: =IF($A13="","",IF('Job Info'!$B$58="",0,SUMIFS('Line Detail'!$R$6:$R$505,'Line Detail'!$C$6:$C$505,$A13,'Line Detail'!$D$6:$D$505,'Job Info'!$B$58,'Line Detail'!$B$6:$B$505,"Base"))) | H13: =IF($A13="","",IF('Job Info'!$B$59="",0,SUMIFS('Line Detail'!$R$6:$R$505,'Line Detail'!$C$6:$C$505,$A13,'Line Detail'!$D$6:$D$505,'Job Info'!$B$59,'Line Detail'!$B$6:$B$505,"Base"))) | I13: =IF($A13="","",IF('Job Info'!$B$60="",0,SUMIFS('Line Detail'!$R$6:$R$505,'Line Detail'!$C$6:$C$505,$A13,'Line Detail'!$D$6:$D$505,'Job Info'!$B$60,'Line Detail'!$B$6:$B$505,"Base"))) | J13: =IF($A13="","",K13-SUM(B13:I13)) | K13: =IFERROR(INDEX(Lists!$C$2:$C$26,MATCH(8,Lists!$D$2:$D$26,0)),"")
A14: =IFERROR(INDEX(Lists!$B$2:$B$26,MATCH(9,Lists!$D$2:$D$26,0)),"") | B14: =IF($A14="","",IF('Job Info'!$B$53="",0,SUMIFS('Line Detail'!$R$6:$R$505,'Line Detail'!$C$6:$C$505,$A14,'Line Detail'!$D$6:$D$505,'Job Info'!$B$53,'Line Detail'!$B$6:$B$505,"Base"))) | C14: =IF($A14="","",IF('Job Info'!$B$54="",0,SUMIFS('Line Detail'!$R$6:$R$505,'Line Detail'!$C$6:$C$505,$A14,'Line Detail'!$D$6:$D$505,'Job Info'!$B$54,'Line Detail'!$B$6:$B$505,"Base"))) | D14: =IF($A14="","",IF('Job Info'!$B$55="",0,SUMIFS('Line Detail'!$R$6:$R$505,'Line Detail'!$C$6:$C$505,$A14,'Line Detail'!$D$6:$D$505,'Job Info'!$B$55,'Line Detail'!$B$6:$B$505,"Base"))) | E14: =IF($A14="","",IF('Job Info'!$B$56="",0,SUMIFS('Line Detail'!$R$6:$R$505,'Line Detail'!$C$6:$C$505,$A14,'Line Detail'!$D$6:$D$505,'Job Info'!$B$56,'Line Detail'!$B$6:$B$505,"Base"))) | F14: =IF($A14="","",IF('Job Info'!$B$57="",0,SUMIFS('Line Detail'!$R$6:$R$505,'Line Detail'!$C$6:$C$505,$A14,'Line Detail'!$D$6:$D$505,'Job Info'!$B$57,'Line Detail'!$B$6:$B$505,"Base"))) | G14: =IF($A14="","",IF('Job Info'!$B$58="",0,SUMIFS('Line Detail'!$R$6:$R$505,'Line Detail'!$C$6:$C$505,$A14,'Line Detail'!$D$6:$D$505,'Job Info'!$B$58,'Line Detail'!$B$6:$B$505,"Base"))) | H14: =IF($A14="","",IF('Job Info'!$B$59="",0,SUMIFS('Line Detail'!$R$6:$R$505,'Line Detail'!$C$6:$C$505,$A14,'Line Detail'!$D$6:$D$505,'Job Info'!$B$59,'Line Detail'!$B$6:$B$505,"Base"))) | I14: =IF($A14="","",IF('Job Info'!$B$60="",0,SUMIFS('Line Detail'!$R$6:$R$505,'Line Detail'!$C$6:$C$505,$A14,'Line Detail'!$D$6:$D$505,'Job Info'!$B$60,'Line Detail'!$B$6:$B$505,"Base"))) | J14: =IF($A14="","",K14-SUM(B14:I14)) | K14: =IFERROR(INDEX(Lists!$C$2:$C$26,MATCH(9,Lists!$D$2:$D$26,0)),"")
A15: =IFERROR(INDEX(Lists!$B$2:$B$26,MATCH(10,Lists!$D$2:$D$26,0)),"") | B15: =IF($A15="","",IF('Job Info'!$B$53="",0,SUMIFS('Line Detail'!$R$6:$R$505,'Line Detail'!$C$6:$C$505,$A15,'Line Detail'!$D$6:$D$505,'Job Info'!$B$53,'Line Detail'!$B$6:$B$505,"Base"))) | C15: =IF($A15="","",IF('Job Info'!$B$54="",0,SUMIFS('Line Detail'!$R$6:$R$505,'Line Detail'!$C$6:$C$505,$A15,'Line Detail'!$D$6:$D$505,'Job Info'!$B$54,'Line Detail'!$B$6:$B$505,"Base"))) | D15: =IF($A15="","",IF('Job Info'!$B$55="",0,SUMIFS('Line Detail'!$R$6:$R$505,'Line Detail'!$C$6:$C$505,$A15,'Line Detail'!$D$6:$D$505,'Job Info'!$B$55,'Line Detail'!$B$6:$B$505,"Base"))) | E15: =IF($A15="","",IF('Job Info'!$B$56="",0,SUMIFS('Line Detail'!$R$6:$R$505,'Line Detail'!$C$6:$C$505,$A15,'Line Detail'!$D$6:$D$505,'Job Info'!$B$56,'Line Detail'!$B$6:$B$505,"Base"))) | F15: =IF($A15="","",IF('Job Info'!$B$57="",0,SUMIFS('Line Detail'!$R$6:$R$505,'Line Detail'!$C$6:$C$505,$A15,'Line Detail'!$D$6:$D$505,'Job Info'!$B$57,'Line Detail'!$B$6:$B$505,"Base"))) | G15: =IF($A15="","",IF('Job Info'!$B$58="",0,SUMIFS('Line Detail'!$R$6:$R$505,'Line Detail'!$C$6:$C$505,$A15,'Line Detail'!$D$6:$D$505,'Job Info'!$B$58,'Line Detail'!$B$6:$B$505,"Base"))) | H15: =IF($A15="","",IF('Job Info'!$B$59="",0,SUMIFS('Line Detail'!$R$6:$R$505,'Line Detail'!$C$6:$C$505,$A15,'Line Detail'!$D$6:$D$505,'Job Info'!$B$59,'Line Detail'!$B$6:$B$505,"Base"))) | I15: =IF($A15="","",IF('Job Info'!$B$60="",0,SUMIFS('Line Detail'!$R$6:$R$505,'Line Detail'!$C$6:$C$505,$A15,'Line Detail'!$D$6:$D$505,'Job Info'!$B$60,'Line Detail'!$B$6:$B$505,"Base"))) | J15: =IF($A15="","",K15-SUM(B15:I15)) | K15: =IFERROR(INDEX(Lists!$C$2:$C$26,MATCH(10,Lists!$D$2:$D$26,0)),"")
A16: =IFERROR(INDEX(Lists!$B$2:$B$26,MATCH(11,Lists!$D$2:$D$26,0)),"") | B16: =IF($A16="","",IF('Job Info'!$B$53="",0,SUMIFS('Line Detail'!$R$6:$R$505,'Line Detail'!$C$6:$C$505,$A16,'Line Detail'!$D$6:$D$505,'Job Info'!$B$53,'Line Detail'!$B$6:$B$505,"Base"))) | C16: =IF($A16="","",IF('Job Info'!$B$54="",0,SUMIFS('Line Detail'!$R$6:$R$505,'Line Detail'!$C$6:$C$505,$A16,'Line Detail'!$D$6:$D$505,'Job Info'!$B$54,'Line Detail'!$B$6:$B$505,"Base"))) | D16: =IF($A16="","",IF('Job Info'!$B$55="",0,SUMIFS('Line Detail'!$R$6:$R$505,'Line Detail'!$C$6:$C$505,$A16,'Line Detail'!$D$6:$D$505,'Job Info'!$B$55,'Line Detail'!$B$6:$B$505,"Base"))) | E16: =IF($A16="","",IF('Job Info'!$B$56="",0,SUMIFS('Line Detail'!$R$6:$R$505,'Line Detail'!$C$6:$C$505,$A16,'Line Detail'!$D$6:$D$505,'Job Info'!$B$56,'Line Detail'!$B$6:$B$505,"Base"))) | F16: =IF($A16="","",IF('Job Info'!$B$57="",0,SUMIFS('Line Detail'!$R$6:$R$505,'Line Detail'!$C$6:$C$505,$A16,'Line Detail'!$D$6:$D$505,'Job Info'!$B$57,'Line Detail'!$B$6:$B$505,"Base"))) | G16: =IF($A16="","",IF('Job Info'!$B$58="",0,SUMIFS('Line Detail'!$R$6:$R$505,'Line Detail'!$C$6:$C$505,$A16,'Line Detail'!$D$6:$D$505,'Job Info'!$B$58,'Line Detail'!$B$6:$B$505,"Base"))) | H16: =IF($A16="","",IF('Job Info'!$B$59="",0,SUMIFS('Line Detail'!$R$6:$R$505,'Line Detail'!$C$6:$C$505,$A16,'Line Detail'!$D$6:$D$505,'Job Info'!$B$59,'Line Detail'!$B$6:$B$505,"Base"))) | I16: =IF($A16="","",IF('Job Info'!$B$60="",0,SUMIFS('Line Detail'!$R$6:$R$505,'Line Detail'!$C$6:$C$505,$A16,'Line Detail'!$D$6:$D$505,'Job Info'!$B$60,'Line Detail'!$B$6:$B$505,"Base"))) | J16: =IF($A16="","",K16-SUM(B16:I16)) | K16: =IFERROR(INDEX(Lists!$C$2:$C$26,MATCH(11,Lists!$D$2:$D$26,0)),"")
A17: =IFERROR(INDEX(Lists!$B$2:$B$26,MATCH(12,Lists!$D$2:$D$26,0)),"") | B17: =IF($A17="","",IF('Job Info'!$B$53="",0,SUMIFS('Line Detail'!$R$6:$R$505,'Line Detail'!$C$6:$C$505,$A17,'Line Detail'!$D$6:$D$505,'Job Info'!$B$53,'Line Detail'!$B$6:$B$505,"Base"))) | C17: =IF($A17="","",IF('Job Info'!$B$54="",0,SUMIFS('Line Detail'!$R$6:$R$505,'Line Detail'!$C$6:$C$505,$A17,'Line Detail'!$D$6:$D$505,'Job Info'!$B$54,'Line Detail'!$B$6:$B$505,"Base"))) | D17: =IF($A17="","",IF('Job Info'!$B$55="",0,SUMIFS('Line Detail'!$R$6:$R$505,'Line Detail'!$C$6:$C$505,$A17,'Line Detail'!$D$6:$D$505,'Job Info'!$B$55,'Line Detail'!$B$6:$B$505,"Base"))) | E17: =IF($A17="","",IF('Job Info'!$B$56="",0,SUMIFS('Line Detail'!$R$6:$R$505,'Line Detail'!$C$6:$C$505,$A17,'Line Detail'!$D$6:$D$505,'Job Info'!$B$56,'Line Detail'!$B$6:$B$505,"Base"))) | F17: =IF($A17="","",IF('Job Info'!$B$57="",0,SUMIFS('Line Detail'!$R$6:$R$505,'Line Detail'!$C$6:$C$505,$A17,'Line Detail'!$D$6:$D$505,'Job Info'!$B$57,'Line Detail'!$B$6:$B$505,"Base"))) | G17: =IF($A17="","",IF('Job Info'!$B$58="",0,SUMIFS('Line Detail'!$R$6:$R$505,'Line Detail'!$C$6:$C$505,$A17,'Line Detail'!$D$6:$D$505,'Job Info'!$B$58,'Line Detail'!$B$6:$B$505,"Base"))) | H17: =IF($A17="","",IF('Job Info'!$B$59="",0,SUMIFS('Line Detail'!$R$6:$R$505,'Line Detail'!$C$6:$C$505,$A17,'Line Detail'!$D$6:$D$505,'Job Info'!$B$59,'Line Detail'!$B$6:$B$505,"Base"))) | I17: =IF($A17="","",IF('Job Info'!$B$60="",0,SUMIFS('Line Detail'!$R$6:$R$505,'Line Detail'!$C$6:$C$505,$A17,'Line Detail'!$D$6:$D$505,'Job Info'!$B$60,'Line Detail'!$B$6:$B$505,"Base"))) | J17: =IF($A17="","",K17-SUM(B17:I17)) | K17: =IFERROR(INDEX(Lists!$C$2:$C$26,MATCH(12,Lists!$D$2:$D$26,0)),"")
A18: =IFERROR(INDEX(Lists!$B$2:$B$26,MATCH(13,Lists!$D$2:$D$26,0)),"") | B18: =IF($A18="","",IF('Job Info'!$B$53="",0,SUMIFS('Line Detail'!$R$6:$R$505,'Line Detail'!$C$6:$C$505,$A18,'Line Detail'!$D$6:$D$505,'Job Info'!$B$53,'Line Detail'!$B$6:$B$505,"Base"))) | C18: =IF($A18="","",IF('Job Info'!$B$54="",0,SUMIFS('Line Detail'!$R$6:$R$505,'Line Detail'!$C$6:$C$505,$A18,'Line Detail'!$D$6:$D$505,'Job Info'!$B$54,'Line Detail'!$B$6:$B$505,"Base"))) | D18: =IF($A18="","",IF('Job Info'!$B$55="",0,SUMIFS('Line Detail'!$R$6:$R$505,'Line Detail'!$C$6:$C$505,$A18,'Line Detail'!$D$6:$D$505,'Job Info'!$B$55,'Line Detail'!$B$6:$B$505,"Base"))) | E18: =IF($A18="","",IF('Job Info'!$B$56="",0,SUMIFS('Line Detail'!$R$6:$R$505,'Line Detail'!$C$6:$C$505,$A18,'Line Detail'!$D$6:$D$505,'Job Info'!$B$56,'Line Detail'!$B$6:$B$505,"Base"))) | F18: =IF($A18="","",IF('Job Info'!$B$57="",0,SUMIFS('Line Detail'!$R$6:$R$505,'Line Detail'!$C$6:$C$505,$A18,'Line Detail'!$D$6:$D$505,'Job Info'!$B$57,'Line Detail'!$B$6:$B$505,"Base"))) | G18: =IF($A18="","",IF('Job Info'!$B$58="",0,SUMIFS('Line Detail'!$R$6:$R$505,'Line Detail'!$C$6:$C$505,$A18,'Line Detail'!$D$6:$D$505,'Job Info'!$B$58,'Line Detail'!$B$6:$B$505,"Base"))) | H18: =IF($A18="","",IF('Job Info'!$B$59="",0,SUMIFS('Line Detail'!$R$6:$R$505,'Line Detail'!$C$6:$C$505,$A18,'Line Detail'!$D$6:$D$505,'Job Info'!$B$59,'Line Detail'!$B$6:$B$505,"Base"))) | I18: =IF($A18="","",IF('Job Info'!$B$60="",0,SUMIFS('Line Detail'!$R$6:$R$505,'Line Detail'!$C$6:$C$505,$A18,'Line Detail'!$D$6:$D$505,'Job Info'!$B$60,'Line Detail'!$B$6:$B$505,"Base"))) | J18: =IF($A18="","",K18-SUM(B18:I18)) | K18: =IFERROR(INDEX(Lists!$C$2:$C$26,MATCH(13,Lists!$D$2:$D$26,0)),"")
A19: =IFERROR(INDEX(Lists!$B$2:$B$26,MATCH(14,Lists!$D$2:$D$26,0)),"") | B19: =IF($A19="","",IF('Job Info'!$B$53="",0,SUMIFS('Line Detail'!$R$6:$R$505,'Line Detail'!$C$6:$C$505,$A19,'Line Detail'!$D$6:$D$505,'Job Info'!$B$53,'Line Detail'!$B$6:$B$505,"Base"))) | C19: =IF($A19="","",IF('Job Info'!$B$54="",0,SUMIFS('Line Detail'!$R$6:$R$505,'Line Detail'!$C$6:$C$505,$A19,'Line Detail'!$D$6:$D$505,'Job Info'!$B$54,'Line Detail'!$B$6:$B$505,"Base"))) | D19: =IF($A19="","",IF('Job Info'!$B$55="",0,SUMIFS('Line Detail'!$R$6:$R$505,'Line Detail'!$C$6:$C$505,$A19,'Line Detail'!$D$6:$D$505,'Job Info'!$B$55,'Line Detail'!$B$6:$B$505,"Base"))) | E19: =IF($A19="","",IF('Job Info'!$B$56="",0,SUMIFS('Line Detail'!$R$6:$R$505,'Line Detail'!$C$6:$C$505,$A19,'Line Detail'!$D$6:$D$505,'Job Info'!$B$56,'Line Detail'!$B$6:$B$505,"Base"))) | F19: =IF($A19="","",IF('Job Info'!$B$57="",0,SUMIFS('Line Detail'!$R$6:$R$505,'Line Detail'!$C$6:$C$505,$A19,'Line Detail'!$D$6:$D$505,'Job Info'!$B$57,'Line Detail'!$B$6:$B$505,"Base"))) | G19: =IF($A19="","",IF('Job Info'!$B$58="",0,SUMIFS('Line Detail'!$R$6:$R$505,'Line Detail'!$C$6:$C$505,$A19,'Line Detail'!$D$6:$D$505,'Job Info'!$B$58,'Line Detail'!$B$6:$B$505,"Base"))) | H19: =IF($A19="","",IF('Job Info'!$B$59="",0,SUMIFS('Line Detail'!$R$6:$R$505,'Line Detail'!$C$6:$C$505,$A19,'Line Detail'!$D$6:$D$505,'Job Info'!$B$59,'Line Detail'!$B$6:$B$505,"Base"))) | I19: =IF($A19="","",IF('Job Info'!$B$60="",0,SUMIFS('Line Detail'!$R$6:$R$505,'Line Detail'!$C$6:$C$505,$A19,'Line Detail'!$D$6:$D$505,'Job Info'!$B$60,'Line Detail'!$B$6:$B$505,"Base"))) | J19: =IF($A19="","",K19-SUM(B19:I19)) | K19: =IFERROR(INDEX(Lists!$C$2:$C$26,MATCH(14,Lists!$D$2:$D$26,0)),"")
A20: =IFERROR(INDEX(Lists!$B$2:$B$26,MATCH(15,Lists!$D$2:$D$26,0)),"") | B20: =IF($A20="","",IF('Job Info'!$B$53="",0,SUMIFS('Line Detail'!$R$6:$R$505,'Line Detail'!$C$6:$C$505,$A20,'Line Detail'!$D$6:$D$505,'Job Info'!$B$53,'Line Detail'!$B$6:$B$505,"Base"))) | C20: =IF($A20="","",IF('Job Info'!$B$54="",0,SUMIFS('Line Detail'!$R$6:$R$505,'Line Detail'!$C$6:$C$505,$A20,'Line Detail'!$D$6:$D$505,'Job Info'!$B$54,'Line Detail'!$B$6:$B$505,"Base"))) | D20: =IF($A20="","",IF('Job Info'!$B$55="",0,SUMIFS('Line Detail'!$R$6:$R$505,'Line Detail'!$C$6:$C$505,$A20,'Line Detail'!$D$6:$D$505,'Job Info'!$B$55,'Line Detail'!$B$6:$B$505,"Base"))) | E20: =IF($A20="","",IF('Job Info'!$B$56="",0,SUMIFS('Line Detail'!$R$6:$R$505,'Line Detail'!$C$6:$C$505,$A20,'Line Detail'!$D$6:$D$505,'Job Info'!$B$56,'Line Detail'!$B$6:$B$505,"Base"))) | F20: =IF($A20="","",IF('Job Info'!$B$57="",0,SUMIFS('Line Detail'!$R$6:$R$505,'Line Detail'!$C$6:$C$505,$A20,'Line Detail'!$D$6:$D$505,'Job Info'!$B$57,'Line Detail'!$B$6:$B$505,"Base"))) | G20: =IF($A20="","",IF('Job Info'!$B$58="",0,SUMIFS('Line Detail'!$R$6:$R$505,'Line Detail'!$C$6:$C$505,$A20,'Line Detail'!$D$6:$D$505,'Job Info'!$B$58,'Line Detail'!$B$6:$B$505,"Base"))) | H20: =IF($A20="","",IF('Job Info'!$B$59="",0,SUMIFS('Line Detail'!$R$6:$R$505,'Line Detail'!$C$6:$C$505,$A20,'Line Detail'!$D$6:$D$505,'Job Info'!$B$59,'Line Detail'!$B$6:$B$505,"Base"))) | I20: =IF($A20="","",IF('Job Info'!$B$60="",0,SUMIFS('Line Detail'!$R$6:$R$505,'Line Detail'!$C$6:$C$505,$A20,'Line Detail'!$D$6:$D$505,'Job Info'!$B$60,'Line Detail'!$B$6:$B$505,"Base"))) | J20: =IF($A20="","",K20-SUM(B20:I20)) | K20: =IFERROR(INDEX(Lists!$C$2:$C$26,MATCH(15,Lists!$D$2:$D$26,0)),"")
A21: =IFERROR(INDEX(Lists!$B$2:$B$26,MATCH(16,Lists!$D$2:$D$26,0)),"") | B21: =IF($A21="","",IF('Job Info'!$B$53="",0,SUMIFS('Line Detail'!$R$6:$R$505,'Line Detail'!$C$6:$C$505,$A21,'Line Detail'!$D$6:$D$505,'Job Info'!$B$53,'Line Detail'!$B$6:$B$505,"Base"))) | C21: =IF($A21="","",IF('Job Info'!$B$54="",0,SUMIFS('Line Detail'!$R$6:$R$505,'Line Detail'!$C$6:$C$505,$A21,'Line Detail'!$D$6:$D$505,'Job Info'!$B$54,'Line Detail'!$B$6:$B$505,"Base"))) | D21: =IF($A21="","",IF('Job Info'!$B$55="",0,SUMIFS('Line Detail'!$R$6:$R$505,'Line Detail'!$C$6:$C$505,$A21,'Line Detail'!$D$6:$D$505,'Job Info'!$B$55,'Line Detail'!$B$6:$B$505,"Base"))) | E21: =IF($A21="","",IF('Job Info'!$B$56="",0,SUMIFS('Line Detail'!$R$6:$R$505,'Line Detail'!$C$6:$C$505,$A21,'Line Detail'!$D$6:$D$505,'Job Info'!$B$56,'Line Detail'!$B$6:$B$505,"Base"))) | F21: =IF($A21="","",IF('Job Info'!$B$57="",0,SUMIFS('Line Detail'!$R$6:$R$505,'Line Detail'!$C$6:$C$505,$A21,'Line Detail'!$D$6:$D$505,'Job Info'!$B$57,'Line Detail'!$B$6:$B$505,"Base"))) | G21: =IF($A21="","",IF('Job Info'!$B$58="",0,SUMIFS('Line Detail'!$R$6:$R$505,'Line Detail'!$C$6:$C$505,$A21,'Line Detail'!$D$6:$D$505,'Job Info'!$B$58,'Line Detail'!$B$6:$B$505,"Base"))) | H21: =IF($A21="","",IF('Job Info'!$B$59="",0,SUMIFS('Line Detail'!$R$6:$R$505,'Line Detail'!$C$6:$C$505,$A21,'Line Detail'!$D$6:$D$505,'Job Info'!$B$59,'Line Detail'!$B$6:$B$505,"Base"))) | I21: =IF($A21="","",IF('Job Info'!$B$60="",0,SUMIFS('Line Detail'!$R$6:$R$505,'Line Detail'!$C$6:$C$505,$A21,'Line Detail'!$D$6:$D$505,'Job Info'!$B$60,'Line Detail'!$B$6:$B$505,"Base"))) | J21: =IF($A21="","",K21-SUM(B21:I21)) | K21: =IFERROR(INDEX(Lists!$C$2:$C$26,MATCH(16,Lists!$D$2:$D$26,0)),"")
A22: TOTAL BY AREA | B22: =SUM(B6:B21) -> 6328.7537 | C22: =SUM(C6:C21) -> 0 | D22: =SUM(D6:D21) -> 0 | E22: =SUM(E6:E21) -> 0 | F22: =SUM(F6:F21) -> 0 | G22: =SUM(G6:G21) -> 0 | H22: =SUM(H6:H21) -> 0 | I22: =SUM(I6:I21) -> 0 | ... K22: =SUM(K6:K21) -> 6328.7537
A24: AREA | B24: MATERIAL | C24: LABOR | D24: TOTAL
A25: =IF('Job Info'!$B$53="","",'Job Info'!$B$53) -> Units / Apartments | B25: =IF('Job Info'!$B$53="",0,SUMIFS('Line Detail'!$P$6:$P$505,'Line Detail'!$D$6:$D$505,'Job Info'!$B$53,'Line Detail'!$B$6:$B$505,"Base")) -> 4475.8125 | C25: =IF('Job Info'!$B$53="",0,SUMIFS('Line Detail'!$Q$6:$Q$505,'Line Detail'!$D$6:$D$505,'Job Info'!$B$53,'Line Detail'!$B$6:$B$505,"Base")) -> 1852.9412 | D25: =B25+C25 -> 6328.7537
A26: =IF('Job Info'!$B$54="","",'Job Info'!$B$54) -> Clubhouse | B26: =IF('Job Info'!$B$54="",0,SUMIFS('Line Detail'!$P$6:$P$505,'Line Detail'!$D$6:$D$505,'Job Info'!$B$54,'Line Detail'!$B$6:$B$505,"Base")) -> 0 | C26: =IF('Job Info'!$B$54="",0,SUMIFS('Line Detail'!$Q$6:$Q$505,'Line Detail'!$D$6:$D$505,'Job Info'!$B$54,'Line Detail'!$B$6:$B$505,"Base")) -> 0 | D26: =B26+C26 -> 0
A27: =IF('Job Info'!$B$55="","",'Job Info'!$B$55) -> Leasing / Amenity | B27: =IF('Job Info'!$B$55="",0,SUMIFS('Line Detail'!$P$6:$P$505,'Line Detail'!$D$6:$D$505,'Job Info'!$B$55,'Line Detail'!$B$6:$B$505,"Base")) -> 0 | C27: =IF('Job Info'!$B$55="",0,SUMIFS('Line Detail'!$Q$6:$Q$505,'Line Detail'!$D$6:$D$505,'Job Info'!$B$55,'Line Detail'!$B$6:$B$505,"Base")) -> 0 | D27: =B27+C27 -> 0
A28: =IF('Job Info'!$B$56="","",'Job Info'!$B$56) -> Corridors / Common | B28: =IF('Job Info'!$B$56="",0,SUMIFS('Line Detail'!$P$6:$P$505,'Line Detail'!$D$6:$D$505,'Job Info'!$B$56,'Line Detail'!$B$6:$B$505,"Base")) -> 0 | C28: =IF('Job Info'!$B$56="",0,SUMIFS('Line Detail'!$Q$6:$Q$505,'Line Detail'!$D$6:$D$505,'Job Info'!$B$56,'Line Detail'!$B$6:$B$505,"Base")) -> 0 | D28: =B28+C28 -> 0
A29: =IF('Job Info'!$B$57="","",'Job Info'!$B$57) -> Maintenance | B29: =IF('Job Info'!$B$57="",0,SUMIFS('Line Detail'!$P$6:$P$505,'Line Detail'!$D$6:$D$505,'Job Info'!$B$57,'Line Detail'!$B$6:$B$505,"Base")) -> 0 | C29: =IF('Job Info'!$B$57="",0,SUMIFS('Line Detail'!$Q$6:$Q$505,'Line Detail'!$D$6:$D$505,'Job Info'!$B$57,'Line Detail'!$B$6:$B$505,"Base")) -> 0 | D29: =B29+C29 -> 0
A30: =IF('Job Info'!$B$58="","",'Job Info'!$B$58) -> Garages | B30: =IF('Job Info'!$B$58="",0,SUMIFS('Line Detail'!$P$6:$P$505,'Line Detail'!$D$6:$D$505,'Job Info'!$B$58,'Line Detail'!$B$6:$B$505,"Base")) -> 0 | C30: =IF('Job Info'!$B$58="",0,SUMIFS('Line Detail'!$Q$6:$Q$505,'Line Detail'!$D$6:$D$505,'Job Info'!$B$58,'Line Detail'!$B$6:$B$505,"Base")) -> 0 | D30: =B30+C30 -> 0
A31: =IF('Job Info'!$B$59="","",'Job Info'!$B$59) -> Pool Cabana | B31: =IF('Job Info'!$B$59="",0,SUMIFS('Line Detail'!$P$6:$P$505,'Line Detail'!$D$6:$D$505,'Job Info'!$B$59,'Line Detail'!$B$6:$B$505,"Base")) -> 0 | C31: =IF('Job Info'!$B$59="",0,SUMIFS('Line Detail'!$Q$6:$Q$505,'Line Detail'!$D$6:$D$505,'Job Info'!$B$59,'Line Detail'!$B$6:$B$505,"Base")) -> 0 | D31: =B31+C31 -> 0
A32: =IF('Job Info'!$B$60="","",'Job Info'!$B$60) | B32: =IF('Job Info'!$B$60="",0,SUMIFS('Line Detail'!$P$6:$P$505,'Line Detail'!$D$6:$D$505,'Job Info'!$B$60,'Line Detail'!$B$6:$B$505,"Base")) -> 0 | C32: =IF('Job Info'!$B$60="",0,SUMIFS('Line Detail'!$Q$6:$Q$505,'Line Detail'!$D$6:$D$505,'Job Info'!$B$60,'Line Detail'!$B$6:$B$505,"Base")) -> 0 | D32: =B32+C32 -> 0
A33: Unassigned / Misc. | B33: =SUMIFS('Line Detail'!$P$6:$P$505,'Line Detail'!$B$6:$B$505,"Base")-SUM(B25:B32) -> 0 | C33: =SUMIFS('Line Detail'!$Q$6:$Q$505,'Line Detail'!$B$6:$B$505,"Base")-SUM(C25:C32) -> 0 | D33: =B33+C33 -> 0
A34: JOB TOTALS (before bond) | B34: =SUM(B25:B33) -> 4475.8125 | C34: =SUM(C25:C33) -> 1852.9412 | D34: =SUM(D25:D33) -> 6328.7537

Sheet Bid Summary
A1: ='Job Info'!$B$5&" - BID SUMMARY" -> Four Corners Building Supply - BID SUMMARY
A2: ="Job: "&'Job Info'!$B$20&" | Proposal "&'Job Info'!$B$28&" | Plans dated "&IF('Job Info'!$B$25="","[date TBD]",TEXT('Job Info'!$B$25,"mmmm d, yyyy")) -> Job: | Proposal | Plans dated [date TBD]
A3: ="Part of the proposal. Unit prices include material"&IF('Job Info'!$B$38="Yes"," (with "&TEXT('Job Info'!$B$37,"0.0%")&" sales tax)","")&" and installation labor where applicable. Lines marked Alt or Optional are NOT in the base bid." -> Part of the proposal. Unit prices include material (with 9.0% sales tax) and installation labor where applicable. Lines marked Alt or Optional are NOT in the base bid.
A5: No. | B5: Group | C5: CSI Section | D5: Area | E5: Mark | F5: Description | G5: Qty | H5: UOM | I5: Unit Price | J5: Total Price | K5: Notes
A6: =IF($M6=0,"",1) -> 1 | B6: =IF($M6=0,"",IF(INDEX('Line Detail'!$B$6:$B$505,$M6)="","",INDEX('Line Detail'!$B$6:$B$505,$M6))) -> Base | C6: =IF($M6=0,"",IF(INDEX('Line Detail'!$C$6:$C$505,$M6)="","",INDEX('Line Detail'!$C$6:$C$505,$M6))) -> 06 20 00 Interior Trim / Finish Carpentry | D6: =IF($M6=0,"",IF(INDEX('Line Detail'!$D$6:$D$505,$M6)="","",INDEX('Line Detail'!$D$6:$D$505,$M6))) -> Units / Apartments | E6: =IF($M6=0,"",IF(INDEX('Line Detail'!$E$6:$E$505,$M6)="","",INDEX('Line Detail'!$E$6:$E$505,$M6))) | F6: =IF($M6=0,"",IF(INDEX('Line Detail'!$F$6:$F$505,$M6)="","",INDEX('Line Detail'!$F$6:$F$505,$M6))) -> Base FJ Primed 1x6 | G6: =IF($M6=0,"",IF(INDEX('Line Detail'!$G$6:$G$505,$M6)="","",INDEX('Line Detail'!$G$6:$G$505,$M6))) -> 1000 | H6: =IF($M6=0,"",IF(INDEX('Line Detail'!$H$6:$H$505,$M6)="","",INDEX('Line Detail'!$H$6:$H$505,$M6))) -> LF | I6: =IF($M6=0,"",IF(INDEX('Line Detail'!$O$6:$O$505,$M6)="","",INDEX('Line Detail'!$O$6:$O$505,$M6))) -> 3.2697426 | J6: =IF($M6=0,"",IF(INDEX('Line Detail'!$R$6:$R$505,$M6)="","",INDEX('Line Detail'!$R$6:$R$505,$M6))) -> 3269.7426 | K6: =IF($M6=0,"",IF(INDEX('Line Detail'!$S$6:$S$505,$M6)="","",INDEX('Line Detail'!$S$6:$S$505,$M6))) | M6: =IFERROR(MATCH(1,'Line Detail'!$W$6:$W$505,0),0) -> 1
A7: =IF($M7=0,"",2) -> 2 | B7: =IF($M7=0,"",IF(INDEX('Line Detail'!$B$6:$B$505,$M7)="","",INDEX('Line Detail'!$B$6:$B$505,$M7))) -> Base | C7: =IF($M7=0,"",IF(INDEX('Line Detail'!$C$6:$C$505,$M7)="","",INDEX('Line Detail'!$C$6:$C$505,$M7))) -> 08 17 43 Interior Pre-Hung Doors | D7: =IF($M7=0,"",IF(INDEX('Line Detail'!$D$6:$D$505,$M7)="","",INDEX('Line Detail'!$D$6:$D$505,$M7))) -> Units / Apartments | E7: =IF($M7=0,"",IF(INDEX('Line Detail'!$E$6:$E$505,$M7)="","",INDEX('Line Detail'!$E$6:$E$505,$M7))) -> Type 4 | F7: =IF($M7=0,"",IF(INDEX('Line Detail'!$F$6:$F$505,$M7)="","",INDEX('Line Detail'!$F$6:$F$505,$M7))) -> 3068 Hollow Core Hardboard 2-Panel Shaker 1-3/8", FJ split jamb 4-7/8" w/ FJ 1x4 casing, 3 ea US15 hinges, 2-3/8" backset single bore | G7: =IF($M7=0,"",IF(INDEX('Line Detail'!$G$6:$G$505,$M7)="","",INDEX('Line Detail'!$G$6:$G$505,$M7))) -> 10 | H7: =IF($M7=0,"",IF(INDEX('Line Detail'!$H$6:$H$505,$M7)="","",INDEX('Line Detail'!$H$6:$H$505,$M7))) -> EA | I7: =IF($M7=0,"",IF(INDEX('Line Detail'!$O$6:$O$505,$M7)="","",INDEX('Line Detail'!$O$6:$O$505,$M7))) -> 269.51838 | J7: =IF($M7=0,"",IF(INDEX('Line Detail'!$R$6:$R$505,$M7)="","",INDEX('Line Detail'!$R$6:$R$505,$M7))) -> 2695.1838 | K7: =IF($M7=0,"",IF(INDEX('Line Detail'!$S$6:$S$505,$M7)="","",INDEX('Line Detail'!$S$6:$S$505,$M7))) | M7: =IFERROR(MATCH(2,'Line Detail'!$W$6:$W$505,0),0) -> 2
A8: =IF($M8=0,"",3) -> 3 | B8: =IF($M8=0,"",IF(INDEX('Line Detail'!$B$6:$B$505,$M8)="","",INDEX('Line Detail'!$B$6:$B$505,$M8))) -> Base | C8: =IF($M8=0,"",IF(INDEX('Line Detail'!$C$6:$C$505,$M8)="","",INDEX('Line Detail'!$C$6:$C$505,$M8))) -> 08 71 00 Door Hardware | D8: =IF($M8=0,"",IF(INDEX('Line Detail'!$D$6:$D$505,$M8)="","",INDEX('Line Detail'!$D$6:$D$505,$M8))) -> Units / Apartments | E8: =IF($M8=0,"",IF(INDEX('Line Detail'!$E$6:$E$505,$M8)="","",INDEX('Line Detail'!$E$6:$E$505,$M8))) -> HW Set Bed/Bath | F8: =IF($M8=0,"",IF(INDEX('Line Detail'!$F$6:$F$505,$M8)="","",INDEX('Line Detail'!$F$6:$F$505,$M8))) -> 1 ea privacy lever US15; 1 ea door stop US15 | G8: =IF($M8=0,"",IF(INDEX('Line Detail'!$G$6:$G$505,$M8)="","",INDEX('Line Detail'!$G$6:$G$505,$M8))) -> 10 | H8: =IF($M8=0,"",IF(INDEX('Line Detail'!$H$6:$H$505,$M8)="","",INDEX('Line Detail'!$H$6:$H$505,$M8))) -> SET | I8: =IF($M8=0,"",IF(INDEX('Line Detail'!$O$6:$O$505,$M8)="","",INDEX('Line Detail'!$O$6:$O$505,$M8))) -> 36.382721 | J8: =IF($M8=0,"",IF(INDEX('Line Detail'!$R$6:$R$505,$M8)="","",INDEX('Line Detail'!$R$6:$R$505,$M8))) -> 363.82721 | K8: =IF($M8=0,"",IF(INDEX('Line Detail'!$S$6:$S$505,$M8)="","",INDEX('Line Detail'!$S$6:$S$505,$M8))) | M8: =IFERROR(MATCH(3,'Line Detail'!$W$6:$W$505,0),0) -> 3
A9: =IF($M9=0,"",4) -> 4 | B9: =IF($M9=0,"",IF(INDEX('Line Detail'!$B$6:$B$505,$M9)="","",INDEX('Line Detail'!$B$6:$B$505,$M9))) -> Alt 1 | C9: =IF($M9=0,"",IF(INDEX('Line Detail'!$C$6:$C$505,$M9)="","",INDEX('Line Detail'!$C$6:$C$505,$M9))) -> 08 71 00 Door Hardware | D9: =IF($M9=0,"",IF(INDEX('Line Detail'!$D$6:$D$505,$M9)="","",INDEX('Line Detail'!$D$6:$D$505,$M9))) -> Units / Apartments | E9: =IF($M9=0,"",IF(INDEX('Line Detail'!$E$6:$E$505,$M9)="","",INDEX('Line Detail'!$E$6:$E$505,$M9))) -> HW Set Entry | F9: =IF($M9=0,"",IF(INDEX('Line Detail'!$F$6:$F$505,$M9)="","",INDEX('Line Detail'!$F$6:$F$505,$M9))) -> ADD: battery-powered keypad deadbolt in lieu of keyed deadbolt | G9: =IF($M9=0,"",IF(INDEX('Line Detail'!$G$6:$G$505,$M9)="","",INDEX('Line Detail'!$G$6:$G$505,$M9))) -> 10 | H9: =IF($M9=0,"",IF(INDEX('Line Detail'!$H$6:$H$505,$M9)="","",INDEX('Line Detail'!$H$6:$H$505,$M9))) -> EA | I9: =IF($M9=0,"",IF(INDEX('Line Detail'!$O$6:$O$505,$M9)="","",INDEX('Line Detail'!$O$6:$O$505,$M9))) -> 356.41176 | J9: =IF($M9=0,"",IF(INDEX('Line Detail'!$R$6:$R$505,$M9)="","",INDEX('Line Detail'!$R$6:$R$505,$M9))) -> 3564.1176 | K9: =IF($M9=0,"",IF(INDEX('Line Detail'!$S$6:$S$505,$M9)="","",INDEX('Line Detail'!$S$6:$S$505,$M9))) -> Add alternate | M9: =IFERROR(MATCH(4,'Line Detail'!$W$6:$W$505,0),0) -> 4
A10: =IF($M10=0,"",5) | B10: =IF($M10=0,"",IF(INDEX('Line Detail'!$B$6:$B$505,$M10)="","",INDEX('Line Detail'!$B$6:$B$505,$M10))) | C10: =IF($M10=0,"",IF(INDEX('Line Detail'!$C$6:$C$505,$M10)="","",INDEX('Line Detail'!$C$6:$C$505,$M10))) | D10: =IF($M10=0,"",IF(INDEX('Line Detail'!$D$6:$D$505,$M10)="","",INDEX('Line Detail'!$D$6:$D$505,$M10))) | E10: =IF($M10=0,"",IF(INDEX('Line Detail'!$E$6:$E$505,$M10)="","",INDEX('Line Detail'!$E$6:$E$505,$M10))) | F10: =IF($M10=0,"",IF(INDEX('Line Detail'!$F$6:$F$505,$M10)="","",INDEX('Line Detail'!$F$6:$F$505,$M10))) | G10: =IF($M10=0,"",IF(INDEX('Line Detail'!$G$6:$G$505,$M10)="","",INDEX('Line Detail'!$G$6:$G$505,$M10))) | H10: =IF($M10=0,"",IF(INDEX('Line Detail'!$H$6:$H$505,$M10)="","",INDEX('Line Detail'!$H$6:$H$505,$M10))) | I10: =IF($M10=0,"",IF(INDEX('Line Detail'!$O$6:$O$505,$M10)="","",INDEX('Line Detail'!$O$6:$O$505,$M10))) | J10: =IF($M10=0,"",IF(INDEX('Line Detail'!$R$6:$R$505,$M10)="","",INDEX('Line Detail'!$R$6:$R$505,$M10))) | K10: =IF($M10=0,"",IF(INDEX('Line Detail'!$S$6:$S$505,$M10)="","",INDEX('Line Detail'!$S$6:$S$505,$M10))) | M10: =IFERROR(MATCH(5,'Line Detail'!$W$6:$W$505,0),0) -> 0
A11: =IF($M11=0,"",6) | B11: =IF($M11=0,"",IF(INDEX('Line Detail'!$B$6:$B$505,$M11)="","",INDEX('Line Detail'!$B$6:$B$505,$M11))) | C11: =IF($M11=0,"",IF(INDEX('Line Detail'!$C$6:$C$505,$M11)="","",INDEX('Line Detail'!$C$6:$C$505,$M11))) | D11: =IF($M11=0,"",IF(INDEX('Line Detail'!$D$6:$D$505,$M11)="","",INDEX('Line Detail'!$D$6:$D$505,$M11))) | E11: =IF($M11=0,"",IF(INDEX('Line Detail'!$E$6:$E$505,$M11)="","",INDEX('Line Detail'!$E$6:$E$505,$M11))) | F11: =IF($M11=0,"",IF(INDEX('Line Detail'!$F$6:$F$505,$M11)="","",INDEX('Line Detail'!$F$6:$F$505,$M11))) | G11: =IF($M11=0,"",IF(INDEX('Line Detail'!$G$6:$G$505,$M11)="","",INDEX('Line Detail'!$G$6:$G$505,$M11))) | H11: =IF($M11=0,"",IF(INDEX('Line Detail'!$H$6:$H$505,$M11)="","",INDEX('Line Detail'!$H$6:$H$505,$M11))) | I11: =IF($M11=0,"",IF(INDEX('Line Detail'!$O$6:$O$505,$M11)="","",INDEX('Line Detail'!$O$6:$O$505,$M11))) | J11: =IF($M11=0,"",IF(INDEX('Line Detail'!$R$6:$R$505,$M11)="","",INDEX('Line Detail'!$R$6:$R$505,$M11))) | K11: =IF($M11=0,"",IF(INDEX('Line Detail'!$S$6:$S$505,$M11)="","",INDEX('Line Detail'!$S$6:$S$505,$M11))) | M11: =IFERROR(MATCH(6,'Line Detail'!$W$6:$W$505,0),0) -> 0
A12: =IF($M12=0,"",7) | B12: =IF($M12=0,"",IF(INDEX('Line Detail'!$B$6:$B$505,$M12)="","",INDEX('Line Detail'!$B$6:$B$505,$M12))) | C12: =IF($M12=0,"",IF(INDEX('Line Detail'!$C$6:$C$505,$M12)="","",INDEX('Line Detail'!$C$6:$C$505,$M12))) | D12: =IF($M12=0,"",IF(INDEX('Line Detail'!$D$6:$D$505,$M12)="","",INDEX('Line Detail'!$D$6:$D$505,$M12))) | E12: =IF($M12=0,"",IF(INDEX('Line Detail'!$E$6:$E$505,$M12)="","",INDEX('Line Detail'!$E$6:$E$505,$M12))) | F12: =IF($M12=0,"",IF(INDEX('Line Detail'!$F$6:$F$505,$M12)="","",INDEX('Line Detail'!$F$6:$F$505,$M12))) | G12: =IF($M12=0,"",IF(INDEX('Line Detail'!$G$6:$G$505,$M12)="","",INDEX('Line Detail'!$G$6:$G$505,$M12))) | H12: =IF($M12=0,"",IF(INDEX('Line Detail'!$H$6:$H$505,$M12)="","",INDEX('Line Detail'!$H$6:$H$505,$M12))) | I12: =IF($M12=0,"",IF(INDEX('Line Detail'!$O$6:$O$505,$M12)="","",INDEX('Line Detail'!$O$6:$O$505,$M12))) | J12: =IF($M12=0,"",IF(INDEX('Line Detail'!$R$6:$R$505,$M12)="","",INDEX('Line Detail'!$R$6:$R$505,$M12))) | K12: =IF($M12=0,"",IF(INDEX('Line Detail'!$S$6:$S$505,$M12)="","",INDEX('Line Detail'!$S$6:$S$505,$M12))) | M12: =IFERROR(MATCH(7,'Line Detail'!$W$6:$W$505,0),0) -> 0
A13: =IF($M13=0,"",8) | B13: =IF($M13=0,"",IF(INDEX('Line Detail'!$B$6:$B$505,$M13)="","",INDEX('Line Detail'!$B$6:$B$505,$M13))) | C13: =IF($M13=0,"",IF(INDEX('Line Detail'!$C$6:$C$505,$M13)="","",INDEX('Line Detail'!$C$6:$C$505,$M13))) | D13: =IF($M13=0,"",IF(INDEX('Line Detail'!$D$6:$D$505,$M13)="","",INDEX('Line Detail'!$D$6:$D$505,$M13))) | E13: =IF($M13=0,"",IF(INDEX('Line Detail'!$E$6:$E$505,$M13)="","",INDEX('Line Detail'!$E$6:$E$505,$M13))) | F13: =IF($M13=0,"",IF(INDEX('Line Detail'!$F$6:$F$505,$M13)="","",INDEX('Line Detail'!$F$6:$F$505,$M13))) | G13: =IF($M13=0,"",IF(INDEX('Line Detail'!$G$6:$G$505,$M13)="","",INDEX('Line Detail'!$G$6:$G$505,$M13))) | H13: =IF($M13=0,"",IF(INDEX('Line Detail'!$H$6:$H$505,$M13)="","",INDEX('Line Detail'!$H$6:$H$505,$M13))) | I13: =IF($M13=0,"",IF(INDEX('Line Detail'!$O$6:$O$505,$M13)="","",INDEX('Line Detail'!$O$6:$O$505,$M13))) | J13: =IF($M13=0,"",IF(INDEX('Line Detail'!$R$6:$R$505,$M13)="","",INDEX('Line Detail'!$R$6:$R$505,$M13))) | K13: =IF($M13=0,"",IF(INDEX('Line Detail'!$S$6:$S$505,$M13)="","",INDEX('Line Detail'!$S$6:$S$505,$M13))) | M13: =IFERROR(MATCH(8,'Line Detail'!$W$6:$W$505,0),0) -> 0
A14: =IF($M14=0,"",9) | B14: =IF($M14=0,"",IF(INDEX('Line Detail'!$B$6:$B$505,$M14)="","",INDEX('Line Detail'!$B$6:$B$505,$M14))) | C14: =IF($M14=0,"",IF(INDEX('Line Detail'!$C$6:$C$505,$M14)="","",INDEX('Line Detail'!$C$6:$C$505,$M14))) | D14: =IF($M14=0,"",IF(INDEX('Line Detail'!$D$6:$D$505,$M14)="","",INDEX('Line Detail'!$D$6:$D$505,$M14))) | E14: =IF($M14=0,"",IF(INDEX('Line Detail'!$E$6:$E$505,$M14)="","",INDEX('Line Detail'!$E$6:$E$505,$M14))) | F14: =IF($M14=0,"",IF(INDEX('Line Detail'!$F$6:$F$505,$M14)="","",INDEX('Line Detail'!$F$6:$F$505,$M14))) | G14: =IF($M14=0,"",IF(INDEX('Line Detail'!$G$6:$G$505,$M14)="","",INDEX('Line Detail'!$G$6:$G$505,$M14))) | H14: =IF($M14=0,"",IF(INDEX('Line Detail'!$H$6:$H$505,$M14)="","",INDEX('Line Detail'!$H$6:$H$505,$M14))) | I14: =IF($M14=0,"",IF(INDEX('Line Detail'!$O$6:$O$505,$M14)="","",INDEX('Line Detail'!$O$6:$O$505,$M14))) | J14: =IF($M14=0,"",IF(INDEX('Line Detail'!$R$6:$R$505,$M14)="","",INDEX('Line Detail'!$R$6:$R$505,$M14))) | K14: =IF($M14=0,"",IF(INDEX('Line Detail'!$S$6:$S$505,$M14)="","",INDEX('Line Detail'!$S$6:$S$505,$M14))) | M14: =IFERROR(MATCH(9,'Line Detail'!$W$6:$W$505,0),0) -> 0
A15: =IF($M15=0,"",10) | B15: =IF($M15=0,"",IF(INDEX('Line Detail'!$B$6:$B$505,$M15)="","",INDEX('Line Detail'!$B$6:$B$505,$M15))) | C15: =IF($M15=0,"",IF(INDEX('Line Detail'!$C$6:$C$505,$M15)="","",INDEX('Line Detail'!$C$6:$C$505,$M15))) | D15: =IF($M15=0,"",IF(INDEX('Line Detail'!$D$6:$D$505,$M15)="","",INDEX('Line Detail'!$D$6:$D$505,$M15))) | E15: =IF($M15=0,"",IF(INDEX('Line Detail'!$E$6:$E$505,$M15)="","",INDEX('Line Detail'!$E$6:$E$505,$M15))) | F15: =IF($M15=0,"",IF(INDEX('Line Detail'!$F$6:$F$505,$M15)="","",INDEX('Line Detail'!$F$6:$F$505,$M15))) | G15: =IF($M15=0,"",IF(INDEX('Line Detail'!$G$6:$G$505,$M15)="","",INDEX('Line Detail'!$G$6:$G$505,$M15))) | H15: =IF($M15=0,"",IF(INDEX('Line Detail'!$H$6:$H$505,$M15)="","",INDEX('Line Detail'!$H$6:$H$505,$M15))) | I15: =IF($M15=0,"",IF(INDEX('Line Detail'!$O$6:$O$505,$M15)="","",INDEX('Line Detail'!$O$6:$O$505,$M15))) | J15: =IF($M15=0,"",IF(INDEX('Line Detail'!$R$6:$R$505,$M15)="","",INDEX('Line Detail'!$R$6:$R$505,$M15))) | K15: =IF($M15=0,"",IF(INDEX('Line Detail'!$S$6:$S$505,$M15)="","",INDEX('Line Detail'!$S$6:$S$505,$M15))) | M15: =IFERROR(MATCH(10,'Line Detail'!$W$6:$W$505,0),0) -> 0
A16: =IF($M16=0,"",11) | B16: =IF($M16=0,"",IF(INDEX('Line Detail'!$B$6:$B$505,$M16)="","",INDEX('Line Detail'!$B$6:$B$505,$M16))) | C16: =IF($M16=0,"",IF(INDEX('Line Detail'!$C$6:$C$505,$M16)="","",INDEX('Line Detail'!$C$6:$C$505,$M16))) | D16: =IF($M16=0,"",IF(INDEX('Line Detail'!$D$6:$D$505,$M16)="","",INDEX('Line Detail'!$D$6:$D$505,$M16))) | E16: =IF($M16=0,"",IF(INDEX('Line Detail'!$E$6:$E$505,$M16)="","",INDEX('Line Detail'!$E$6:$E$505,$M16))) | F16: =IF($M16=0,"",IF(INDEX('Line Detail'!$F$6:$F$505,$M16)="","",INDEX('Line Detail'!$F$6:$F$505,$M16))) | G16: =IF($M16=0,"",IF(INDEX('Line Detail'!$G$6:$G$505,$M16)="","",INDEX('Line Detail'!$G$6:$G$505,$M16))) | H16: =IF($M16=0,"",IF(INDEX('Line Detail'!$H$6:$H$505,$M16)="","",INDEX('Line Detail'!$H$6:$H$505,$M16))) | I16: =IF($M16=0,"",IF(INDEX('Line Detail'!$O$6:$O$505,$M16)="","",INDEX('Line Detail'!$O$6:$O$505,$M16))) | J16: =IF($M16=0,"",IF(INDEX('Line Detail'!$R$6:$R$505,$M16)="","",INDEX('Line Detail'!$R$6:$R$505,$M16))) | K16: =IF($M16=0,"",IF(INDEX('Line Detail'!$S$6:$S$505,$M16)="","",INDEX('Line Detail'!$S$6:$S$505,$M16))) | M16: =IFERROR(MATCH(11,'Line Detail'!$W$6:$W$505,0),0) -> 0
A17: =IF($M17=0,"",12) | B17: =IF($M17=0,"",IF(INDEX('Line Detail'!$B$6:$B$505,$M17)="","",INDEX('Line Detail'!$B$6:$B$505,$M17))) | C17: =IF($M17=0,"",IF(INDEX('Line Detail'!$C$6:$C$505,$M17)="","",INDEX('Line Detail'!$C$6:$C$505,$M17))) | D17: =IF($M17=0,"",IF(INDEX('Line Detail'!$D$6:$D$505,$M17)="","",INDEX('Line Detail'!$D$6:$D$505,$M17))) | E17: =IF($M17=0,"",IF(INDEX('Line Detail'!$E$6:$E$505,$M17)="","",INDEX('Line Detail'!$E$6:$E$505,$M17))) | F17: =IF($M17=0,"",IF(INDEX('Line Detail'!$F$6:$F$505,$M17)="","",INDEX('Line Detail'!$F$6:$F$505,$M17))) | G17: =IF($M17=0,"",IF(INDEX('Line Detail'!$G$6:$G$505,$M17)="","",INDEX('Line Detail'!$G$6:$G$505,$M17))) | H17: =IF($M17=0,"",IF(INDEX('Line Detail'!$H$6:$H$505,$M17)="","",INDEX('Line Detail'!$H$6:$H$505,$M17))) | I17: =IF($M17=0,"",IF(INDEX('Line Detail'!$O$6:$O$505,$M17)="","",INDEX('Line Detail'!$O$6:$O$505,$M17))) | J17: =IF($M17=0,"",IF(INDEX('Line Detail'!$R$6:$R$505,$M17)="","",INDEX('Line Detail'!$R$6:$R$505,$M17))) | K17: =IF($M17=0,"",IF(INDEX('Line Detail'!$S$6:$S$505,$M17)="","",INDEX('Line Detail'!$S$6:$S$505,$M17))) | M17: =IFERROR(MATCH(12,'Line Detail'!$W$6:$W$505,0),0) -> 0
A18: =IF($M18=0,"",13) | B18: =IF($M18=0,"",IF(INDEX('Line Detail'!$B$6:$B$505,$M18)="","",INDEX('Line Detail'!$B$6:$B$505,$M18))) | C18: =IF($M18=0,"",IF(INDEX('Line Detail'!$C$6:$C$505,$M18)="","",INDEX('Line Detail'!$C$6:$C$505,$M18))) | D18: =IF($M18=0,"",IF(INDEX('Line Detail'!$D$6:$D$505,$M18)="","",INDEX('Line Detail'!$D$6:$D$505,$M18))) | E18: =IF($M18=0,"",IF(INDEX('Line Detail'!$E$6:$E$505,$M18)="","",INDEX('Line Detail'!$E$6:$E$505,$M18))) | F18: =IF($M18=0,"",IF(INDEX('Line Detail'!$F$6:$F$505,$M18)="","",INDEX('Line Detail'!$F$6:$F$505,$M18))) | G18: =IF($M18=0,"",IF(INDEX('Line Detail'!$G$6:$G$505,$M18)="","",INDEX('Line Detail'!$G$6:$G$505,$M18))) | H18: =IF($M18=0,"",IF(INDEX('Line Detail'!$H$6:$H$505,$M18)="","",INDEX('Line Detail'!$H$6:$H$505,$M18))) | I18: =IF($M18=0,"",IF(INDEX('Line Detail'!$O$6:$O$505,$M18)="","",INDEX('Line Detail'!$O$6:$O$505,$M18))) | J18: =IF($M18=0,"",IF(INDEX('Line Detail'!$R$6:$R$505,$M18)="","",INDEX('Line Detail'!$R$6:$R$505,$M18))) | K18: =IF($M18=0,"",IF(INDEX('Line Detail'!$S$6:$S$505,$M18)="","",INDEX('Line Detail'!$S$6:$S$505,$M18))) | M18: =IFERROR(MATCH(13,'Line Detail'!$W$6:$W$505,0),0) -> 0
A19: =IF($M19=0,"",14) | B19: =IF($M19=0,"",IF(INDEX('Line Detail'!$B$6:$B$505,$M19)="","",INDEX('Line Detail'!$B$6:$B$505,$M19))) | C19: =IF($M19=0,"",IF(INDEX('Line Detail'!$C$6:$C$505,$M19)="","",INDEX('Line Detail'!$C$6:$C$505,$M19))) | D19: =IF($M19=0,"",IF(INDEX('Line Detail'!$D$6:$D$505,$M19)="","",INDEX('Line Detail'!$D$6:$D$505,$M19))) | E19: =IF($M19=0,"",IF(INDEX('Line Detail'!$E$6:$E$505,$M19)="","",INDEX('Line Detail'!$E$6:$E$505,$M19))) | F19: =IF($M19=0,"",IF(INDEX('Line Detail'!$F$6:$F$505,$M19)="","",INDEX('Line Detail'!$F$6:$F$505,$M19))) | G19: =IF($M19=0,"",IF(INDEX('Line Detail'!$G$6:$G$505,$M19)="","",INDEX('Line Detail'!$G$6:$G$505,$M19))) | H19: =IF($M19=0,"",IF(INDEX('Line Detail'!$H$6:$H$505,$M19)="","",INDEX('Line Detail'!$H$6:$H$505,$M19))) | I19: =IF($M19=0,"",IF(INDEX('Line Detail'!$O$6:$O$505,$M19)="","",INDEX('Line Detail'!$O$6:$O$505,$M19))) | J19: =IF($M19=0,"",IF(INDEX('Line Detail'!$R$6:$R$505,$M19)="","",INDEX('Line Detail'!$R$6:$R$505,$M19))) | K19: =IF($M19=0,"",IF(INDEX('Line Detail'!$S$6:$S$505,$M19)="","",INDEX('Line Detail'!$S$6:$S$505,$M19))) | M19: =IFERROR(MATCH(14,'Line Detail'!$W$6:$W$505,0),0) -> 0
A20: =IF($M20=0,"",15) | B20: =IF($M20=0,"",IF(INDEX('Line Detail'!$B$6:$B$505,$M20)="","",INDEX('Line Detail'!$B$6:$B$505,$M20))) | C20: =IF($M20=0,"",IF(INDEX('Line Detail'!$C$6:$C$505,$M20)="","",INDEX('Line Detail'!$C$6:$C$505,$M20))) | D20: =IF($M20=0,"",IF(INDEX('Line Detail'!$D$6:$D$505,$M20)="","",INDEX('Line Detail'!$D$6:$D$505,$M20))) | E20: =IF($M20=0,"",IF(INDEX('Line Detail'!$E$6:$E$505,$M20)="","",INDEX('Line Detail'!$E$6:$E$505,$M20))) | F20: =IF($M20=0,"",IF(INDEX('Line Detail'!$F$6:$F$505,$M20)="","",INDEX('Line Detail'!$F$6:$F$505,$M20))) | G20: =IF($M20=0,"",IF(INDEX('Line Detail'!$G$6:$G$505,$M20)="","",INDEX('Line Detail'!$G$6:$G$505,$M20))) | H20: =IF($M20=0,"",IF(INDEX('Line Detail'!$H$6:$H$505,$M20)="","",INDEX('Line Detail'!$H$6:$H$505,$M20))) | I20: =IF($M20=0,"",IF(INDEX('Line Detail'!$O$6:$O$505,$M20)="","",INDEX('Line Detail'!$O$6:$O$505,$M20))) | J20: =IF($M20=0,"",IF(INDEX('Line Detail'!$R$6:$R$505,$M20)="","",INDEX('Line Detail'!$R$6:$R$505,$M20))) | K20: =IF($M20=0,"",IF(INDEX('Line Detail'!$S$6:$S$505,$M20)="","",INDEX('Line Detail'!$S$6:$S$505,$M20))) | M20: =IFERROR(MATCH(15,'Line Detail'!$W$6:$W$505,0),0) -> 0
A21: =IF($M21=0,"",16) | B21: =IF($M21=0,"",IF(INDEX('Line Detail'!$B$6:$B$505,$M21)="","",INDEX('Line Detail'!$B$6:$B$505,$M21))) | C21: =IF($M21=0,"",IF(INDEX('Line Detail'!$C$6:$C$505,$M21)="","",INDEX('Line Detail'!$C$6:$C$505,$M21))) | D21: =IF($M21=0,"",IF(INDEX('Line Detail'!$D$6:$D$505,$M21)="","",INDEX('Line Detail'!$D$6:$D$505,$M21))) | E21: =IF($M21=0,"",IF(INDEX('Line Detail'!$E$6:$E$505,$M21)="","",INDEX('Line Detail'!$E$6:$E$505,$M21))) | F21: =IF($M21=0,"",IF(INDEX('Line Detail'!$F$6:$F$505,$M21)="","",INDEX('Line Detail'!$F$6:$F$505,$M21))) | G21: =IF($M21=0,"",IF(INDEX('Line Detail'!$G$6:$G$505,$M21)="","",INDEX('Line Detail'!$G$6:$G$505,$M21))) | H21: =IF($M21=0,"",IF(INDEX('Line Detail'!$H$6:$H$505,$M21)="","",INDEX('Line Detail'!$H$6:$H$505,$M21))) | I21: =IF($M21=0,"",IF(INDEX('Line Detail'!$O$6:$O$505,$M21)="","",INDEX('Line Detail'!$O$6:$O$505,$M21))) | J21: =IF($M21=0,"",IF(INDEX('Line Detail'!$R$6:$R$505,$M21)="","",INDEX('Line Detail'!$R$6:$R$505,$M21))) | K21: =IF($M21=0,"",IF(INDEX('Line Detail'!$S$6:$S$505,$M21)="","",INDEX('Line Detail'!$S$6:$S$505,$M21))) | M21: =IFERROR(MATCH(16,'Line Detail'!$W$6:$W$505,0),0) -> 0
A22: =IF($M22=0,"",17) | B22: =IF($M22=0,"",IF(INDEX('Line Detail'!$B$6:$B$505,$M22)="","",INDEX('Line Detail'!$B$6:$B$505,$M22))) | C22: =IF($M22=0,"",IF(INDEX('Line Detail'!$C$6:$C$505,$M22)="","",INDEX('Line Detail'!$C$6:$C$505,$M22))) | D22: =IF($M22=0,"",IF(INDEX('Line Detail'!$D$6:$D$505,$M22)="","",INDEX('Line Detail'!$D$6:$D$505,$M22))) | E22: =IF($M22=0,"",IF(INDEX('Line Detail'!$E$6:$E$505,$M22)="","",INDEX('Line Detail'!$E$6:$E$505,$M22))) | F22: =IF($M22=0,"",IF(INDEX('Line Detail'!$F$6:$F$505,$M22)="","",INDEX('Line Detail'!$F$6:$F$505,$M22))) | G22: =IF($M22=0,"",IF(INDEX('Line Detail'!$G$6:$G$505,$M22)="","",INDEX('Line Detail'!$G$6:$G$505,$M22))) | H22: =IF($M22=0,"",IF(INDEX('Line Detail'!$H$6:$H$505,$M22)="","",INDEX('Line Detail'!$H$6:$H$505,$M22))) | I22: =IF($M22=0,"",IF(INDEX('Line Detail'!$O$6:$O$505,$M22)="","",INDEX('Line Detail'!$O$6:$O$505,$M22))) | J22: =IF($M22=0,"",IF(INDEX('Line Detail'!$R$6:$R$505,$M22)="","",INDEX('Line Detail'!$R$6:$R$505,$M22))) | K22: =IF($M22=0,"",IF(INDEX('Line Detail'!$S$6:$S$505,$M22)="","",INDEX('Line Detail'!$S$6:$S$505,$M22))) | M22: =IFERROR(MATCH(17,'Line Detail'!$W$6:$W$505,0),0) -> 0
A23: =IF($M23=0,"",18) | B23: =IF($M23=0,"",IF(INDEX('Line Detail'!$B$6:$B$505,$M23)="","",INDEX('Line Detail'!$B$6:$B$505,$M23))) | C23: =IF($M23=0,"",IF(INDEX('Line Detail'!$C$6:$C$505,$M23)="","",INDEX('Line Detail'!$C$6:$C$505,$M23))) | D23: =IF($M23=0,"",IF(INDEX('Line Detail'!$D$6:$D$505,$M23)="","",INDEX('Line Detail'!$D$6:$D$505,$M23))) | E23: =IF($M23=0,"",IF(INDEX('Line Detail'!$E$6:$E$505,$M23)="","",INDEX('Line Detail'!$E$6:$E$505,$M23))) | F23: =IF($M23=0,"",IF(INDEX('Line Detail'!$F$6:$F$505,$M23)="","",INDEX('Line Detail'!$F$6:$F$505,$M23))) | G23: =IF($M23=0,"",IF(INDEX('Line Detail'!$G$6:$G$505,$M23)="","",INDEX('Line Detail'!$G$6:$G$505,$M23))) | H23: =IF($M23=0,"",IF(INDEX('Line Detail'!$H$6:$H$505,$M23)="","",INDEX('Line Detail'!$H$6:$H$505,$M23))) | I23: =IF($M23=0,"",IF(INDEX('Line Detail'!$O$6:$O$505,$M23)="","",INDEX('Line Detail'!$O$6:$O$505,$M23))) | J23: =IF($M23=0,"",IF(INDEX('Line Detail'!$R$6:$R$505,$M23)="","",INDEX('Line Detail'!$R$6:$R$505,$M23))) | K23: =IF($M23=0,"",IF(INDEX('Line Detail'!$S$6:$S$505,$M23)="","",INDEX('Line Detail'!$S$6:$S$505,$M23))) | M23: =IFERROR(MATCH(18,'Line Detail'!$W$6:$W$505,0),0) -> 0
A24: =IF($M24=0,"",19) | B24: =IF($M24=0,"",IF(INDEX('Line Detail'!$B$6:$B$505,$M24)="","",INDEX('Line Detail'!$B$6:$B$505,$M24))) | C24: =IF($M24=0,"",IF(INDEX('Line Detail'!$C$6:$C$505,$M24)="","",INDEX('Line Detail'!$C$6:$C$505,$M24))) | D24: =IF($M24=0,"",IF(INDEX('Line Detail'!$D$6:$D$505,$M24)="","",INDEX('Line Detail'!$D$6:$D$505,$M24))) | E24: =IF($M24=0,"",IF(INDEX('Line Detail'!$E$6:$E$505,$M24)="","",INDEX('Line Detail'!$E$6:$E$505,$M24))) | F24: =IF($M24=0,"",IF(INDEX('Line Detail'!$F$6:$F$505,$M24)="","",INDEX('Line Detail'!$F$6:$F$505,$M24))) | G24: =IF($M24=0,"",IF(INDEX('Line Detail'!$G$6:$G$505,$M24)="","",INDEX('Line Detail'!$G$6:$G$505,$M24))) | H24: =IF($M24=0,"",IF(INDEX('Line Detail'!$H$6:$H$505,$M24)="","",INDEX('Line Detail'!$H$6:$H$505,$M24))) | I24: =IF($M24=0,"",IF(INDEX('Line Detail'!$O$6:$O$505,$M24)="","",INDEX('Line Detail'!$O$6:$O$505,$M24))) | J24: =IF($M24=0,"",IF(INDEX('Line Detail'!$R$6:$R$505,$M24)="","",INDEX('Line Detail'!$R$6:$R$505,$M24))) | K24: =IF($M24=0,"",IF(INDEX('Line Detail'!$S$6:$S$505,$M24)="","",INDEX('Line Detail'!$S$6:$S$505,$M24))) | M24: =IFERROR(MATCH(19,'Line Detail'!$W$6:$W$505,0),0) -> 0
A25: =IF($M25=0,"",20) | B25: =IF($M25=0,"",IF(INDEX('Line Detail'!$B$6:$B$505,$M25)="","",INDEX('Line Detail'!$B$6:$B$505,$M25))) | C25: =IF($M25=0,"",IF(INDEX('Line Detail'!$C$6:$C$505,$M25)="","",INDEX('Line Detail'!$C$6:$C$505,$M25))) | D25: =IF($M25=0,"",IF(INDEX('Line Detail'!$D$6:$D$505,$M25)="","",INDEX('Line Detail'!$D$6:$D$505,$M25))) | E25: =IF($M25=0,"",IF(INDEX('Line Detail'!$E$6:$E$505,$M25)="","",INDEX('Line Detail'!$E$6:$E$505,$M25))) | F25: =IF($M25=0,"",IF(INDEX('Line Detail'!$F$6:$F$505,$M25)="","",INDEX('Line Detail'!$F$6:$F$505,$M25))) | G25: =IF($M25=0,"",IF(INDEX('Line Detail'!$G$6:$G$505,$M25)="","",INDEX('Line Detail'!$G$6:$G$505,$M25))) | H25: =IF($M25=0,"",IF(INDEX('Line Detail'!$H$6:$H$505,$M25)="","",INDEX('Line Detail'!$H$6:$H$505,$M25))) | I25: =IF($M25=0,"",IF(INDEX('Line Detail'!$O$6:$O$505,$M25)="","",INDEX('Line Detail'!$O$6:$O$505,$M25))) | J25: =IF($M25=0,"",IF(INDEX('Line Detail'!$R$6:$R$505,$M25)="","",INDEX('Line Detail'!$R$6:$R$505,$M25))) | K25: =IF($M25=0,"",IF(INDEX('Line Detail'!$S$6:$S$505,$M25)="","",INDEX('Line Detail'!$S$6:$S$505,$M25))) | M25: =IFERROR(MATCH(20,'Line Detail'!$W$6:$W$505,0),0) -> 0
A26: =IF($M26=0,"",21) | B26: =IF($M26=0,"",IF(INDEX('Line Detail'!$B$6:$B$505,$M26)="","",INDEX('Line Detail'!$B$6:$B$505,$M26))) | C26: =IF($M26=0,"",IF(INDEX('Line Detail'!$C$6:$C$505,$M26)="","",INDEX('Line Detail'!$C$6:$C$505,$M26))) | D26: =IF($M26=0,"",IF(INDEX('Line Detail'!$D$6:$D$505,$M26)="","",INDEX('Line Detail'!$D$6:$D$505,$M26))) | E26: =IF($M26=0,"",IF(INDEX('Line Detail'!$E$6:$E$505,$M26)="","",INDEX('Line Detail'!$E$6:$E$505,$M26))) | F26: =IF($M26=0,"",IF(INDEX('Line Detail'!$F$6:$F$505,$M26)="","",INDEX('Line Detail'!$F$6:$F$505,$M26))) | G26: =IF($M26=0,"",IF(INDEX('Line Detail'!$G$6:$G$505,$M26)="","",INDEX('Line Detail'!$G$6:$G$505,$M26))) | H26: =IF($M26=0,"",IF(INDEX('Line Detail'!$H$6:$H$505,$M26)="","",INDEX('Line Detail'!$H$6:$H$505,$M26))) | I26: =IF($M26=0,"",IF(INDEX('Line Detail'!$O$6:$O$505,$M26)="","",INDEX('Line Detail'!$O$6:$O$505,$M26))) | J26: =IF($M26=0,"",IF(INDEX('Line Detail'!$R$6:$R$505,$M26)="","",INDEX('Line Detail'!$R$6:$R$505,$M26))) | K26: =IF($M26=0,"",IF(INDEX('Line Detail'!$S$6:$S$505,$M26)="","",INDEX('Line Detail'!$S$6:$S$505,$M26))) | M26: =IFERROR(MATCH(21,'Line Detail'!$W$6:$W$505,0),0) -> 0
A27: =IF($M27=0,"",22) | B27: =IF($M27=0,"",IF(INDEX('Line Detail'!$B$6:$B$505,$M27)="","",INDEX('Line Detail'!$B$6:$B$505,$M27))) | C27: =IF($M27=0,"",IF(INDEX('Line Detail'!$C$6:$C$505,$M27)="","",INDEX('Line Detail'!$C$6:$C$505,$M27))) | D27: =IF($M27=0,"",IF(INDEX('Line Detail'!$D$6:$D$505,$M27)="","",INDEX('Line Detail'!$D$6:$D$505,$M27))) | E27: =IF($M27=0,"",IF(INDEX('Line Detail'!$E$6:$E$505,$M27)="","",INDEX('Line Detail'!$E$6:$E$505,$M27))) | F27: =IF($M27=0,"",IF(INDEX('Line Detail'!$F$6:$F$505,$M27)="","",INDEX('Line Detail'!$F$6:$F$505,$M27))) | G27: =IF($M27=0,"",IF(INDEX('Line Detail'!$G$6:$G$505,$M27)="","",INDEX('Line Detail'!$G$6:$G$505,$M27))) | H27: =IF($M27=0,"",IF(INDEX('Line Detail'!$H$6:$H$505,$M27)="","",INDEX('Line Detail'!$H$6:$H$505,$M27))) | I27: =IF($M27=0,"",IF(INDEX('Line Detail'!$O$6:$O$505,$M27)="","",INDEX('Line Detail'!$O$6:$O$505,$M27))) | J27: =IF($M27=0,"",IF(INDEX('Line Detail'!$R$6:$R$505,$M27)="","",INDEX('Line Detail'!$R$6:$R$505,$M27))) | K27: =IF($M27=0,"",IF(INDEX('Line Detail'!$S$6:$S$505,$M27)="","",INDEX('Line Detail'!$S$6:$S$505,$M27))) | M27: =IFERROR(MATCH(22,'Line Detail'!$W$6:$W$505,0),0) -> 0
A28: =IF($M28=0,"",23) | B28: =IF($M28=0,"",IF(INDEX('Line Detail'!$B$6:$B$505,$M28)="","",INDEX('Line Detail'!$B$6:$B$505,$M28))) | C28: =IF($M28=0,"",IF(INDEX('Line Detail'!$C$6:$C$505,$M28)="","",INDEX('Line Detail'!$C$6:$C$505,$M28))) | D28: =IF($M28=0,"",IF(INDEX('Line Detail'!$D$6:$D$505,$M28)="","",INDEX('Line Detail'!$D$6:$D$505,$M28))) | E28: =IF($M28=0,"",IF(INDEX('Line Detail'!$E$6:$E$505,$M28)="","",INDEX('Line Detail'!$E$6:$E$505,$M28))) | F28: =IF($M28=0,"",IF(INDEX('Line Detail'!$F$6:$F$505,$M28)="","",INDEX('Line Detail'!$F$6:$F$505,$M28))) | G28: =IF($M28=0,"",IF(INDEX('Line Detail'!$G$6:$G$505,$M28)="","",INDEX('Line Detail'!$G$6:$G$505,$M28))) | H28: =IF($M28=0,"",IF(INDEX('Line Detail'!$H$6:$H$505,$M28)="","",INDEX('Line Detail'!$H$6:$H$505,$M28))) | I28: =IF($M28=0,"",IF(INDEX('Line Detail'!$O$6:$O$505,$M28)="","",INDEX('Line Detail'!$O$6:$O$505,$M28))) | J28: =IF($M28=0,"",IF(INDEX('Line Detail'!$R$6:$R$505,$M28)="","",INDEX('Line Detail'!$R$6:$R$505,$M28))) | K28: =IF($M28=0,"",IF(INDEX('Line Detail'!$S$6:$S$505,$M28)="","",INDEX('Line Detail'!$S$6:$S$505,$M28))) | M28: =IFERROR(MATCH(23,'Line Detail'!$W$6:$W$505,0),0) -> 0
A29: =IF($M29=0,"",24) | B29: =IF($M29=0,"",IF(INDEX('Line Detail'!$B$6:$B$505,$M29)="","",INDEX('Line Detail'!$B$6:$B$505,$M29))) | C29: =IF($M29=0,"",IF(INDEX('Line Detail'!$C$6:$C$505,$M29)="","",INDEX('Line Detail'!$C$6:$C$505,$M29))) | D29: =IF($M29=0,"",IF(INDEX('Line Detail'!$D$6:$D$505,$M29)="","",INDEX('Line Detail'!$D$6:$D$505,$M29))) | E29: =IF($M29=0,"",IF(INDEX('Line Detail'!$E$6:$E$505,$M29)="","",INDEX('Line Detail'!$E$6:$E$505,$M29))) | F29: =IF($M29=0,"",IF(INDEX('Line Detail'!$F$6:$F$505,$M29)="","",INDEX('Line Detail'!$F$6:$F$505,$M29))) | G29: =IF($M29=0,"",IF(INDEX('Line Detail'!$G$6:$G$505,$M29)="","",INDEX('Line Detail'!$G$6:$G$505,$M29))) | H29: =IF($M29=0,"",IF(INDEX('Line Detail'!$H$6:$H$505,$M29)="","",INDEX('Line Detail'!$H$6:$H$505,$M29))) | I29: =IF($M29=0,"",IF(INDEX('Line Detail'!$O$6:$O$505,$M29)="","",INDEX('Line Detail'!$O$6:$O$505,$M29))) | J29: =IF($M29=0,"",IF(INDEX('Line Detail'!$R$6:$R$505,$M29)="","",INDEX('Line Detail'!$R$6:$R$505,$M29))) | K29: =IF($M29=0,"",IF(INDEX('Line Detail'!$S$6:$S$505,$M29)="","",INDEX('Line Detail'!$S$6:$S$505,$M29))) | M29: =IFERROR(MATCH(24,'Line Detail'!$W$6:$W$505,0),0) -> 0
A30: =IF($M30=0,"",25) | B30: =IF($M30=0,"",IF(INDEX('Line Detail'!$B$6:$B$505,$M30)="","",INDEX('Line Detail'!$B$6:$B$505,$M30))) | C30: =IF($M30=0,"",IF(INDEX('Line Detail'!$C$6:$C$505,$M30)="","",INDEX('Line Detail'!$C$6:$C$505,$M30))) | D30: =IF($M30=0,"",IF(INDEX('Line Detail'!$D$6:$D$505,$M30)="","",INDEX('Line Detail'!$D$6:$D$505,$M30))) | E30: =IF($M30=0,"",IF(INDEX('Line Detail'!$E$6:$E$505,$M30)="","",INDEX('Line Detail'!$E$6:$E$505,$M30))) | F30: =IF($M30=0,"",IF(INDEX('Line Detail'!$F$6:$F$505,$M30)="","",INDEX('Line Detail'!$F$6:$F$505,$M30))) | G30: =IF($M30=0,"",IF(INDEX('Line Detail'!$G$6:$G$505,$M30)="","",INDEX('Line Detail'!$G$6:$G$505,$M30))) | H30: =IF($M30=0,"",IF(INDEX('Line Detail'!$H$6:$H$505,$M30)="","",INDEX('Line Detail'!$H$6:$H$505,$M30))) | I30: =IF($M30=0,"",IF(INDEX('Line Detail'!$O$6:$O$505,$M30)="","",INDEX('Line Detail'!$O$6:$O$505,$M30))) | J30: =IF($M30=0,"",IF(INDEX('Line Detail'!$R$6:$R$505,$M30)="","",INDEX('Line Detail'!$R$6:$R$505,$M30))) | K30: =IF($M30=0,"",IF(INDEX('Line Detail'!$S$6:$S$505,$M30)="","",INDEX('Line Detail'!$S$6:$S$505,$M30))) | M30: =IFERROR(MATCH(25,'Line Detail'!$W$6:$W$505,0),0) -> 0
A31: =IF($M31=0,"",26) | B31: =IF($M31=0,"",IF(INDEX('Line Detail'!$B$6:$B$505,$M31)="","",INDEX('Line Detail'!$B$6:$B$505,$M31))) | C31: =IF($M31=0,"",IF(INDEX('Line Detail'!$C$6:$C$505,$M31)="","",INDEX('Line Detail'!$C$6:$C$505,$M31))) | D31: =IF($M31=0,"",IF(INDEX('Line Detail'!$D$6:$D$505,$M31)="","",INDEX('Line Detail'!$D$6:$D$505,$M31))) | E31: =IF($M31=0,"",IF(INDEX('Line Detail'!$E$6:$E$505,$M31)="","",INDEX('Line Detail'!$E$6:$E$505,$M31))) | F31: =IF($M31=0,"",IF(INDEX('Line Detail'!$F$6:$F$505,$M31)="","",INDEX('Line Detail'!$F$6:$F$505,$M31))) | G31: =IF($M31=0,"",IF(INDEX('Line Detail'!$G$6:$G$505,$M31)="","",INDEX('Line Detail'!$G$6:$G$505,$M31))) | H31: =IF($M31=0,"",IF(INDEX('Line Detail'!$H$6:$H$505,$M31)="","",INDEX('Line Detail'!$H$6:$H$505,$M31))) | I31: =IF($M31=0,"",IF(INDEX('Line Detail'!$O$6:$O$505,$M31)="","",INDEX('Line Detail'!$O$6:$O$505,$M31))) | J31: =IF($M31=0,"",IF(INDEX('Line Detail'!$R$6:$R$505,$M31)="","",INDEX('Line Detail'!$R$6:$R$505,$M31))) | K31: =IF($M31=0,"",IF(INDEX('Line Detail'!$S$6:$S$505,$M31)="","",INDEX('Line Detail'!$S$6:$S$505,$M31))) | M31: =IFERROR(MATCH(26,'Line Detail'!$W$6:$W$505,0),0) -> 0
A32: =IF($M32=0,"",27) | B32: =IF($M32=0,"",IF(INDEX('Line Detail'!$B$6:$B$505,$M32)="","",INDEX('Line Detail'!$B$6:$B$505,$M32))) | C32: =IF($M32=0,"",IF(INDEX('Line Detail'!$C$6:$C$505,$M32)="","",INDEX('Line Detail'!$C$6:$C$505,$M32))) | D32: =IF($M32=0,"",IF(INDEX('Line Detail'!$D$6:$D$505,$M32)="","",INDEX('Line Detail'!$D$6:$D$505,$M32))) | E32: =IF($M32=0,"",IF(INDEX('Line Detail'!$E$6:$E$505,$M32)="","",INDEX('Line Detail'!$E$6:$E$505,$M32))) | F32: =IF($M32=0,"",IF(INDEX('Line Detail'!$F$6:$F$505,$M32)="","",INDEX('Line Detail'!$F$6:$F$505,$M32))) | G32: =IF($M32=0,"",IF(INDEX('Line Detail'!$G$6:$G$505,$M32)="","",INDEX('Line Detail'!$G$6:$G$505,$M32))) | H32: =IF($M32=0,"",IF(INDEX('Line Detail'!$H$6:$H$505,$M32)="","",INDEX('Line Detail'!$H$6:$H$505,$M32))) | I32: =IF($M32=0,"",IF(INDEX('Line Detail'!$O$6:$O$505,$M32)="","",INDEX('Line Detail'!$O$6:$O$505,$M32))) | J32: =IF($M32=0,"",IF(INDEX('Line Detail'!$R$6:$R$505,$M32)="","",INDEX('Line Detail'!$R$6:$R$505,$M32))) | K32: =IF($M32=0,"",IF(INDEX('Line Detail'!$S$6:$S$505,$M32)="","",INDEX('Line Detail'!$S$6:$S$505,$M32))) | M32: =IFERROR(MATCH(27,'Line Detail'!$W$6:$W$505,0),0) -> 0
A33: =IF($M33=0,"",28) | B33: =IF($M33=0,"",IF(INDEX('Line Detail'!$B$6:$B$505,$M33)="","",INDEX('Line Detail'!$B$6:$B$505,$M33))) | C33: =IF($M33=0,"",IF(INDEX('Line Detail'!$C$6:$C$505,$M33)="","",INDEX('Line Detail'!$C$6:$C$505,$M33))) | D33: =IF($M33=0,"",IF(INDEX('Line Detail'!$D$6:$D$505,$M33)="","",INDEX('Line Detail'!$D$6:$D$505,$M33))) | E33: =IF($M33=0,"",IF(INDEX('Line Detail'!$E$6:$E$505,$M33)="","",INDEX('Line Detail'!$E$6:$E$505,$M33))) | F33: =IF($M33=0,"",IF(INDEX('Line Detail'!$F$6:$F$505,$M33)="","",INDEX('Line Detail'!$F$6:$F$505,$M33))) | G33: =IF($M33=0,"",IF(INDEX('Line Detail'!$G$6:$G$505,$M33)="","",INDEX('Line Detail'!$G$6:$G$505,$M33))) | H33: =IF($M33=0,"",IF(INDEX('Line Detail'!$H$6:$H$505,$M33)="","",INDEX('Line Detail'!$H$6:$H$505,$M33))) | I33: =IF($M33=0,"",IF(INDEX('Line Detail'!$O$6:$O$505,$M33)="","",INDEX('Line Detail'!$O$6:$O$505,$M33))) | J33: =IF($M33=0,"",IF(INDEX('Line Detail'!$R$6:$R$505,$M33)="","",INDEX('Line Detail'!$R$6:$R$505,$M33))) | K33: =IF($M33=0,"",IF(INDEX('Line Detail'!$S$6:$S$505,$M33)="","",INDEX('Line Detail'!$S$6:$S$505,$M33))) | M33: =IFERROR(MATCH(28,'Line Detail'!$W$6:$W$505,0),0) -> 0
A34: =IF($M34=0,"",29) | B34: =IF($M34=0,"",IF(INDEX('Line Detail'!$B$6:$B$505,$M34)="","",INDEX('Line Detail'!$B$6:$B$505,$M34))) | C34: =IF($M34=0,"",IF(INDEX('Line Detail'!$C$6:$C$505,$M34)="","",INDEX('Line Detail'!$C$6:$C$505,$M34))) | D34: =IF($M34=0,"",IF(INDEX('Line Detail'!$D$6:$D$505,$M34)="","",INDEX('Line Detail'!$D$6:$D$505,$M34))) | E34: =IF($M34=0,"",IF(INDEX('Line Detail'!$E$6:$E$505,$M34)="","",INDEX('Line Detail'!$E$6:$E$505,$M34))) | F34: =IF($M34=0,"",IF(INDEX('Line Detail'!$F$6:$F$505,$M34)="","",INDEX('Line Detail'!$F$6:$F$505,$M34))) | G34: =IF($M34=0,"",IF(INDEX('Line Detail'!$G$6:$G$505,$M34)="","",INDEX('Line Detail'!$G$6:$G$505,$M34))) | H34: =IF($M34=0,"",IF(INDEX('Line Detail'!$H$6:$H$505,$M34)="","",INDEX('Line Detail'!$H$6:$H$505,$M34))) | I34: =IF($M34=0,"",IF(INDEX('Line Detail'!$O$6:$O$505,$M34)="","",INDEX('Line Detail'!$O$6:$O$505,$M34))) | J34: =IF($M34=0,"",IF(INDEX('Line Detail'!$R$6:$R$505,$M34)="","",INDEX('Line Detail'!$R$6:$R$505,$M34))) | K34: =IF($M34=0,"",IF(INDEX('Line Detail'!$S$6:$S$505,$M34)="","",INDEX('Line Detail'!$S$6:$S$505,$M34))) | M34: =IFERROR(MATCH(29,'Line Detail'!$W$6:$W$505,0),0) -> 0
A35: =IF($M35=0,"",30) | B35: =IF($M35=0,"",IF(INDEX('Line Detail'!$B$6:$B$505,$M35)="","",INDEX('Line Detail'!$B$6:$B$505,$M35))) | C35: =IF($M35=0,"",IF(INDEX('Line Detail'!$C$6:$C$505,$M35)="","",INDEX('Line Detail'!$C$6:$C$505,$M35))) | D35: =IF($M35=0,"",IF(INDEX('Line Detail'!$D$6:$D$505,$M35)="","",INDEX('Line Detail'!$D$6:$D$505,$M35))) | E35: =IF($M35=0,"",IF(INDEX('Line Detail'!$E$6:$E$505,$M35)="","",INDEX('Line Detail'!$E$6:$E$505,$M35))) | F35: =IF($M35=0,"",IF(INDEX('Line Detail'!$F$6:$F$505,$M35)="","",INDEX('Line Detail'!$F$6:$F$505,$M35))) | G35: =IF($M35=0,"",IF(INDEX('Line Detail'!$G$6:$G$505,$M35)="","",INDEX('Line Detail'!$G$6:$G$505,$M35))) | H35: =IF($M35=0,"",IF(INDEX('Line Detail'!$H$6:$H$505,$M35)="","",INDEX('Line Detail'!$H$6:$H$505,$M35))) | I35: =IF($M35=0,"",IF(INDEX('Line Detail'!$O$6:$O$505,$M35)="","",INDEX('Line Detail'!$O$6:$O$505,$M35))) | J35: =IF($M35=0,"",IF(INDEX('Line Detail'!$R$6:$R$505,$M35)="","",INDEX('Line Detail'!$R$6:$R$505,$M35))) | K35: =IF($M35=0,"",IF(INDEX('Line Detail'!$S$6:$S$505,$M35)="","",INDEX('Line Detail'!$S$6:$S$505,$M35))) | M35: =IFERROR(MATCH(30,'Line Detail'!$W$6:$W$505,0),0) -> 0
A36: =IF($M36=0,"",31) | B36: =IF($M36=0,"",IF(INDEX('Line Detail'!$B$6:$B$505,$M36)="","",INDEX('Line Detail'!$B$6:$B$505,$M36))) | C36: =IF($M36=0,"",IF(INDEX('Line Detail'!$C$6:$C$505,$M36)="","",INDEX('Line Detail'!$C$6:$C$505,$M36))) | D36: =IF($M36=0,"",IF(INDEX('Line Detail'!$D$6:$D$505,$M36)="","",INDEX('Line Detail'!$D$6:$D$505,$M36))) | E36: =IF($M36=0,"",IF(INDEX('Line Detail'!$E$6:$E$505,$M36)="","",INDEX('Line Detail'!$E$6:$E$505,$M36))) | F36: =IF($M36=0,"",IF(INDEX('Line Detail'!$F$6:$F$505,$M36)="","",INDEX('Line Detail'!$F$6:$F$505,$M36))) | G36: =IF($M36=0,"",IF(INDEX('Line Detail'!$G$6:$G$505,$M36)="","",INDEX('Line Detail'!$G$6:$G$505,$M36))) | H36: =IF($M36=0,"",IF(INDEX('Line Detail'!$H$6:$H$505,$M36)="","",INDEX('Line Detail'!$H$6:$H$505,$M36))) | I36: =IF($M36=0,"",IF(INDEX('Line Detail'!$O$6:$O$505,$M36)="","",INDEX('Line Detail'!$O$6:$O$505,$M36))) | J36: =IF($M36=0,"",IF(INDEX('Line Detail'!$R$6:$R$505,$M36)="","",INDEX('Line Detail'!$R$6:$R$505,$M36))) | K36: =IF($M36=0,"",IF(INDEX('Line Detail'!$S$6:$S$505,$M36)="","",INDEX('Line Detail'!$S$6:$S$505,$M36))) | M36: =IFERROR(MATCH(31,'Line Detail'!$W$6:$W$505,0),0) -> 0
A37: =IF($M37=0,"",32) | B37: =IF($M37=0,"",IF(INDEX('Line Detail'!$B$6:$B$505,$M37)="","",INDEX('Line Detail'!$B$6:$B$505,$M37))) | C37: =IF($M37=0,"",IF(INDEX('Line Detail'!$C$6:$C$505,$M37)="","",INDEX('Line Detail'!$C$6:$C$505,$M37))) | D37: =IF($M37=0,"",IF(INDEX('Line Detail'!$D$6:$D$505,$M37)="","",INDEX('Line Detail'!$D$6:$D$505,$M37))) | E37: =IF($M37=0,"",IF(INDEX('Line Detail'!$E$6:$E$505,$M37)="","",INDEX('Line Detail'!$E$6:$E$505,$M37))) | F37: =IF($M37=0,"",IF(INDEX('Line Detail'!$F$6:$F$505,$M37)="","",INDEX('Line Detail'!$F$6:$F$505,$M37))) | G37: =IF($M37=0,"",IF(INDEX('Line Detail'!$G$6:$G$505,$M37)="","",INDEX('Line Detail'!$G$6:$G$505,$M37))) | H37: =IF($M37=0,"",IF(INDEX('Line Detail'!$H$6:$H$505,$M37)="","",INDEX('Line Detail'!$H$6:$H$505,$M37))) | I37: =IF($M37=0,"",IF(INDEX('Line Detail'!$O$6:$O$505,$M37)="","",INDEX('Line Detail'!$O$6:$O$505,$M37))) | J37: =IF($M37=0,"",IF(INDEX('Line Detail'!$R$6:$R$505,$M37)="","",INDEX('Line Detail'!$R$6:$R$505,$M37))) | K37: =IF($M37=0,"",IF(INDEX('Line Detail'!$S$6:$S$505,$M37)="","",INDEX('Line Detail'!$S$6:$S$505,$M37))) | M37: =IFERROR(MATCH(32,'Line Detail'!$W$6:$W$505,0),0) -> 0
A38: =IF($M38=0,"",33) | B38: =IF($M38=0,"",IF(INDEX('Line Detail'!$B$6:$B$505,$M38)="","",INDEX('Line Detail'!$B$6:$B$505,$M38))) | C38: =IF($M38=0,"",IF(INDEX('Line Detail'!$C$6:$C$505,$M38)="","",INDEX('Line Detail'!$C$6:$C$505,$M38))) | D38: =IF($M38=0,"",IF(INDEX('Line Detail'!$D$6:$D$505,$M38)="","",INDEX('Line Detail'!$D$6:$D$505,$M38))) | E38: =IF($M38=0,"",IF(INDEX('Line Detail'!$E$6:$E$505,$M38)="","",INDEX('Line Detail'!$E$6:$E$505,$M38))) | F38: =IF($M38=0,"",IF(INDEX('Line Detail'!$F$6:$F$505,$M38)="","",INDEX('Line Detail'!$F$6:$F$505,$M38))) | G38: =IF($M38=0,"",IF(INDEX('Line Detail'!$G$6:$G$505,$M38)="","",INDEX('Line Detail'!$G$6:$G$505,$M38))) | H38: =IF($M38=0,"",IF(INDEX('Line Detail'!$H$6:$H$505,$M38)="","",INDEX('Line Detail'!$H$6:$H$505,$M38))) | I38: =IF($M38=0,"",IF(INDEX('Line Detail'!$O$6:$O$505,$M38)="","",INDEX('Line Detail'!$O$6:$O$505,$M38))) | J38: =IF($M38=0,"",IF(INDEX('Line Detail'!$R$6:$R$505,$M38)="","",INDEX('Line Detail'!$R$6:$R$505,$M38))) | K38: =IF($M38=0,"",IF(INDEX('Line Detail'!$S$6:$S$505,$M38)="","",INDEX('Line Detail'!$S$6:$S$505,$M38))) | M38: =IFERROR(MATCH(33,'Line Detail'!$W$6:$W$505,0),0) -> 0
A39: =IF($M39=0,"",34) | B39: =IF($M39=0,"",IF(INDEX('Line Detail'!$B$6:$B$505,$M39)="","",INDEX('Line Detail'!$B$6:$B$505,$M39))) | C39: =IF($M39=0,"",IF(INDEX('Line Detail'!$C$6:$C$505,$M39)="","",INDEX('Line Detail'!$C$6:$C$505,$M39))) | D39: =IF($M39=0,"",IF(INDEX('Line Detail'!$D$6:$D$505,$M39)="","",INDEX('Line Detail'!$D$6:$D$505,$M39))) | E39: =IF($M39=0,"",IF(INDEX('Line Detail'!$E$6:$E$505,$M39)="","",INDEX('Line Detail'!$E$6:$E$505,$M39))) | F39: =IF($M39=0,"",IF(INDEX('Line Detail'!$F$6:$F$505,$M39)="","",INDEX('Line Detail'!$F$6:$F$505,$M39))) | G39: =IF($M39=0,"",IF(INDEX('Line Detail'!$G$6:$G$505,$M39)="","",INDEX('Line Detail'!$G$6:$G$505,$M39))) | H39: =IF($M39=0,"",IF(INDEX('Line Detail'!$H$6:$H$505,$M39)="","",INDEX('Line Detail'!$H$6:$H$505,$M39))) | I39: =IF($M39=0,"",IF(INDEX('Line Detail'!$O$6:$O$505,$M39)="","",INDEX('Line Detail'!$O$6:$O$505,$M39))) | J39: =IF($M39=0,"",IF(INDEX('Line Detail'!$R$6:$R$505,$M39)="","",INDEX('Line Detail'!$R$6:$R$505,$M39))) | K39: =IF($M39=0,"",IF(INDEX('Line Detail'!$S$6:$S$505,$M39)="","",INDEX('Line Detail'!$S$6:$S$505,$M39))) | M39: =IFERROR(MATCH(34,'Line Detail'!$W$6:$W$505,0),0) -> 0
A40: =IF($M40=0,"",35) | B40: =IF($M40=0,"",IF(INDEX('Line Detail'!$B$6:$B$505,$M40)="","",INDEX('Line Detail'!$B$6:$B$505,$M40))) | C40: =IF($M40=0,"",IF(INDEX('Line Detail'!$C$6:$C$505,$M40)="","",INDEX('Line Detail'!$C$6:$C$505,$M40))) | D40: =IF($M40=0,"",IF(INDEX('Line Detail'!$D$6:$D$505,$M40)="","",INDEX('Line Detail'!$D$6:$D$505,$M40))) | E40: =IF($M40=0,"",IF(INDEX('Line Detail'!$E$6:$E$505,$M40)="","",INDEX('Line Detail'!$E$6:$E$505,$M40))) | F40: =IF($M40=0,"",IF(INDEX('Line Detail'!$F$6:$F$505,$M40)="","",INDEX('Line Detail'!$F$6:$F$505,$M40))) | G40: =IF($M40=0,"",IF(INDEX('Line Detail'!$G$6:$G$505,$M40)="","",INDEX('Line Detail'!$G$6:$G$505,$M40))) | H40: =IF($M40=0,"",IF(INDEX('Line Detail'!$H$6:$H$505,$M40)="","",INDEX('Line Detail'!$H$6:$H$505,$M40))) | I40: =IF($M40=0,"",IF(INDEX('Line Detail'!$O$6:$O$505,$M40)="","",INDEX('Line Detail'!$O$6:$O$505,$M40))) | J40: =IF($M40=0,"",IF(INDEX('Line Detail'!$R$6:$R$505,$M40)="","",INDEX('Line Detail'!$R$6:$R$505,$M40))) | K40: =IF($M40=0,"",IF(INDEX('Line Detail'!$S$6:$S$505,$M40)="","",INDEX('Line Detail'!$S$6:$S$505,$M40))) | M40: =IFERROR(MATCH(35,'Line Detail'!$W$6:$W$505,0),0) -> 0
A41: =IF($M41=0,"",36) | B41: =IF($M41=0,"",IF(INDEX('Line Detail'!$B$6:$B$505,$M41)="","",INDEX('Line Detail'!$B$6:$B$505,$M41))) | C41: =IF($M41=0,"",IF(INDEX('Line Detail'!$C$6:$C$505,$M41)="","",INDEX('Line Detail'!$C$6:$C$505,$M41))) | D41: =IF($M41=0,"",IF(INDEX('Line Detail'!$D$6:$D$505,$M41)="","",INDEX('Line Detail'!$D$6:$D$505,$M41))) | E41: =IF($M41=0,"",IF(INDEX('Line Detail'!$E$6:$E$505,$M41)="","",INDEX('Line Detail'!$E$6:$E$505,$M41))) | F41: =IF($M41=0,"",IF(INDEX('Line Detail'!$F$6:$F$505,$M41)="","",INDEX('Line Detail'!$F$6:$F$505,$M41))) | G41: =IF($M41=0,"",IF(INDEX('Line Detail'!$G$6:$G$505,$M41)="","",INDEX('Line Detail'!$G$6:$G$505,$M41))) | H41: =IF($M41=0,"",IF(INDEX('Line Detail'!$H$6:$H$505,$M41)="","",INDEX('Line Detail'!$H$6:$H$505,$M41))) | I41: =IF($M41=0,"",IF(INDEX('Line Detail'!$O$6:$O$505,$M41)="","",INDEX('Line Detail'!$O$6:$O$505,$M41))) | J41: =IF($M41=0,"",IF(INDEX('Line Detail'!$R$6:$R$505,$M41)="","",INDEX('Line Detail'!$R$6:$R$505,$M41))) | K41: =IF($M41=0,"",IF(INDEX('Line Detail'!$S$6:$S$505,$M41)="","",INDEX('Line Detail'!$S$6:$S$505,$M41))) | M41: =IFERROR(MATCH(36,'Line Detail'!$W$6:$W$505,0),0) -> 0
A42: =IF($M42=0,"",37) | B42: =IF($M42=0,"",IF(INDEX('Line Detail'!$B$6:$B$505,$M42)="","",INDEX('Line Detail'!$B$6:$B$505,$M42))) | C42: =IF($M42=0,"",IF(INDEX('Line Detail'!$C$6:$C$505,$M42)="","",INDEX('Line Detail'!$C$6:$C$505,$M42))) | D42: =IF($M42=0,"",IF(INDEX('Line Detail'!$D$6:$D$505,$M42)="","",INDEX('Line Detail'!$D$6:$D$505,$M42))) | E42: =IF($M42=0,"",IF(INDEX('Line Detail'!$E$6:$E$505,$M42)="","",INDEX('Line Detail'!$E$6:$E$505,$M42))) | F42: =IF($M42=0,"",IF(INDEX('Line Detail'!$F$6:$F$505,$M42)="","",INDEX('Line Detail'!$F$6:$F$505,$M42))) | G42: =IF($M42=0,"",IF(INDEX('Line Detail'!$G$6:$G$505,$M42)="","",INDEX('Line Detail'!$G$6:$G$505,$M42))) | H42: =IF($M42=0,"",IF(INDEX('Line Detail'!$H$6:$H$505,$M42)="","",INDEX('Line Detail'!$H$6:$H$505,$M42))) | I42: =IF($M42=0,"",IF(INDEX('Line Detail'!$O$6:$O$505,$M42)="","",INDEX('Line Detail'!$O$6:$O$505,$M42))) | J42: =IF($M42=0,"",IF(INDEX('Line Detail'!$R$6:$R$505,$M42)="","",INDEX('Line Detail'!$R$6:$R$505,$M42))) | K42: =IF($M42=0,"",IF(INDEX('Line Detail'!$S$6:$S$505,$M42)="","",INDEX('Line Detail'!$S$6:$S$505,$M42))) | M42: =IFERROR(MATCH(37,'Line Detail'!$W$6:$W$505,0),0) -> 0
A43: =IF($M43=0,"",38) | B43: =IF($M43=0,"",IF(INDEX('Line Detail'!$B$6:$B$505,$M43)="","",INDEX('Line Detail'!$B$6:$B$505,$M43))) | C43: =IF($M43=0,"",IF(INDEX('Line Detail'!$C$6:$C$505,$M43)="","",INDEX('Line Detail'!$C$6:$C$505,$M43))) | D43: =IF($M43=0,"",IF(INDEX('Line Detail'!$D$6:$D$505,$M43)="","",INDEX('Line Detail'!$D$6:$D$505,$M43))) | E43: =IF($M43=0,"",IF(INDEX('Line Detail'!$E$6:$E$505,$M43)="","",INDEX('Line Detail'!$E$6:$E$505,$M43))) | F43: =IF($M43=0,"",IF(INDEX('Line Detail'!$F$6:$F$505,$M43)="","",INDEX('Line Detail'!$F$6:$F$505,$M43))) | G43: =IF($M43=0,"",IF(INDEX('Line Detail'!$G$6:$G$505,$M43)="","",INDEX('Line Detail'!$G$6:$G$505,$M43))) | H43: =IF($M43=0,"",IF(INDEX('Line Detail'!$H$6:$H$505,$M43)="","",INDEX('Line Detail'!$H$6:$H$505,$M43))) | I43: =IF($M43=0,"",IF(INDEX('Line Detail'!$O$6:$O$505,$M43)="","",INDEX('Line Detail'!$O$6:$O$505,$M43))) | J43: =IF($M43=0,"",IF(INDEX('Line Detail'!$R$6:$R$505,$M43)="","",INDEX('Line Detail'!$R$6:$R$505,$M43))) | K43: =IF($M43=0,"",IF(INDEX('Line Detail'!$S$6:$S$505,$M43)="","",INDEX('Line Detail'!$S$6:$S$505,$M43))) | M43: =IFERROR(MATCH(38,'Line Detail'!$W$6:$W$505,0),0) -> 0
A44: =IF($M44=0,"",39) | B44: =IF($M44=0,"",IF(INDEX('Line Detail'!$B$6:$B$505,$M44)="","",INDEX('Line Detail'!$B$6:$B$505,$M44))) | C44: =IF($M44=0,"",IF(INDEX('Line Detail'!$C$6:$C$505,$M44)="","",INDEX('Line Detail'!$C$6:$C$505,$M44))) | D44: =IF($M44=0,"",IF(INDEX('Line Detail'!$D$6:$D$505,$M44)="","",INDEX('Line Detail'!$D$6:$D$505,$M44))) | E44: =IF($M44=0,"",IF(INDEX('Line Detail'!$E$6:$E$505,$M44)="","",INDEX('Line Detail'!$E$6:$E$505,$M44))) | F44: =IF($M44=0,"",IF(INDEX('Line Detail'!$F$6:$F$505,$M44)="","",INDEX('Line Detail'!$F$6:$F$505,$M44))) | G44: =IF($M44=0,"",IF(INDEX('Line Detail'!$G$6:$G$505,$M44)="","",INDEX('Line Detail'!$G$6:$G$505,$M44))) | H44: =IF($M44=0,"",IF(INDEX('Line Detail'!$H$6:$H$505,$M44)="","",INDEX('Line Detail'!$H$6:$H$505,$M44))) | I44: =IF($M44=0,"",IF(INDEX('Line Detail'!$O$6:$O$505,$M44)="","",INDEX('Line Detail'!$O$6:$O$505,$M44))) | J44: =IF($M44=0,"",IF(INDEX('Line Detail'!$R$6:$R$505,$M44)="","",INDEX('Line Detail'!$R$6:$R$505,$M44))) | K44: =IF($M44=0,"",IF(INDEX('Line Detail'!$S$6:$S$505,$M44)="","",INDEX('Line Detail'!$S$6:$S$505,$M44))) | M44: =IFERROR(MATCH(39,'Line Detail'!$W$6:$W$505,0),0) -> 0
A45: =IF($M45=0,"",40) | B45: =IF($M45=0,"",IF(INDEX('Line Detail'!$B$6:$B$505,$M45)="","",INDEX('Line Detail'!$B$6:$B$505,$M45))) | C45: =IF($M45=0,"",IF(INDEX('Line Detail'!$C$6:$C$505,$M45)="","",INDEX('Line Detail'!$C$6:$C$505,$M45))) | D45: =IF($M45=0,"",IF(INDEX('Line Detail'!$D$6:$D$505,$M45)="","",INDEX('Line Detail'!$D$6:$D$505,$M45))) | E45: =IF($M45=0,"",IF(INDEX('Line Detail'!$E$6:$E$505,$M45)="","",INDEX('Line Detail'!$E$6:$E$505,$M45))) | F45: =IF($M45=0,"",IF(INDEX('Line Detail'!$F$6:$F$505,$M45)="","",INDEX('Line Detail'!$F$6:$F$505,$M45))) | G45: =IF($M45=0,"",IF(INDEX('Line Detail'!$G$6:$G$505,$M45)="","",INDEX('Line Detail'!$G$6:$G$505,$M45))) | H45: =IF($M45=0,"",IF(INDEX('Line Detail'!$H$6:$H$505,$M45)="","",INDEX('Line Detail'!$H$6:$H$505,$M45))) | I45: =IF($M45=0,"",IF(INDEX('Line Detail'!$O$6:$O$505,$M45)="","",INDEX('Line Detail'!$O$6:$O$505,$M45))) | J45: =IF($M45=0,"",IF(INDEX('Line Detail'!$R$6:$R$505,$M45)="","",INDEX('Line Detail'!$R$6:$R$505,$M45))) | K45: =IF($M45=0,"",IF(INDEX('Line Detail'!$S$6:$S$505,$M45)="","",INDEX('Line Detail'!$S$6:$S$505,$M45))) | M45: =IFERROR(MATCH(40,'Line Detail'!$W$6:$W$505,0),0) -> 0
A46: =IF($M46=0,"",41) | B46: =IF($M46=0,"",IF(INDEX('Line Detail'!$B$6:$B$505,$M46)="","",INDEX('Line Detail'!$B$6:$B$505,$M46))) | C46: =IF($M46=0,"",IF(INDEX('Line Detail'!$C$6:$C$505,$M46)="","",INDEX('Line Detail'!$C$6:$C$505,$M46))) | D46: =IF($M46=0,"",IF(INDEX('Line Detail'!$D$6:$D$505,$M46)="","",INDEX('Line Detail'!$D$6:$D$505,$M46))) | E46: =IF($M46=0,"",IF(INDEX('Line Detail'!$E$6:$E$505,$M46)="","",INDEX('Line Detail'!$E$6:$E$505,$M46))) | F46: =IF($M46=0,"",IF(INDEX('Line Detail'!$F$6:$F$505,$M46)="","",INDEX('Line Detail'!$F$6:$F$505,$M46))) | G46: =IF($M46=0,"",IF(INDEX('Line Detail'!$G$6:$G$505,$M46)="","",INDEX('Line Detail'!$G$6:$G$505,$M46))) | H46: =IF($M46=0,"",IF(INDEX('Line Detail'!$H$6:$H$505,$M46)="","",INDEX('Line Detail'!$H$6:$H$505,$M46))) | I46: =IF($M46=0,"",IF(INDEX('Line Detail'!$O$6:$O$505,$M46)="","",INDEX('Line Detail'!$O$6:$O$505,$M46))) | J46: =IF($M46=0,"",IF(INDEX('Line Detail'!$R$6:$R$505,$M46)="","",INDEX('Line Detail'!$R$6:$R$505,$M46))) | K46: =IF($M46=0,"",IF(INDEX('Line Detail'!$S$6:$S$505,$M46)="","",INDEX('Line Detail'!$S$6:$S$505,$M46))) | M46: =IFERROR(MATCH(41,'Line Detail'!$W$6:$W$505,0),0) -> 0
A47: =IF($M47=0,"",42) | B47: =IF($M47=0,"",IF(INDEX('Line Detail'!$B$6:$B$505,$M47)="","",INDEX('Line Detail'!$B$6:$B$505,$M47))) | C47: =IF($M47=0,"",IF(INDEX('Line Detail'!$C$6:$C$505,$M47)="","",INDEX('Line Detail'!$C$6:$C$505,$M47))) | D47: =IF($M47=0,"",IF(INDEX('Line Detail'!$D$6:$D$505,$M47)="","",INDEX('Line Detail'!$D$6:$D$505,$M47))) | E47: =IF($M47=0,"",IF(INDEX('Line Detail'!$E$6:$E$505,$M47)="","",INDEX('Line Detail'!$E$6:$E$505,$M47))) | F47: =IF($M47=0,"",IF(INDEX('Line Detail'!$F$6:$F$505,$M47)="","",INDEX('Line Detail'!$F$6:$F$505,$M47))) | G47: =IF($M47=0,"",IF(INDEX('Line Detail'!$G$6:$G$505,$M47)="","",INDEX('Line Detail'!$G$6:$G$505,$M47))) | H47: =IF($M47=0,"",IF(INDEX('Line Detail'!$H$6:$H$505,$M47)="","",INDEX('Line Detail'!$H$6:$H$505,$M47))) | I47: =IF($M47=0,"",IF(INDEX('Line Detail'!$O$6:$O$505,$M47)="","",INDEX('Line Detail'!$O$6:$O$505,$M47))) | J47: =IF($M47=0,"",IF(INDEX('Line Detail'!$R$6:$R$505,$M47)="","",INDEX('Line Detail'!$R$6:$R$505,$M47))) | K47: =IF($M47=0,"",IF(INDEX('Line Detail'!$S$6:$S$505,$M47)="","",INDEX('Line Detail'!$S$6:$S$505,$M47))) | M47: =IFERROR(MATCH(42,'Line Detail'!$W$6:$W$505,0),0) -> 0
A48: =IF($M48=0,"",43) | B48: =IF($M48=0,"",IF(INDEX('Line Detail'!$B$6:$B$505,$M48)="","",INDEX('Line Detail'!$B$6:$B$505,$M48))) | C48: =IF($M48=0,"",IF(INDEX('Line Detail'!$C$6:$C$505,$M48)="","",INDEX('Line Detail'!$C$6:$C$505,$M48))) | D48: =IF($M48=0,"",IF(INDEX('Line Detail'!$D$6:$D$505,$M48)="","",INDEX('Line Detail'!$D$6:$D$505,$M48))) | E48: =IF($M48=0,"",IF(INDEX('Line Detail'!$E$6:$E$505,$M48)="","",INDEX('Line Detail'!$E$6:$E$505,$M48))) | F48: =IF($M48=0,"",IF(INDEX('Line Detail'!$F$6:$F$505,$M48)="","",INDEX('Line Detail'!$F$6:$F$505,$M48))) | G48: =IF($M48=0,"",IF(INDEX('Line Detail'!$G$6:$G$505,$M48)="","",INDEX('Line Detail'!$G$6:$G$505,$M48))) | H48: =IF($M48=0,"",IF(INDEX('Line Detail'!$H$6:$H$505,$M48)="","",INDEX('Line Detail'!$H$6:$H$505,$M48))) | I48: =IF($M48=0,"",IF(INDEX('Line Detail'!$O$6:$O$505,$M48)="","",INDEX('Line Detail'!$O$6:$O$505,$M48))) | J48: =IF($M48=0,"",IF(INDEX('Line Detail'!$R$6:$R$505,$M48)="","",INDEX('Line Detail'!$R$6:$R$505,$M48))) | K48: =IF($M48=0,"",IF(INDEX('Line Detail'!$S$6:$S$505,$M48)="","",INDEX('Line Detail'!$S$6:$S$505,$M48))) | M48: =IFERROR(MATCH(43,'Line Detail'!$W$6:$W$505,0),0) -> 0
A49: =IF($M49=0,"",44) | B49: =IF($M49=0,"",IF(INDEX('Line Detail'!$B$6:$B$505,$M49)="","",INDEX('Line Detail'!$B$6:$B$505,$M49))) | C49: =IF($M49=0,"",IF(INDEX('Line Detail'!$C$6:$C$505,$M49)="","",INDEX('Line Detail'!$C$6:$C$505,$M49))) | D49: =IF($M49=0,"",IF(INDEX('Line Detail'!$D$6:$D$505,$M49)="","",INDEX('Line Detail'!$D$6:$D$505,$M49))) | E49: =IF($M49=0,"",IF(INDEX('Line Detail'!$E$6:$E$505,$M49)="","",INDEX('Line Detail'!$E$6:$E$505,$M49))) | F49: =IF($M49=0,"",IF(INDEX('Line Detail'!$F$6:$F$505,$M49)="","",INDEX('Line Detail'!$F$6:$F$505,$M49))) | G49: =IF($M49=0,"",IF(INDEX('Line Detail'!$G$6:$G$505,$M49)="","",INDEX('Line Detail'!$G$6:$G$505,$M49))) | H49: =IF($M49=0,"",IF(INDEX('Line Detail'!$H$6:$H$505,$M49)="","",INDEX('Line Detail'!$H$6:$H$505,$M49))) | I49: =IF($M49=0,"",IF(INDEX('Line Detail'!$O$6:$O$505,$M49)="","",INDEX('Line Detail'!$O$6:$O$505,$M49))) | J49: =IF($M49=0,"",IF(INDEX('Line Detail'!$R$6:$R$505,$M49)="","",INDEX('Line Detail'!$R$6:$R$505,$M49))) | K49: =IF($M49=0,"",IF(INDEX('Line Detail'!$S$6:$S$505,$M49)="","",INDEX('Line Detail'!$S$6:$S$505,$M49))) | M49: =IFERROR(MATCH(44,'Line Detail'!$W$6:$W$505,0),0) -> 0
A50: =IF($M50=0,"",45) | B50: =IF($M50=0,"",IF(INDEX('Line Detail'!$B$6:$B$505,$M50)="","",INDEX('Line Detail'!$B$6:$B$505,$M50))) | C50: =IF($M50=0,"",IF(INDEX('Line Detail'!$C$6:$C$505,$M50)="","",INDEX('Line Detail'!$C$6:$C$505,$M50))) | D50: =IF($M50=0,"",IF(INDEX('Line Detail'!$D$6:$D$505,$M50)="","",INDEX('Line Detail'!$D$6:$D$505,$M50))) | E50: =IF($M50=0,"",IF(INDEX('Line Detail'!$E$6:$E$505,$M50)="","",INDEX('Line Detail'!$E$6:$E$505,$M50))) | F50: =IF($M50=0,"",IF(INDEX('Line Detail'!$F$6:$F$505,$M50)="","",INDEX('Line Detail'!$F$6:$F$505,$M50))) | G50: =IF($M50=0,"",IF(INDEX('Line Detail'!$G$6:$G$505,$M50)="","",INDEX('Line Detail'!$G$6:$G$505,$M50))) | H50: =IF($M50=0,"",IF(INDEX('Line Detail'!$H$6:$H$505,$M50)="","",INDEX('Line Detail'!$H$6:$H$505,$M50))) | I50: =IF($M50=0,"",IF(INDEX('Line Detail'!$O$6:$O$505,$M50)="","",INDEX('Line Detail'!$O$6:$O$505,$M50))) | J50: =IF($M50=0,"",IF(INDEX('Line Detail'!$R$6:$R$505,$M50)="","",INDEX('Line Detail'!$R$6:$R$505,$M50))) | K50: =IF($M50=0,"",IF(INDEX('Line Detail'!$S$6:$S$505,$M50)="","",INDEX('Line Detail'!$S$6:$S$505,$M50))) | M50: =IFERROR(MATCH(45,'Line Detail'!$W$6:$W$505,0),0) -> 0
A51: =IF($M51=0,"",46) | B51: =IF($M51=0,"",IF(INDEX('Line Detail'!$B$6:$B$505,$M51)="","",INDEX('Line Detail'!$B$6:$B$505,$M51))) | C51: =IF($M51=0,"",IF(INDEX('Line Detail'!$C$6:$C$505,$M51)="","",INDEX('Line Detail'!$C$6:$C$505,$M51))) | D51: =IF($M51=0,"",IF(INDEX('Line Detail'!$D$6:$D$505,$M51)="","",INDEX('Line Detail'!$D$6:$D$505,$M51))) | E51: =IF($M51=0,"",IF(INDEX('Line Detail'!$E$6:$E$505,$M51)="","",INDEX('Line Detail'!$E$6:$E$505,$M51))) | F51: =IF($M51=0,"",IF(INDEX('Line Detail'!$F$6:$F$505,$M51)="","",INDEX('Line Detail'!$F$6:$F$505,$M51))) | G51: =IF($M51=0,"",IF(INDEX('Line Detail'!$G$6:$G$505,$M51)="","",INDEX('Line Detail'!$G$6:$G$505,$M51))) | H51: =IF($M51=0,"",IF(INDEX('Line Detail'!$H$6:$H$505,$M51)="","",INDEX('Line Detail'!$H$6:$H$505,$M51))) | I51: =IF($M51=0,"",IF(INDEX('Line Detail'!$O$6:$O$505,$M51)="","",INDEX('Line Detail'!$O$6:$O$505,$M51))) | J51: =IF($M51=0,"",IF(INDEX('Line Detail'!$R$6:$R$505,$M51)="","",INDEX('Line Detail'!$R$6:$R$505,$M51))) | K51: =IF($M51=0,"",IF(INDEX('Line Detail'!$S$6:$S$505,$M51)="","",INDEX('Line Detail'!$S$6:$S$505,$M51))) | M51: =IFERROR(MATCH(46,'Line Detail'!$W$6:$W$505,0),0) -> 0
A52: =IF($M52=0,"",47) | B52: =IF($M52=0,"",IF(INDEX('Line Detail'!$B$6:$B$505,$M52)="","",INDEX('Line Detail'!$B$6:$B$505,$M52))) | C52: =IF($M52=0,"",IF(INDEX('Line Detail'!$C$6:$C$505,$M52)="","",INDEX('Line Detail'!$C$6:$C$505,$M52))) | D52: =IF($M52=0,"",IF(INDEX('Line Detail'!$D$6:$D$505,$M52)="","",INDEX('Line Detail'!$D$6:$D$505,$M52))) | E52: =IF($M52=0,"",IF(INDEX('Line Detail'!$E$6:$E$505,$M52)="","",INDEX('Line Detail'!$E$6:$E$505,$M52))) | F52: =IF($M52=0,"",IF(INDEX('Line Detail'!$F$6:$F$505,$M52)="","",INDEX('Line Detail'!$F$6:$F$505,$M52))) | G52: =IF($M52=0,"",IF(INDEX('Line Detail'!$G$6:$G$505,$M52)="","",INDEX('Line Detail'!$G$6:$G$505,$M52))) | H52: =IF($M52=0,"",IF(INDEX('Line Detail'!$H$6:$H$505,$M52)="","",INDEX('Line Detail'!$H$6:$H$505,$M52))) | I52: =IF($M52=0,"",IF(INDEX('Line Detail'!$O$6:$O$505,$M52)="","",INDEX('Line Detail'!$O$6:$O$505,$M52))) | J52: =IF($M52=0,"",IF(INDEX('Line Detail'!$R$6:$R$505,$M52)="","",INDEX('Line Detail'!$R$6:$R$505,$M52))) | K52: =IF($M52=0,"",IF(INDEX('Line Detail'!$S$6:$S$505,$M52)="","",INDEX('Line Detail'!$S$6:$S$505,$M52))) | M52: =IFERROR(MATCH(47,'Line Detail'!$W$6:$W$505,0),0) -> 0
A53: =IF($M53=0,"",48) | B53: =IF($M53=0,"",IF(INDEX('Line Detail'!$B$6:$B$505,$M53)="","",INDEX('Line Detail'!$B$6:$B$505,$M53))) | C53: =IF($M53=0,"",IF(INDEX('Line Detail'!$C$6:$C$505,$M53)="","",INDEX('Line Detail'!$C$6:$C$505,$M53))) | D53: =IF($M53=0,"",IF(INDEX('Line Detail'!$D$6:$D$505,$M53)="","",INDEX('Line Detail'!$D$6:$D$505,$M53))) | E53: =IF($M53=0,"",IF(INDEX('Line Detail'!$E$6:$E$505,$M53)="","",INDEX('Line Detail'!$E$6:$E$505,$M53))) | F53: =IF($M53=0,"",IF(INDEX('Line Detail'!$F$6:$F$505,$M53)="","",INDEX('Line Detail'!$F$6:$F$505,$M53))) | G53: =IF($M53=0,"",IF(INDEX('Line Detail'!$G$6:$G$505,$M53)="","",INDEX('Line Detail'!$G$6:$G$505,$M53))) | H53: =IF($M53=0,"",IF(INDEX('Line Detail'!$H$6:$H$505,$M53)="","",INDEX('Line Detail'!$H$6:$H$505,$M53))) | I53: =IF($M53=0,"",IF(INDEX('Line Detail'!$O$6:$O$505,$M53)="","",INDEX('Line Detail'!$O$6:$O$505,$M53))) | J53: =IF($M53=0,"",IF(INDEX('Line Detail'!$R$6:$R$505,$M53)="","",INDEX('Line Detail'!$R$6:$R$505,$M53))) | K53: =IF($M53=0,"",IF(INDEX('Line Detail'!$S$6:$S$505,$M53)="","",INDEX('Line Detail'!$S$6:$S$505,$M53))) | M53: =IFERROR(MATCH(48,'Line Detail'!$W$6:$W$505,0),0) -> 0
A54: =IF($M54=0,"",49) | B54: =IF($M54=0,"",IF(INDEX('Line Detail'!$B$6:$B$505,$M54)="","",INDEX('Line Detail'!$B$6:$B$505,$M54))) | C54: =IF($M54=0,"",IF(INDEX('Line Detail'!$C$6:$C$505,$M54)="","",INDEX('Line Detail'!$C$6:$C$505,$M54))) | D54: =IF($M54=0,"",IF(INDEX('Line Detail'!$D$6:$D$505,$M54)="","",INDEX('Line Detail'!$D$6:$D$505,$M54))) | E54: =IF($M54=0,"",IF(INDEX('Line Detail'!$E$6:$E$505,$M54)="","",INDEX('Line Detail'!$E$6:$E$505,$M54))) | F54: =IF($M54=0,"",IF(INDEX('Line Detail'!$F$6:$F$505,$M54)="","",INDEX('Line Detail'!$F$6:$F$505,$M54))) | G54: =IF($M54=0,"",IF(INDEX('Line Detail'!$G$6:$G$505,$M54)="","",INDEX('Line Detail'!$G$6:$G$505,$M54))) | H54: =IF($M54=0,"",IF(INDEX('Line Detail'!$H$6:$H$505,$M54)="","",INDEX('Line Detail'!$H$6:$H$505,$M54))) | I54: =IF($M54=0,"",IF(INDEX('Line Detail'!$O$6:$O$505,$M54)="","",INDEX('Line Detail'!$O$6:$O$505,$M54))) | J54: =IF($M54=0,"",IF(INDEX('Line Detail'!$R$6:$R$505,$M54)="","",INDEX('Line Detail'!$R$6:$R$505,$M54))) | K54: =IF($M54=0,"",IF(INDEX('Line Detail'!$S$6:$S$505,$M54)="","",INDEX('Line Detail'!$S$6:$S$505,$M54))) | M54: =IFERROR(MATCH(49,'Line Detail'!$W$6:$W$505,0),0) -> 0
A55: =IF($M55=0,"",50) | B55: =IF($M55=0,"",IF(INDEX('Line Detail'!$B$6:$B$505,$M55)="","",INDEX('Line Detail'!$B$6:$B$505,$M55))) | C55: =IF($M55=0,"",IF(INDEX('Line Detail'!$C$6:$C$505,$M55)="","",INDEX('Line Detail'!$C$6:$C$505,$M55))) | D55: =IF($M55=0,"",IF(INDEX('Line Detail'!$D$6:$D$505,$M55)="","",INDEX('Line Detail'!$D$6:$D$505,$M55))) | E55: =IF($M55=0,"",IF(INDEX('Line Detail'!$E$6:$E$505,$M55)="","",INDEX('Line Detail'!$E$6:$E$505,$M55))) | F55: =IF($M55=0,"",IF(INDEX('Line Detail'!$F$6:$F$505,$M55)="","",INDEX('Line Detail'!$F$6:$F$505,$M55))) | G55: =IF($M55=0,"",IF(INDEX('Line Detail'!$G$6:$G$505,$M55)="","",INDEX('Line Detail'!$G$6:$G$505,$M55))) | H55: =IF($M55=0,"",IF(INDEX('Line Detail'!$H$6:$H$505,$M55)="","",INDEX('Line Detail'!$H$6:$H$505,$M55))) | I55: =IF($M55=0,"",IF(INDEX('Line Detail'!$O$6:$O$505,$M55)="","",INDEX('Line Detail'!$O$6:$O$505,$M55))) | J55: =IF($M55=0,"",IF(INDEX('Line Detail'!$R$6:$R$505,$M55)="","",INDEX('Line Detail'!$R$6:$R$505,$M55))) | K55: =IF($M55=0,"",IF(INDEX('Line Detail'!$S$6:$S$505,$M55)="","",INDEX('Line Detail'!$S$6:$S$505,$M55))) | M55: =IFERROR(MATCH(50,'Line Detail'!$W$6:$W$505,0),0) -> 0
A56: =IF($M56=0,"",51) | B56: =IF($M56=0,"",IF(INDEX('Line Detail'!$B$6:$B$505,$M56)="","",INDEX('Line Detail'!$B$6:$B$505,$M56))) | C56: =IF($M56=0,"",IF(INDEX('Line Detail'!$C$6:$C$505,$M56)="","",INDEX('Line Detail'!$C$6:$C$505,$M56))) | D56: =IF($M56=0,"",IF(INDEX('Line Detail'!$D$6:$D$505,$M56)="","",INDEX('Line Detail'!$D$6:$D$505,$M56))) | E56: =IF($M56=0,"",IF(INDEX('Line Detail'!$E$6:$E$505,$M56)="","",INDEX('Line Detail'!$E$6:$E$505,$M56))) | F56: =IF($M56=0,"",IF(INDEX('Line Detail'!$F$6:$F$505,$M56)="","",INDEX('Line Detail'!$F$6:$F$505,$M56))) | G56: =IF($M56=0,"",IF(INDEX('Line Detail'!$G$6:$G$505,$M56)="","",INDEX('Line Detail'!$G$6:$G$505,$M56))) | H56: =IF($M56=0,"",IF(INDEX('Line Detail'!$H$6:$H$505,$M56)="","",INDEX('Line Detail'!$H$6:$H$505,$M56))) | I56: =IF($M56=0,"",IF(INDEX('Line Detail'!$O$6:$O$505,$M56)="","",INDEX('Line Detail'!$O$6:$O$505,$M56))) | J56: =IF($M56=0,"",IF(INDEX('Line Detail'!$R$6:$R$505,$M56)="","",INDEX('Line Detail'!$R$6:$R$505,$M56))) | K56: =IF($M56=0,"",IF(INDEX('Line Detail'!$S$6:$S$505,$M56)="","",INDEX('Line Detail'!$S$6:$S$505,$M56))) | M56: =IFERROR(MATCH(51,'Line Detail'!$W$6:$W$505,0),0) -> 0
A57: =IF($M57=0,"",52) | B57: =IF($M57=0,"",IF(INDEX('Line Detail'!$B$6:$B$505,$M57)="","",INDEX('Line Detail'!$B$6:$B$505,$M57))) | C57: =IF($M57=0,"",IF(INDEX('Line Detail'!$C$6:$C$505,$M57)="","",INDEX('Line Detail'!$C$6:$C$505,$M57))) | D57: =IF($M57=0,"",IF(INDEX('Line Detail'!$D$6:$D$505,$M57)="","",INDEX('Line Detail'!$D$6:$D$505,$M57))) | E57: =IF($M57=0,"",IF(INDEX('Line Detail'!$E$6:$E$505,$M57)="","",INDEX('Line Detail'!$E$6:$E$505,$M57))) | F57: =IF($M57=0,"",IF(INDEX('Line Detail'!$F$6:$F$505,$M57)="","",INDEX('Line Detail'!$F$6:$F$505,$M57))) | G57: =IF($M57=0,"",IF(INDEX('Line Detail'!$G$6:$G$505,$M57)="","",INDEX('Line Detail'!$G$6:$G$505,$M57))) | H57: =IF($M57=0,"",IF(INDEX('Line Detail'!$H$6:$H$505,$M57)="","",INDEX('Line Detail'!$H$6:$H$505,$M57))) | I57: =IF($M57=0,"",IF(INDEX('Line Detail'!$O$6:$O$505,$M57)="","",INDEX('Line Detail'!$O$6:$O$505,$M57))) | J57: =IF($M57=0,"",IF(INDEX('Line Detail'!$R$6:$R$505,$M57)="","",INDEX('Line Detail'!$R$6:$R$505,$M57))) | K57: =IF($M57=0,"",IF(INDEX('Line Detail'!$S$6:$S$505,$M57)="","",INDEX('Line Detail'!$S$6:$S$505,$M57))) | M57: =IFERROR(MATCH(52,'Line Detail'!$W$6:$W$505,0),0) -> 0
A58: =IF($M58=0,"",53) | B58: =IF($M58=0,"",IF(INDEX('Line Detail'!$B$6:$B$505,$M58)="","",INDEX('Line Detail'!$B$6:$B$505,$M58))) | C58: =IF($M58=0,"",IF(INDEX('Line Detail'!$C$6:$C$505,$M58)="","",INDEX('Line Detail'!$C$6:$C$505,$M58))) | D58: =IF($M58=0,"",IF(INDEX('Line Detail'!$D$6:$D$505,$M58)="","",INDEX('Line Detail'!$D$6:$D$505,$M58))) | E58: =IF($M58=0,"",IF(INDEX('Line Detail'!$E$6:$E$505,$M58)="","",INDEX('Line Detail'!$E$6:$E$505,$M58))) | F58: =IF($M58=0,"",IF(INDEX('Line Detail'!$F$6:$F$505,$M58)="","",INDEX('Line Detail'!$F$6:$F$505,$M58))) | G58: =IF($M58=0,"",IF(INDEX('Line Detail'!$G$6:$G$505,$M58)="","",INDEX('Line Detail'!$G$6:$G$505,$M58))) | H58: =IF($M58=0,"",IF(INDEX('Line Detail'!$H$6:$H$505,$M58)="","",INDEX('Line Detail'!$H$6:$H$505,$M58))) | I58: =IF($M58=0,"",IF(INDEX('Line Detail'!$O$6:$O$505,$M58)="","",INDEX('Line Detail'!$O$6:$O$505,$M58))) | J58: =IF($M58=0,"",IF(INDEX('Line Detail'!$R$6:$R$505,$M58)="","",INDEX('Line Detail'!$R$6:$R$505,$M58))) | K58: =IF($M58=0,"",IF(INDEX('Line Detail'!$S$6:$S$505,$M58)="","",INDEX('Line Detail'!$S$6:$S$505,$M58))) | M58: =IFERROR(MATCH(53,'Line Detail'!$W$6:$W$505,0),0) -> 0
A59: =IF($M59=0,"",54) | B59: =IF($M59=0,"",IF(INDEX('Line Detail'!$B$6:$B$505,$M59)="","",INDEX('Line Detail'!$B$6:$B$505,$M59))) | C59: =IF($M59=0,"",IF(INDEX('Line Detail'!$C$6:$C$505,$M59)="","",INDEX('Line Detail'!$C$6:$C$505,$M59))) | D59: =IF($M59=0,"",IF(INDEX('Line Detail'!$D$6:$D$505,$M59)="","",INDEX('Line Detail'!$D$6:$D$505,$M59))) | E59: =IF($M59=0,"",IF(INDEX('Line Detail'!$E$6:$E$505,$M59)="","",INDEX('Line Detail'!$E$6:$E$505,$M59))) | F59: =IF($M59=0,"",IF(INDEX('Line Detail'!$F$6:$F$505,$M59)="","",INDEX('Line Detail'!$F$6:$F$505,$M59))) | G59: =IF($M59=0,"",IF(INDEX('Line Detail'!$G$6:$G$505,$M59)="","",INDEX('Line Detail'!$G$6:$G$505,$M59))) | H59: =IF($M59=0,"",IF(INDEX('Line Detail'!$H$6:$H$505,$M59)="","",INDEX('Line Detail'!$H$6:$H$505,$M59))) | I59: =IF($M59=0,"",IF(INDEX('Line Detail'!$O$6:$O$505,$M59)="","",INDEX('Line Detail'!$O$6:$O$505,$M59))) | J59: =IF($M59=0,"",IF(INDEX('Line Detail'!$R$6:$R$505,$M59)="","",INDEX('Line Detail'!$R$6:$R$505,$M59))) | K59: =IF($M59=0,"",IF(INDEX('Line Detail'!$S$6:$S$505,$M59)="","",INDEX('Line Detail'!$S$6:$S$505,$M59))) | M59: =IFERROR(MATCH(54,'Line Detail'!$W$6:$W$505,0),0) -> 0
A60: =IF($M60=0,"",55) | B60: =IF($M60=0,"",IF(INDEX('Line Detail'!$B$6:$B$505,$M60)="","",INDEX('Line Detail'!$B$6:$B$505,$M60))) | C60: =IF($M60=0,"",IF(INDEX('Line Detail'!$C$6:$C$505,$M60)="","",INDEX('Line Detail'!$C$6:$C$505,$M60))) | D60: =IF($M60=0,"",IF(INDEX('Line Detail'!$D$6:$D$505,$M60)="","",INDEX('Line Detail'!$D$6:$D$505,$M60))) | E60: =IF($M60=0,"",IF(INDEX('Line Detail'!$E$6:$E$505,$M60)="","",INDEX('Line Detail'!$E$6:$E$505,$M60))) | F60: =IF($M60=0,"",IF(INDEX('Line Detail'!$F$6:$F$505,$M60)="","",INDEX('Line Detail'!$F$6:$F$505,$M60))) | G60: =IF($M60=0,"",IF(INDEX('Line Detail'!$G$6:$G$505,$M60)="","",INDEX('Line Detail'!$G$6:$G$505,$M60))) | H60: =IF($M60=0,"",IF(INDEX('Line Detail'!$H$6:$H$505,$M60)="","",INDEX('Line Detail'!$H$6:$H$505,$M60))) | I60: =IF($M60=0,"",IF(INDEX('Line Detail'!$O$6:$O$505,$M60)="","",INDEX('Line Detail'!$O$6:$O$505,$M60))) | J60: =IF($M60=0,"",IF(INDEX('Line Detail'!$R$6:$R$505,$M60)="","",INDEX('Line Detail'!$R$6:$R$505,$M60))) | K60: =IF($M60=0,"",IF(INDEX('Line Detail'!$S$6:$S$505,$M60)="","",INDEX('Line Detail'!$S$6:$S$505,$M60))) | M60: =IFERROR(MATCH(55,'Line Detail'!$W$6:$W$505,0),0) -> 0
A61: =IF($M61=0,"",56) | B61: =IF($M61=0,"",IF(INDEX('Line Detail'!$B$6:$B$505,$M61)="","",INDEX('Line Detail'!$B$6:$B$505,$M61))) | C61: =IF($M61=0,"",IF(INDEX('Line Detail'!$C$6:$C$505,$M61)="","",INDEX('Line Detail'!$C$6:$C$505,$M61))) | D61: =IF($M61=0,"",IF(INDEX('Line Detail'!$D$6:$D$505,$M61)="","",INDEX('Line Detail'!$D$6:$D$505,$M61))) | E61: =IF($M61=0,"",IF(INDEX('Line Detail'!$E$6:$E$505,$M61)="","",INDEX('Line Detail'!$E$6:$E$505,$M61))) | F61: =IF($M61=0,"",IF(INDEX('Line Detail'!$F$6:$F$505,$M61)="","",INDEX('Line Detail'!$F$6:$F$505,$M61))) | G61: =IF($M61=0,"",IF(INDEX('Line Detail'!$G$6:$G$505,$M61)="","",INDEX('Line Detail'!$G$6:$G$505,$M61))) | H61: =IF($M61=0,"",IF(INDEX('Line Detail'!$H$6:$H$505,$M61)="","",INDEX('Line Detail'!$H$6:$H$505,$M61))) | I61: =IF($M61=0,"",IF(INDEX('Line Detail'!$O$6:$O$505,$M61)="","",INDEX('Line Detail'!$O$6:$O$505,$M61))) | J61: =IF($M61=0,"",IF(INDEX('Line Detail'!$R$6:$R$505,$M61)="","",INDEX('Line Detail'!$R$6:$R$505,$M61))) | K61: =IF($M61=0,"",IF(INDEX('Line Detail'!$S$6:$S$505,$M61)="","",INDEX('Line Detail'!$S$6:$S$505,$M61))) | M61: =IFERROR(MATCH(56,'Line Detail'!$W$6:$W$505,0),0) -> 0
A62: =IF($M62=0,"",57) | B62: =IF($M62=0,"",IF(INDEX('Line Detail'!$B$6:$B$505,$M62)="","",INDEX('Line Detail'!$B$6:$B$505,$M62))) | C62: =IF($M62=0,"",IF(INDEX('Line Detail'!$C$6:$C$505,$M62)="","",INDEX('Line Detail'!$C$6:$C$505,$M62))) | D62: =IF($M62=0,"",IF(INDEX('Line Detail'!$D$6:$D$505,$M62)="","",INDEX('Line Detail'!$D$6:$D$505,$M62))) | E62: =IF($M62=0,"",IF(INDEX('Line Detail'!$E$6:$E$505,$M62)="","",INDEX('Line Detail'!$E$6:$E$505,$M62))) | F62: =IF($M62=0,"",IF(INDEX('Line Detail'!$F$6:$F$505,$M62)="","",INDEX('Line Detail'!$F$6:$F$505,$M62))) | G62: =IF($M62=0,"",IF(INDEX('Line Detail'!$G$6:$G$505,$M62)="","",INDEX('Line Detail'!$G$6:$G$505,$M62))) | H62: =IF($M62=0,"",IF(INDEX('Line Detail'!$H$6:$H$505,$M62)="","",INDEX('Line Detail'!$H$6:$H$505,$M62))) | I62: =IF($M62=0,"",IF(INDEX('Line Detail'!$O$6:$O$505,$M62)="","",INDEX('Line Detail'!$O$6:$O$505,$M62))) | J62: =IF($M62=0,"",IF(INDEX('Line Detail'!$R$6:$R$505,$M62)="","",INDEX('Line Detail'!$R$6:$R$505,$M62))) | K62: =IF($M62=0,"",IF(INDEX('Line Detail'!$S$6:$S$505,$M62)="","",INDEX('Line Detail'!$S$6:$S$505,$M62))) | M62: =IFERROR(MATCH(57,'Line Detail'!$W$6:$W$505,0),0) -> 0
A63: =IF($M63=0,"",58) | B63: =IF($M63=0,"",IF(INDEX('Line Detail'!$B$6:$B$505,$M63)="","",INDEX('Line Detail'!$B$6:$B$505,$M63))) | C63: =IF($M63=0,"",IF(INDEX('Line Detail'!$C$6:$C$505,$M63)="","",INDEX('Line Detail'!$C$6:$C$505,$M63))) | D63: =IF($M63=0,"",IF(INDEX('Line Detail'!$D$6:$D$505,$M63)="","",INDEX('Line Detail'!$D$6:$D$505,$M63))) | E63: =IF($M63=0,"",IF(INDEX('Line Detail'!$E$6:$E$505,$M63)="","",INDEX('Line Detail'!$E$6:$E$505,$M63))) | F63: =IF($M63=0,"",IF(INDEX('Line Detail'!$F$6:$F$505,$M63)="","",INDEX('Line Detail'!$F$6:$F$505,$M63))) | G63: =IF($M63=0,"",IF(INDEX('Line Detail'!$G$6:$G$505,$M63)="","",INDEX('Line Detail'!$G$6:$G$505,$M63))) | H63: =IF($M63=0,"",IF(INDEX('Line Detail'!$H$6:$H$505,$M63)="","",INDEX('Line Detail'!$H$6:$H$505,$M63))) | I63: =IF($M63=0,"",IF(INDEX('Line Detail'!$O$6:$O$505,$M63)="","",INDEX('Line Detail'!$O$6:$O$505,$M63))) | J63: =IF($M63=0,"",IF(INDEX('Line Detail'!$R$6:$R$505,$M63)="","",INDEX('Line Detail'!$R$6:$R$505,$M63))) | K63: =IF($M63=0,"",IF(INDEX('Line Detail'!$S$6:$S$505,$M63)="","",INDEX('Line Detail'!$S$6:$S$505,$M63))) | M63: =IFERROR(MATCH(58,'Line Detail'!$W$6:$W$505,0),0) -> 0
A64: =IF($M64=0,"",59) | B64: =IF($M64=0,"",IF(INDEX('Line Detail'!$B$6:$B$505,$M64)="","",INDEX('Line Detail'!$B$6:$B$505,$M64))) | C64: =IF($M64=0,"",IF(INDEX('Line Detail'!$C$6:$C$505,$M64)="","",INDEX('Line Detail'!$C$6:$C$505,$M64))) | D64: =IF($M64=0,"",IF(INDEX('Line Detail'!$D$6:$D$505,$M64)="","",INDEX('Line Detail'!$D$6:$D$505,$M64))) | E64: =IF($M64=0,"",IF(INDEX('Line Detail'!$E$6:$E$505,$M64)="","",INDEX('Line Detail'!$E$6:$E$505,$M64))) | F64: =IF($M64=0,"",IF(INDEX('Line Detail'!$F$6:$F$505,$M64)="","",INDEX('Line Detail'!$F$6:$F$505,$M64))) | G64: =IF($M64=0,"",IF(INDEX('Line Detail'!$G$6:$G$505,$M64)="","",INDEX('Line Detail'!$G$6:$G$505,$M64))) | H64: =IF($M64=0,"",IF(INDEX('Line Detail'!$H$6:$H$505,$M64)="","",INDEX('Line Detail'!$H$6:$H$505,$M64))) | I64: =IF($M64=0,"",IF(INDEX('Line Detail'!$O$6:$O$505,$M64)="","",INDEX('Line Detail'!$O$6:$O$505,$M64))) | J64: =IF($M64=0,"",IF(INDEX('Line Detail'!$R$6:$R$505,$M64)="","",INDEX('Line Detail'!$R$6:$R$505,$M64))) | K64: =IF($M64=0,"",IF(INDEX('Line Detail'!$S$6:$S$505,$M64)="","",INDEX('Line Detail'!$S$6:$S$505,$M64))) | M64: =IFERROR(MATCH(59,'Line Detail'!$W$6:$W$505,0),0) -> 0
A65: =IF($M65=0,"",60) | B65: =IF($M65=0,"",IF(INDEX('Line Detail'!$B$6:$B$505,$M65)="","",INDEX('Line Detail'!$B$6:$B$505,$M65))) | C65: =IF($M65=0,"",IF(INDEX('Line Detail'!$C$6:$C$505,$M65)="","",INDEX('Line Detail'!$C$6:$C$505,$M65))) | D65: =IF($M65=0,"",IF(INDEX('Line Detail'!$D$6:$D$505,$M65)="","",INDEX('Line Detail'!$D$6:$D$505,$M65))) | E65: =IF($M65=0,"",IF(INDEX('Line Detail'!$E$6:$E$505,$M65)="","",INDEX('Line Detail'!$E$6:$E$505,$M65))) | F65: =IF($M65=0,"",IF(INDEX('Line Detail'!$F$6:$F$505,$M65)="","",INDEX('Line Detail'!$F$6:$F$505,$M65))) | G65: =IF($M65=0,"",IF(INDEX('Line Detail'!$G$6:$G$505,$M65)="","",INDEX('Line Detail'!$G$6:$G$505,$M65))) | H65: =IF($M65=0,"",IF(INDEX('Line Detail'!$H$6:$H$505,$M65)="","",INDEX('Line Detail'!$H$6:$H$505,$M65))) | I65: =IF($M65=0,"",IF(INDEX('Line Detail'!$O$6:$O$505,$M65)="","",INDEX('Line Detail'!$O$6:$O$505,$M65))) | J65: =IF($M65=0,"",IF(INDEX('Line Detail'!$R$6:$R$505,$M65)="","",INDEX('Line Detail'!$R$6:$R$505,$M65))) | K65: =IF($M65=0,"",IF(INDEX('Line Detail'!$S$6:$S$505,$M65)="","",INDEX('Line Detail'!$S$6:$S$505,$M65))) | M65: =IFERROR(MATCH(60,'Line Detail'!$W$6:$W$505,0),0) -> 0
A66: =IF($M66=0,"",61) | B66: =IF($M66=0,"",IF(INDEX('Line Detail'!$B$6:$B$505,$M66)="","",INDEX('Line Detail'!$B$6:$B$505,$M66))) | C66: =IF($M66=0,"",IF(INDEX('Line Detail'!$C$6:$C$505,$M66)="","",INDEX('Line Detail'!$C$6:$C$505,$M66))) | D66: =IF($M66=0,"",IF(INDEX('Line Detail'!$D$6:$D$505,$M66)="","",INDEX('Line Detail'!$D$6:$D$505,$M66))) | E66: =IF($M66=0,"",IF(INDEX('Line Detail'!$E$6:$E$505,$M66)="","",INDEX('Line Detail'!$E$6:$E$505,$M66))) | F66: =IF($M66=0,"",IF(INDEX('Line Detail'!$F$6:$F$505,$M66)="","",INDEX('Line Detail'!$F$6:$F$505,$M66))) | G66: =IF($M66=0,"",IF(INDEX('Line Detail'!$G$6:$G$505,$M66)="","",INDEX('Line Detail'!$G$6:$G$505,$M66))) | H66: =IF($M66=0,"",IF(INDEX('Line Detail'!$H$6:$H$505,$M66)="","",INDEX('Line Detail'!$H$6:$H$505,$M66))) | I66: =IF($M66=0,"",IF(INDEX('Line Detail'!$O$6:$O$505,$M66)="","",INDEX('Line Detail'!$O$6:$O$505,$M66))) | J66: =IF($M66=0,"",IF(INDEX('Line Detail'!$R$6:$R$505,$M66)="","",INDEX('Line Detail'!$R$6:$R$505,$M66))) | K66: =IF($M66=0,"",IF(INDEX('Line Detail'!$S$6:$S$505,$M66)="","",INDEX('Line Detail'!$S$6:$S$505,$M66))) | M66: =IFERROR(MATCH(61,'Line Detail'!$W$6:$W$505,0),0) -> 0
A67: =IF($M67=0,"",62) | B67: =IF($M67=0,"",IF(INDEX('Line Detail'!$B$6:$B$505,$M67)="","",INDEX('Line Detail'!$B$6:$B$505,$M67))) | C67: =IF($M67=0,"",IF(INDEX('Line Detail'!$C$6:$C$505,$M67)="","",INDEX('Line Detail'!$C$6:$C$505,$M67))) | D67: =IF($M67=0,"",IF(INDEX('Line Detail'!$D$6:$D$505,$M67)="","",INDEX('Line Detail'!$D$6:$D$505,$M67))) | E67: =IF($M67=0,"",IF(INDEX('Line Detail'!$E$6:$E$505,$M67)="","",INDEX('Line Detail'!$E$6:$E$505,$M67))) | F67: =IF($M67=0,"",IF(INDEX('Line Detail'!$F$6:$F$505,$M67)="","",INDEX('Line Detail'!$F$6:$F$505,$M67))) | G67: =IF($M67=0,"",IF(INDEX('Line Detail'!$G$6:$G$505,$M67)="","",INDEX('Line Detail'!$G$6:$G$505,$M67))) | H67: =IF($M67=0,"",IF(INDEX('Line Detail'!$H$6:$H$505,$M67)="","",INDEX('Line Detail'!$H$6:$H$505,$M67))) | I67: =IF($M67=0,"",IF(INDEX('Line Detail'!$O$6:$O$505,$M67)="","",INDEX('Line Detail'!$O$6:$O$505,$M67))) | J67: =IF($M67=0,"",IF(INDEX('Line Detail'!$R$6:$R$505,$M67)="","",INDEX('Line Detail'!$R$6:$R$505,$M67))) | K67: =IF($M67=0,"",IF(INDEX('Line Detail'!$S$6:$S$505,$M67)="","",INDEX('Line Detail'!$S$6:$S$505,$M67))) | M67: =IFERROR(MATCH(62,'Line Detail'!$W$6:$W$505,0),0) -> 0
A68: =IF($M68=0,"",63) | B68: =IF($M68=0,"",IF(INDEX('Line Detail'!$B$6:$B$505,$M68)="","",INDEX('Line Detail'!$B$6:$B$505,$M68))) | C68: =IF($M68=0,"",IF(INDEX('Line Detail'!$C$6:$C$505,$M68)="","",INDEX('Line Detail'!$C$6:$C$505,$M68))) | D68: =IF($M68=0,"",IF(INDEX('Line Detail'!$D$6:$D$505,$M68)="","",INDEX('Line Detail'!$D$6:$D$505,$M68))) | E68: =IF($M68=0,"",IF(INDEX('Line Detail'!$E$6:$E$505,$M68)="","",INDEX('Line Detail'!$E$6:$E$505,$M68))) | F68: =IF($M68=0,"",IF(INDEX('Line Detail'!$F$6:$F$505,$M68)="","",INDEX('Line Detail'!$F$6:$F$505,$M68))) | G68: =IF($M68=0,"",IF(INDEX('Line Detail'!$G$6:$G$505,$M68)="","",INDEX('Line Detail'!$G$6:$G$505,$M68))) | H68: =IF($M68=0,"",IF(INDEX('Line Detail'!$H$6:$H$505,$M68)="","",INDEX('Line Detail'!$H$6:$H$505,$M68))) | I68: =IF($M68=0,"",IF(INDEX('Line Detail'!$O$6:$O$505,$M68)="","",INDEX('Line Detail'!$O$6:$O$505,$M68))) | J68: =IF($M68=0,"",IF(INDEX('Line Detail'!$R$6:$R$505,$M68)="","",INDEX('Line Detail'!$R$6:$R$505,$M68))) | K68: =IF($M68=0,"",IF(INDEX('Line Detail'!$S$6:$S$505,$M68)="","",INDEX('Line Detail'!$S$6:$S$505,$M68))) | M68: =IFERROR(MATCH(63,'Line Detail'!$W$6:$W$505,0),0) -> 0
A69: =IF($M69=0,"",64) | B69: =IF($M69=0,"",IF(INDEX('Line Detail'!$B$6:$B$505,$M69)="","",INDEX('Line Detail'!$B$6:$B$505,$M69))) | C69: =IF($M69=0,"",IF(INDEX('Line Detail'!$C$6:$C$505,$M69)="","",INDEX('Line Detail'!$C$6:$C$505,$M69))) | D69: =IF($M69=0,"",IF(INDEX('Line Detail'!$D$6:$D$505,$M69)="","",INDEX('Line Detail'!$D$6:$D$505,$M69))) | E69: =IF($M69=0,"",IF(INDEX('Line Detail'!$E$6:$E$505,$M69)="","",INDEX('Line Detail'!$E$6:$E$505,$M69))) | F69: =IF($M69=0,"",IF(INDEX('Line Detail'!$F$6:$F$505,$M69)="","",INDEX('Line Detail'!$F$6:$F$505,$M69))) | G69: =IF($M69=0,"",IF(INDEX('Line Detail'!$G$6:$G$505,$M69)="","",INDEX('Line Detail'!$G$6:$G$505,$M69))) | H69: =IF($M69=0,"",IF(INDEX('Line Detail'!$H$6:$H$505,$M69)="","",INDEX('Line Detail'!$H$6:$H$505,$M69))) | I69: =IF($M69=0,"",IF(INDEX('Line Detail'!$O$6:$O$505,$M69)="","",INDEX('Line Detail'!$O$6:$O$505,$M69))) | J69: =IF($M69=0,"",IF(INDEX('Line Detail'!$R$6:$R$505,$M69)="","",INDEX('Line Detail'!$R$6:$R$505,$M69))) | K69: =IF($M69=0,"",IF(INDEX('Line Detail'!$S$6:$S$505,$M69)="","",INDEX('Line Detail'!$S$6:$S$505,$M69))) | M69: =IFERROR(MATCH(64,'Line Detail'!$W$6:$W$505,0),0) -> 0
A70: =IF($M70=0,"",65) | B70: =IF($M70=0,"",IF(INDEX('Line Detail'!$B$6:$B$505,$M70)="","",INDEX('Line Detail'!$B$6:$B$505,$M70))) | C70: =IF($M70=0,"",IF(INDEX('Line Detail'!$C$6:$C$505,$M70)="","",INDEX('Line Detail'!$C$6:$C$505,$M70))) | D70: =IF($M70=0,"",IF(INDEX('Line Detail'!$D$6:$D$505,$M70)="","",INDEX('Line Detail'!$D$6:$D$505,$M70))) | E70: =IF($M70=0,"",IF(INDEX('Line Detail'!$E$6:$E$505,$M70)="","",INDEX('Line Detail'!$E$6:$E$505,$M70))) | F70: =IF($M70=0,"",IF(INDEX('Line Detail'!$F$6:$F$505,$M70)="","",INDEX('Line Detail'!$F$6:$F$505,$M70))) | G70: =IF($M70=0,"",IF(INDEX('Line Detail'!$G$6:$G$505,$M70)="","",INDEX('Line Detail'!$G$6:$G$505,$M70))) | H70: =IF($M70=0,"",IF(INDEX('Line Detail'!$H$6:$H$505,$M70)="","",INDEX('Line Detail'!$H$6:$H$505,$M70))) | I70: =IF($M70=0,"",IF(INDEX('Line Detail'!$O$6:$O$505,$M70)="","",INDEX('Line Detail'!$O$6:$O$505,$M70))) | J70: =IF($M70=0,"",IF(INDEX('Line Detail'!$R$6:$R$505,$M70)="","",INDEX('Line Detail'!$R$6:$R$505,$M70))) | K70: =IF($M70=0,"",IF(INDEX('Line Detail'!$S$6:$S$505,$M70)="","",INDEX('Line Detail'!$S$6:$S$505,$M70))) | M70: =IFERROR(MATCH(65,'Line Detail'!$W$6:$W$505,0),0) -> 0
A71: =IF($M71=0,"",66) | B71: =IF($M71=0,"",IF(INDEX('Line Detail'!$B$6:$B$505,$M71)="","",INDEX('Line Detail'!$B$6:$B$505,$M71))) | C71: =IF($M71=0,"",IF(INDEX('Line Detail'!$C$6:$C$505,$M71)="","",INDEX('Line Detail'!$C$6:$C$505,$M71))) | D71: =IF($M71=0,"",IF(INDEX('Line Detail'!$D$6:$D$505,$M71)="","",INDEX('Line Detail'!$D$6:$D$505,$M71))) | E71: =IF($M71=0,"",IF(INDEX('Line Detail'!$E$6:$E$505,$M71)="","",INDEX('Line Detail'!$E$6:$E$505,$M71))) | F71: =IF($M71=0,"",IF(INDEX('Line Detail'!$F$6:$F$505,$M71)="","",INDEX('Line Detail'!$F$6:$F$505,$M71))) | G71: =IF($M71=0,"",IF(INDEX('Line Detail'!$G$6:$G$505,$M71)="","",INDEX('Line Detail'!$G$6:$G$505,$M71))) | H71: =IF($M71=0,"",IF(INDEX('Line Detail'!$H$6:$H$505,$M71)="","",INDEX('Line Detail'!$H$6:$H$505,$M71))) | I71: =IF($M71=0,"",IF(INDEX('Line Detail'!$O$6:$O$505,$M71)="","",INDEX('Line Detail'!$O$6:$O$505,$M71))) | J71: =IF($M71=0,"",IF(INDEX('Line Detail'!$R$6:$R$505,$M71)="","",INDEX('Line Detail'!$R$6:$R$505,$M71))) | K71: =IF($M71=0,"",IF(INDEX('Line Detail'!$S$6:$S$505,$M71)="","",INDEX('Line Detail'!$S$6:$S$505,$M71))) | M71: =IFERROR(MATCH(66,'Line Detail'!$W$6:$W$505,0),0) -> 0
A72: =IF($M72=0,"",67) | B72: =IF($M72=0,"",IF(INDEX('Line Detail'!$B$6:$B$505,$M72)="","",INDEX('Line Detail'!$B$6:$B$505,$M72))) | C72: =IF($M72=0,"",IF(INDEX('Line Detail'!$C$6:$C$505,$M72)="","",INDEX('Line Detail'!$C$6:$C$505,$M72))) | D72: =IF($M72=0,"",IF(INDEX('Line Detail'!$D$6:$D$505,$M72)="","",INDEX('Line Detail'!$D$6:$D$505,$M72))) | E72: =IF($M72=0,"",IF(INDEX('Line Detail'!$E$6:$E$505,$M72)="","",INDEX('Line Detail'!$E$6:$E$505,$M72))) | F72: =IF($M72=0,"",IF(INDEX('Line Detail'!$F$6:$F$505,$M72)="","",INDEX('Line Detail'!$F$6:$F$505,$M72))) | G72: =IF($M72=0,"",IF(INDEX('Line Detail'!$G$6:$G$505,$M72)="","",INDEX('Line Detail'!$G$6:$G$505,$M72))) | H72: =IF($M72=0,"",IF(INDEX('Line Detail'!$H$6:$H$505,$M72)="","",INDEX('Line Detail'!$H$6:$H$505,$M72))) | I72: =IF($M72=0,"",IF(INDEX('Line Detail'!$O$6:$O$505,$M72)="","",INDEX('Line Detail'!$O$6:$O$505,$M72))) | J72: =IF($M72=0,"",IF(INDEX('Line Detail'!$R$6:$R$505,$M72)="","",INDEX('Line Detail'!$R$6:$R$505,$M72))) | K72: =IF($M72=0,"",IF(INDEX('Line Detail'!$S$6:$S$505,$M72)="","",INDEX('Line Detail'!$S$6:$S$505,$M72))) | M72: =IFERROR(MATCH(67,'Line Detail'!$W$6:$W$505,0),0) -> 0
A73: =IF($M73=0,"",68) | B73: =IF($M73=0,"",IF(INDEX('Line Detail'!$B$6:$B$505,$M73)="","",INDEX('Line Detail'!$B$6:$B$505,$M73))) | C73: =IF($M73=0,"",IF(INDEX('Line Detail'!$C$6:$C$505,$M73)="","",INDEX('Line Detail'!$C$6:$C$505,$M73))) | D73: =IF($M73=0,"",IF(INDEX('Line Detail'!$D$6:$D$505,$M73)="","",INDEX('Line Detail'!$D$6:$D$505,$M73))) | E73: =IF($M73=0,"",IF(INDEX('Line Detail'!$E$6:$E$505,$M73)="","",INDEX('Line Detail'!$E$6:$E$505,$M73))) | F73: =IF($M73=0,"",IF(INDEX('Line Detail'!$F$6:$F$505,$M73)="","",INDEX('Line Detail'!$F$6:$F$505,$M73))) | G73: =IF($M73=0,"",IF(INDEX('Line Detail'!$G$6:$G$505,$M73)="","",INDEX('Line Detail'!$G$6:$G$505,$M73))) | H73: =IF($M73=0,"",IF(INDEX('Line Detail'!$H$6:$H$505,$M73)="","",INDEX('Line Detail'!$H$6:$H$505,$M73))) | I73: =IF($M73=0,"",IF(INDEX('Line Detail'!$O$6:$O$505,$M73)="","",INDEX('Line Detail'!$O$6:$O$505,$M73))) | J73: =IF($M73=0,"",IF(INDEX('Line Detail'!$R$6:$R$505,$M73)="","",INDEX('Line Detail'!$R$6:$R$505,$M73))) | K73: =IF($M73=0,"",IF(INDEX('Line Detail'!$S$6:$S$505,$M73)="","",INDEX('Line Detail'!$S$6:$S$505,$M73))) | M73: =IFERROR(MATCH(68,'Line Detail'!$W$6:$W$505,0),0) -> 0
A74: =IF($M74=0,"",69) | B74: =IF($M74=0,"",IF(INDEX('Line Detail'!$B$6:$B$505,$M74)="","",INDEX('Line Detail'!$B$6:$B$505,$M74))) | C74: =IF($M74=0,"",IF(INDEX('Line Detail'!$C$6:$C$505,$M74)="","",INDEX('Line Detail'!$C$6:$C$505,$M74))) | D74: =IF($M74=0,"",IF(INDEX('Line Detail'!$D$6:$D$505,$M74)="","",INDEX('Line Detail'!$D$6:$D$505,$M74))) | E74: =IF($M74=0,"",IF(INDEX('Line Detail'!$E$6:$E$505,$M74)="","",INDEX('Line Detail'!$E$6:$E$505,$M74))) | F74: =IF($M74=0,"",IF(INDEX('Line Detail'!$F$6:$F$505,$M74)="","",INDEX('Line Detail'!$F$6:$F$505,$M74))) | G74: =IF($M74=0,"",IF(INDEX('Line Detail'!$G$6:$G$505,$M74)="","",INDEX('Line Detail'!$G$6:$G$505,$M74))) | H74: =IF($M74=0,"",IF(INDEX('Line Detail'!$H$6:$H$505,$M74)="","",INDEX('Line Detail'!$H$6:$H$505,$M74))) | I74: =IF($M74=0,"",IF(INDEX('Line Detail'!$O$6:$O$505,$M74)="","",INDEX('Line Detail'!$O$6:$O$505,$M74))) | J74: =IF($M74=0,"",IF(INDEX('Line Detail'!$R$6:$R$505,$M74)="","",INDEX('Line Detail'!$R$6:$R$505,$M74))) | K74: =IF($M74=0,"",IF(INDEX('Line Detail'!$S$6:$S$505,$M74)="","",INDEX('Line Detail'!$S$6:$S$505,$M74))) | M74: =IFERROR(MATCH(69,'Line Detail'!$W$6:$W$505,0),0) -> 0
A75: =IF($M75=0,"",70) | B75: =IF($M75=0,"",IF(INDEX('Line Detail'!$B$6:$B$505,$M75)="","",INDEX('Line Detail'!$B$6:$B$505,$M75))) | C75: =IF($M75=0,"",IF(INDEX('Line Detail'!$C$6:$C$505,$M75)="","",INDEX('Line Detail'!$C$6:$C$505,$M75))) | D75: =IF($M75=0,"",IF(INDEX('Line Detail'!$D$6:$D$505,$M75)="","",INDEX('Line Detail'!$D$6:$D$505,$M75))) | E75: =IF($M75=0,"",IF(INDEX('Line Detail'!$E$6:$E$505,$M75)="","",INDEX('Line Detail'!$E$6:$E$505,$M75))) | F75: =IF($M75=0,"",IF(INDEX('Line Detail'!$F$6:$F$505,$M75)="","",INDEX('Line Detail'!$F$6:$F$505,$M75))) | G75: =IF($M75=0,"",IF(INDEX('Line Detail'!$G$6:$G$505,$M75)="","",INDEX('Line Detail'!$G$6:$G$505,$M75))) | H75: =IF($M75=0,"",IF(INDEX('Line Detail'!$H$6:$H$505,$M75)="","",INDEX('Line Detail'!$H$6:$H$505,$M75))) | I75: =IF($M75=0,"",IF(INDEX('Line Detail'!$O$6:$O$505,$M75)="","",INDEX('Line Detail'!$O$6:$O$505,$M75))) | J75: =IF($M75=0,"",IF(INDEX('Line Detail'!$R$6:$R$505,$M75)="","",INDEX('Line Detail'!$R$6:$R$505,$M75))) | K75: =IF($M75=0,"",IF(INDEX('Line Detail'!$S$6:$S$505,$M75)="","",INDEX('Line Detail'!$S$6:$S$505,$M75))) | M75: =IFERROR(MATCH(70,'Line Detail'!$W$6:$W$505,0),0) -> 0
A76: =IF($M76=0,"",71) | B76: =IF($M76=0,"",IF(INDEX('Line Detail'!$B$6:$B$505,$M76)="","",INDEX('Line Detail'!$B$6:$B$505,$M76))) | C76: =IF($M76=0,"",IF(INDEX('Line Detail'!$C$6:$C$505,$M76)="","",INDEX('Line Detail'!$C$6:$C$505,$M76))) | D76: =IF($M76=0,"",IF(INDEX('Line Detail'!$D$6:$D$505,$M76)="","",INDEX('Line Detail'!$D$6:$D$505,$M76))) | E76: =IF($M76=0,"",IF(INDEX('Line Detail'!$E$6:$E$505,$M76)="","",INDEX('Line Detail'!$E$6:$E$505,$M76))) | F76: =IF($M76=0,"",IF(INDEX('Line Detail'!$F$6:$F$505,$M76)="","",INDEX('Line Detail'!$F$6:$F$505,$M76))) | G76: =IF($M76=0,"",IF(INDEX('Line Detail'!$G$6:$G$505,$M76)="","",INDEX('Line Detail'!$G$6:$G$505,$M76))) | H76: =IF($M76=0,"",IF(INDEX('Line Detail'!$H$6:$H$505,$M76)="","",INDEX('Line Detail'!$H$6:$H$505,$M76))) | I76: =IF($M76=0,"",IF(INDEX('Line Detail'!$O$6:$O$505,$M76)="","",INDEX('Line Detail'!$O$6:$O$505,$M76))) | J76: =IF($M76=0,"",IF(INDEX('Line Detail'!$R$6:$R$505,$M76)="","",INDEX('Line Detail'!$R$6:$R$505,$M76))) | K76: =IF($M76=0,"",IF(INDEX('Line Detail'!$S$6:$S$505,$M76)="","",INDEX('Line Detail'!$S$6:$S$505,$M76))) | M76: =IFERROR(MATCH(71,'Line Detail'!$W$6:$W$505,0),0) -> 0
A77: =IF($M77=0,"",72) | B77: =IF($M77=0,"",IF(INDEX('Line Detail'!$B$6:$B$505,$M77)="","",INDEX('Line Detail'!$B$6:$B$505,$M77))) | C77: =IF($M77=0,"",IF(INDEX('Line Detail'!$C$6:$C$505,$M77)="","",INDEX('Line Detail'!$C$6:$C$505,$M77))) | D77: =IF($M77=0,"",IF(INDEX('Line Detail'!$D$6:$D$505,$M77)="","",INDEX('Line Detail'!$D$6:$D$505,$M77))) | E77: =IF($M77=0,"",IF(INDEX('Line Detail'!$E$6:$E$505,$M77)="","",INDEX('Line Detail'!$E$6:$E$505,$M77))) | F77: =IF($M77=0,"",IF(INDEX('Line Detail'!$F$6:$F$505,$M77)="","",INDEX('Line Detail'!$F$6:$F$505,$M77))) | G77: =IF($M77=0,"",IF(INDEX('Line Detail'!$G$6:$G$505,$M77)="","",INDEX('Line Detail'!$G$6:$G$505,$M77))) | H77: =IF($M77=0,"",IF(INDEX('Line Detail'!$H$6:$H$505,$M77)="","",INDEX('Line Detail'!$H$6:$H$505,$M77))) | I77: =IF($M77=0,"",IF(INDEX('Line Detail'!$O$6:$O$505,$M77)="","",INDEX('Line Detail'!$O$6:$O$505,$M77))) | J77: =IF($M77=0,"",IF(INDEX('Line Detail'!$R$6:$R$505,$M77)="","",INDEX('Line Detail'!$R$6:$R$505,$M77))) | K77: =IF($M77=0,"",IF(INDEX('Line Detail'!$S$6:$S$505,$M77)="","",INDEX('Line Detail'!$S$6:$S$505,$M77))) | M77: =IFERROR(MATCH(72,'Line Detail'!$W$6:$W$505,0),0) -> 0
A78: =IF($M78=0,"",73) | B78: =IF($M78=0,"",IF(INDEX('Line Detail'!$B$6:$B$505,$M78)="","",INDEX('Line Detail'!$B$6:$B$505,$M78))) | C78: =IF($M78=0,"",IF(INDEX('Line Detail'!$C$6:$C$505,$M78)="","",INDEX('Line Detail'!$C$6:$C$505,$M78))) | D78: =IF($M78=0,"",IF(INDEX('Line Detail'!$D$6:$D$505,$M78)="","",INDEX('Line Detail'!$D$6:$D$505,$M78))) | E78: =IF($M78=0,"",IF(INDEX('Line Detail'!$E$6:$E$505,$M78)="","",INDEX('Line Detail'!$E$6:$E$505,$M78))) | F78: =IF($M78=0,"",IF(INDEX('Line Detail'!$F$6:$F$505,$M78)="","",INDEX('Line Detail'!$F$6:$F$505,$M78))) | G78: =IF($M78=0,"",IF(INDEX('Line Detail'!$G$6:$G$505,$M78)="","",INDEX('Line Detail'!$G$6:$G$505,$M78))) | H78: =IF($M78=0,"",IF(INDEX('Line Detail'!$H$6:$H$505,$M78)="","",INDEX('Line Detail'!$H$6:$H$505,$M78))) | I78: =IF($M78=0,"",IF(INDEX('Line Detail'!$O$6:$O$505,$M78)="","",INDEX('Line Detail'!$O$6:$O$505,$M78))) | J78: =IF($M78=0,"",IF(INDEX('Line Detail'!$R$6:$R$505,$M78)="","",INDEX('Line Detail'!$R$6:$R$505,$M78))) | K78: =IF($M78=0,"",IF(INDEX('Line Detail'!$S$6:$S$505,$M78)="","",INDEX('Line Detail'!$S$6:$S$505,$M78))) | M78: =IFERROR(MATCH(73,'Line Detail'!$W$6:$W$505,0),0) -> 0
A79: =IF($M79=0,"",74) | B79: =IF($M79=0,"",IF(INDEX('Line Detail'!$B$6:$B$505,$M79)="","",INDEX('Line Detail'!$B$6:$B$505,$M79))) | C79: =IF($M79=0,"",IF(INDEX('Line Detail'!$C$6:$C$505,$M79)="","",INDEX('Line Detail'!$C$6:$C$505,$M79))) | D79: =IF($M79=0,"",IF(INDEX('Line Detail'!$D$6:$D$505,$M79)="","",INDEX('Line Detail'!$D$6:$D$505,$M79))) | E79: =IF($M79=0,"",IF(INDEX('Line Detail'!$E$6:$E$505,$M79)="","",INDEX('Line Detail'!$E$6:$E$505,$M79))) | F79: =IF($M79=0,"",IF(INDEX('Line Detail'!$F$6:$F$505,$M79)="","",INDEX('Line Detail'!$F$6:$F$505,$M79))) | G79: =IF($M79=0,"",IF(INDEX('Line Detail'!$G$6:$G$505,$M79)="","",INDEX('Line Detail'!$G$6:$G$505,$M79))) | H79: =IF($M79=0,"",IF(INDEX('Line Detail'!$H$6:$H$505,$M79)="","",INDEX('Line Detail'!$H$6:$H$505,$M79))) | I79: =IF($M79=0,"",IF(INDEX('Line Detail'!$O$6:$O$505,$M79)="","",INDEX('Line Detail'!$O$6:$O$505,$M79))) | J79: =IF($M79=0,"",IF(INDEX('Line Detail'!$R$6:$R$505,$M79)="","",INDEX('Line Detail'!$R$6:$R$505,$M79))) | K79: =IF($M79=0,"",IF(INDEX('Line Detail'!$S$6:$S$505,$M79)="","",INDEX('Line Detail'!$S$6:$S$505,$M79))) | M79: =IFERROR(MATCH(74,'Line Detail'!$W$6:$W$505,0),0) -> 0
A80: =IF($M80=0,"",75) | B80: =IF($M80=0,"",IF(INDEX('Line Detail'!$B$6:$B$505,$M80)="","",INDEX('Line Detail'!$B$6:$B$505,$M80))) | C80: =IF($M80=0,"",IF(INDEX('Line Detail'!$C$6:$C$505,$M80)="","",INDEX('Line Detail'!$C$6:$C$505,$M80))) | D80: =IF($M80=0,"",IF(INDEX('Line Detail'!$D$6:$D$505,$M80)="","",INDEX('Line Detail'!$D$6:$D$505,$M80))) | E80: =IF($M80=0,"",IF(INDEX('Line Detail'!$E$6:$E$505,$M80)="","",INDEX('Line Detail'!$E$6:$E$505,$M80))) | F80: =IF($M80=0,"",IF(INDEX('Line Detail'!$F$6:$F$505,$M80)="","",INDEX('Line Detail'!$F$6:$F$505,$M80))) | G80: =IF($M80=0,"",IF(INDEX('Line Detail'!$G$6:$G$505,$M80)="","",INDEX('Line Detail'!$G$6:$G$505,$M80))) | H80: =IF($M80=0,"",IF(INDEX('Line Detail'!$H$6:$H$505,$M80)="","",INDEX('Line Detail'!$H$6:$H$505,$M80))) | I80: =IF($M80=0,"",IF(INDEX('Line Detail'!$O$6:$O$505,$M80)="","",INDEX('Line Detail'!$O$6:$O$505,$M80))) | J80: =IF($M80=0,"",IF(INDEX('Line Detail'!$R$6:$R$505,$M80)="","",INDEX('Line Detail'!$R$6:$R$505,$M80))) | K80: =IF($M80=0,"",IF(INDEX('Line Detail'!$S$6:$S$505,$M80)="","",INDEX('Line Detail'!$S$6:$S$505,$M80))) | M80: =IFERROR(MATCH(75,'Line Detail'!$W$6:$W$505,0),0) -> 0
A81: =IF($M81=0,"",76) | B81: =IF($M81=0,"",IF(INDEX('Line Detail'!$B$6:$B$505,$M81)="","",INDEX('Line Detail'!$B$6:$B$505,$M81))) | C81: =IF($M81=0,"",IF(INDEX('Line Detail'!$C$6:$C$505,$M81)="","",INDEX('Line Detail'!$C$6:$C$505,$M81))) | D81: =IF($M81=0,"",IF(INDEX('Line Detail'!$D$6:$D$505,$M81)="","",INDEX('Line Detail'!$D$6:$D$505,$M81))) | E81: =IF($M81=0,"",IF(INDEX('Line Detail'!$E$6:$E$505,$M81)="","",INDEX('Line Detail'!$E$6:$E$505,$M81))) | F81: =IF($M81=0,"",IF(INDEX('Line Detail'!$F$6:$F$505,$M81)="","",INDEX('Line Detail'!$F$6:$F$505,$M81))) | G81: =IF($M81=0,"",IF(INDEX('Line Detail'!$G$6:$G$505,$M81)="","",INDEX('Line Detail'!$G$6:$G$505,$M81))) | H81: =IF($M81=0,"",IF(INDEX('Line Detail'!$H$6:$H$505,$M81)="","",INDEX('Line Detail'!$H$6:$H$505,$M81))) | I81: =IF($M81=0,"",IF(INDEX('Line Detail'!$O$6:$O$505,$M81)="","",INDEX('Line Detail'!$O$6:$O$505,$M81))) | J81: =IF($M81=0,"",IF(INDEX('Line Detail'!$R$6:$R$505,$M81)="","",INDEX('Line Detail'!$R$6:$R$505,$M81))) | K81: =IF($M81=0,"",IF(INDEX('Line Detail'!$S$6:$S$505,$M81)="","",INDEX('Line Detail'!$S$6:$S$505,$M81))) | M81: =IFERROR(MATCH(76,'Line Detail'!$W$6:$W$505,0),0) -> 0
A82: =IF($M82=0,"",77) | B82: =IF($M82=0,"",IF(INDEX('Line Detail'!$B$6:$B$505,$M82)="","",INDEX('Line Detail'!$B$6:$B$505,$M82))) | C82: =IF($M82=0,"",IF(INDEX('Line Detail'!$C$6:$C$505,$M82)="","",INDEX('Line Detail'!$C$6:$C$505,$M82))) | D82: =IF($M82=0,"",IF(INDEX('Line Detail'!$D$6:$D$505,$M82)="","",INDEX('Line Detail'!$D$6:$D$505,$M82))) | E82: =IF($M82=0,"",IF(INDEX('Line Detail'!$E$6:$E$505,$M82)="","",INDEX('Line Detail'!$E$6:$E$505,$M82))) | F82: =IF($M82=0,"",IF(INDEX('Line Detail'!$F$6:$F$505,$M82)="","",INDEX('Line Detail'!$F$6:$F$505,$M82))) | G82: =IF($M82=0,"",IF(INDEX('Line Detail'!$G$6:$G$505,$M82)="","",INDEX('Line Detail'!$G$6:$G$505,$M82))) | H82: =IF($M82=0,"",IF(INDEX('Line Detail'!$H$6:$H$505,$M82)="","",INDEX('Line Detail'!$H$6:$H$505,$M82))) | I82: =IF($M82=0,"",IF(INDEX('Line Detail'!$O$6:$O$505,$M82)="","",INDEX('Line Detail'!$O$6:$O$505,$M82))) | J82: =IF($M82=0,"",IF(INDEX('Line Detail'!$R$6:$R$505,$M82)="","",INDEX('Line Detail'!$R$6:$R$505,$M82))) | K82: =IF($M82=0,"",IF(INDEX('Line Detail'!$S$6:$S$505,$M82)="","",INDEX('Line Detail'!$S$6:$S$505,$M82))) | M82: =IFERROR(MATCH(77,'Line Detail'!$W$6:$W$505,0),0) -> 0
A83: =IF($M83=0,"",78) | B83: =IF($M83=0,"",IF(INDEX('Line Detail'!$B$6:$B$505,$M83)="","",INDEX('Line Detail'!$B$6:$B$505,$M83))) | C83: =IF($M83=0,"",IF(INDEX('Line Detail'!$C$6:$C$505,$M83)="","",INDEX('Line Detail'!$C$6:$C$505,$M83))) | D83: =IF($M83=0,"",IF(INDEX('Line Detail'!$D$6:$D$505,$M83)="","",INDEX('Line Detail'!$D$6:$D$505,$M83))) | E83: =IF($M83=0,"",IF(INDEX('Line Detail'!$E$6:$E$505,$M83)="","",INDEX('Line Detail'!$E$6:$E$505,$M83))) | F83: =IF($M83=0,"",IF(INDEX('Line Detail'!$F$6:$F$505,$M83)="","",INDEX('Line Detail'!$F$6:$F$505,$M83))) | G83: =IF($M83=0,"",IF(INDEX('Line Detail'!$G$6:$G$505,$M83)="","",INDEX('Line Detail'!$G$6:$G$505,$M83))) | H83: =IF($M83=0,"",IF(INDEX('Line Detail'!$H$6:$H$505,$M83)="","",INDEX('Line Detail'!$H$6:$H$505,$M83))) | I83: =IF($M83=0,"",IF(INDEX('Line Detail'!$O$6:$O$505,$M83)="","",INDEX('Line Detail'!$O$6:$O$505,$M83))) | J83: =IF($M83=0,"",IF(INDEX('Line Detail'!$R$6:$R$505,$M83)="","",INDEX('Line Detail'!$R$6:$R$505,$M83))) | K83: =IF($M83=0,"",IF(INDEX('Line Detail'!$S$6:$S$505,$M83)="","",INDEX('Line Detail'!$S$6:$S$505,$M83))) | M83: =IFERROR(MATCH(78,'Line Detail'!$W$6:$W$505,0),0) -> 0
A84: =IF($M84=0,"",79) | B84: =IF($M84=0,"",IF(INDEX('Line Detail'!$B$6:$B$505,$M84)="","",INDEX('Line Detail'!$B$6:$B$505,$M84))) | C84: =IF($M84=0,"",IF(INDEX('Line Detail'!$C$6:$C$505,$M84)="","",INDEX('Line Detail'!$C$6:$C$505,$M84))) | D84: =IF($M84=0,"",IF(INDEX('Line Detail'!$D$6:$D$505,$M84)="","",INDEX('Line Detail'!$D$6:$D$505,$M84))) | E84: =IF($M84=0,"",IF(INDEX('Line Detail'!$E$6:$E$505,$M84)="","",INDEX('Line Detail'!$E$6:$E$505,$M84))) | F84: =IF($M84=0,"",IF(INDEX('Line Detail'!$F$6:$F$505,$M84)="","",INDEX('Line Detail'!$F$6:$F$505,$M84))) | G84: =IF($M84=0,"",IF(INDEX('Line Detail'!$G$6:$G$505,$M84)="","",INDEX('Line Detail'!$G$6:$G$505,$M84))) | H84: =IF($M84=0,"",IF(INDEX('Line Detail'!$H$6:$H$505,$M84)="","",INDEX('Line Detail'!$H$6:$H$505,$M84))) | I84: =IF($M84=0,"",IF(INDEX('Line Detail'!$O$6:$O$505,$M84)="","",INDEX('Line Detail'!$O$6:$O$505,$M84))) | J84: =IF($M84=0,"",IF(INDEX('Line Detail'!$R$6:$R$505,$M84)="","",INDEX('Line Detail'!$R$6:$R$505,$M84))) | K84: =IF($M84=0,"",IF(INDEX('Line Detail'!$S$6:$S$505,$M84)="","",INDEX('Line Detail'!$S$6:$S$505,$M84))) | M84: =IFERROR(MATCH(79,'Line Detail'!$W$6:$W$505,0),0) -> 0
A85: =IF($M85=0,"",80) | B85: =IF($M85=0,"",IF(INDEX('Line Detail'!$B$6:$B$505,$M85)="","",INDEX('Line Detail'!$B$6:$B$505,$M85))) | C85: =IF($M85=0,"",IF(INDEX('Line Detail'!$C$6:$C$505,$M85)="","",INDEX('Line Detail'!$C$6:$C$505,$M85))) | D85: =IF($M85=0,"",IF(INDEX('Line Detail'!$D$6:$D$505,$M85)="","",INDEX('Line Detail'!$D$6:$D$505,$M85))) | E85: =IF($M85=0,"",IF(INDEX('Line Detail'!$E$6:$E$505,$M85)="","",INDEX('Line Detail'!$E$6:$E$505,$M85))) | F85: =IF($M85=0,"",IF(INDEX('Line Detail'!$F$6:$F$505,$M85)="","",INDEX('Line Detail'!$F$6:$F$505,$M85))) | G85: =IF($M85=0,"",IF(INDEX('Line Detail'!$G$6:$G$505,$M85)="","",INDEX('Line Detail'!$G$6:$G$505,$M85))) | H85: =IF($M85=0,"",IF(INDEX('Line Detail'!$H$6:$H$505,$M85)="","",INDEX('Line Detail'!$H$6:$H$505,$M85))) | I85: =IF($M85=0,"",IF(INDEX('Line Detail'!$O$6:$O$505,$M85)="","",INDEX('Line Detail'!$O$6:$O$505,$M85))) | J85: =IF($M85=0,"",IF(INDEX('Line Detail'!$R$6:$R$505,$M85)="","",INDEX('Line Detail'!$R$6:$R$505,$M85))) | K85: =IF($M85=0,"",IF(INDEX('Line Detail'!$S$6:$S$505,$M85)="","",INDEX('Line Detail'!$S$6:$S$505,$M85))) | M85: =IFERROR(MATCH(80,'Line Detail'!$W$6:$W$505,0),0) -> 0
A86: =IF($M86=0,"",81) | B86: =IF($M86=0,"",IF(INDEX('Line Detail'!$B$6:$B$505,$M86)="","",INDEX('Line Detail'!$B$6:$B$505,$M86))) | C86: =IF($M86=0,"",IF(INDEX('Line Detail'!$C$6:$C$505,$M86)="","",INDEX('Line Detail'!$C$6:$C$505,$M86))) | D86: =IF($M86=0,"",IF(INDEX('Line Detail'!$D$6:$D$505,$M86)="","",INDEX('Line Detail'!$D$6:$D$505,$M86))) | E86: =IF($M86=0,"",IF(INDEX('Line Detail'!$E$6:$E$505,$M86)="","",INDEX('Line Detail'!$E$6:$E$505,$M86))) | F86: =IF($M86=0,"",IF(INDEX('Line Detail'!$F$6:$F$505,$M86)="","",INDEX('Line Detail'!$F$6:$F$505,$M86))) | G86: =IF($M86=0,"",IF(INDEX('Line Detail'!$G$6:$G$505,$M86)="","",INDEX('Line Detail'!$G$6:$G$505,$M86))) | H86: =IF($M86=0,"",IF(INDEX('Line Detail'!$H$6:$H$505,$M86)="","",INDEX('Line Detail'!$H$6:$H$505,$M86))) | I86: =IF($M86=0,"",IF(INDEX('Line Detail'!$O$6:$O$505,$M86)="","",INDEX('Line Detail'!$O$6:$O$505,$M86))) | J86: =IF($M86=0,"",IF(INDEX('Line Detail'!$R$6:$R$505,$M86)="","",INDEX('Line Detail'!$R$6:$R$505,$M86))) | K86: =IF($M86=0,"",IF(INDEX('Line Detail'!$S$6:$S$505,$M86)="","",INDEX('Line Detail'!$S$6:$S$505,$M86))) | M86: =IFERROR(MATCH(81,'Line Detail'!$W$6:$W$505,0),0) -> 0
A87: =IF($M87=0,"",82) | B87: =IF($M87=0,"",IF(INDEX('Line Detail'!$B$6:$B$505,$M87)="","",INDEX('Line Detail'!$B$6:$B$505,$M87))) | C87: =IF($M87=0,"",IF(INDEX('Line Detail'!$C$6:$C$505,$M87)="","",INDEX('Line Detail'!$C$6:$C$505,$M87))) | D87: =IF($M87=0,"",IF(INDEX('Line Detail'!$D$6:$D$505,$M87)="","",INDEX('Line Detail'!$D$6:$D$505,$M87))) | E87: =IF($M87=0,"",IF(INDEX('Line Detail'!$E$6:$E$505,$M87)="","",INDEX('Line Detail'!$E$6:$E$505,$M87))) | F87: =IF($M87=0,"",IF(INDEX('Line Detail'!$F$6:$F$505,$M87)="","",INDEX('Line Detail'!$F$6:$F$505,$M87))) | G87: =IF($M87=0,"",IF(INDEX('Line Detail'!$G$6:$G$505,$M87)="","",INDEX('Line Detail'!$G$6:$G$505,$M87))) | H87: =IF($M87=0,"",IF(INDEX('Line Detail'!$H$6:$H$505,$M87)="","",INDEX('Line Detail'!$H$6:$H$505,$M87))) | I87: =IF($M87=0,"",IF(INDEX('Line Detail'!$O$6:$O$505,$M87)="","",INDEX('Line Detail'!$O$6:$O$505,$M87))) | J87: =IF($M87=0,"",IF(INDEX('Line Detail'!$R$6:$R$505,$M87)="","",INDEX('Line Detail'!$R$6:$R$505,$M87))) | K87: =IF($M87=0,"",IF(INDEX('Line Detail'!$S$6:$S$505,$M87)="","",INDEX('Line Detail'!$S$6:$S$505,$M87))) | M87: =IFERROR(MATCH(82,'Line Detail'!$W$6:$W$505,0),0) -> 0
A88: =IF($M88=0,"",83) | B88: =IF($M88=0,"",IF(INDEX('Line Detail'!$B$6:$B$505,$M88)="","",INDEX('Line Detail'!$B$6:$B$505,$M88))) | C88: =IF($M88=0,"",IF(INDEX('Line Detail'!$C$6:$C$505,$M88)="","",INDEX('Line Detail'!$C$6:$C$505,$M88))) | D88: =IF($M88=0,"",IF(INDEX('Line Detail'!$D$6:$D$505,$M88)="","",INDEX('Line Detail'!$D$6:$D$505,$M88))) | E88: =IF($M88=0,"",IF(INDEX('Line Detail'!$E$6:$E$505,$M88)="","",INDEX('Line Detail'!$E$6:$E$505,$M88))) | F88: =IF($M88=0,"",IF(INDEX('Line Detail'!$F$6:$F$505,$M88)="","",INDEX('Line Detail'!$F$6:$F$505,$M88))) | G88: =IF($M88=0,"",IF(INDEX('Line Detail'!$G$6:$G$505,$M88)="","",INDEX('Line Detail'!$G$6:$G$505,$M88))) | H88: =IF($M88=0,"",IF(INDEX('Line Detail'!$H$6:$H$505,$M88)="","",INDEX('Line Detail'!$H$6:$H$505,$M88))) | I88: =IF($M88=0,"",IF(INDEX('Line Detail'!$O$6:$O$505,$M88)="","",INDEX('Line Detail'!$O$6:$O$505,$M88))) | J88: =IF($M88=0,"",IF(INDEX('Line Detail'!$R$6:$R$505,$M88)="","",INDEX('Line Detail'!$R$6:$R$505,$M88))) | K88: =IF($M88=0,"",IF(INDEX('Line Detail'!$S$6:$S$505,$M88)="","",INDEX('Line Detail'!$S$6:$S$505,$M88))) | M88: =IFERROR(MATCH(83,'Line Detail'!$W$6:$W$505,0),0) -> 0
A89: =IF($M89=0,"",84) | B89: =IF($M89=0,"",IF(INDEX('Line Detail'!$B$6:$B$505,$M89)="","",INDEX('Line Detail'!$B$6:$B$505,$M89))) | C89: =IF($M89=0,"",IF(INDEX('Line Detail'!$C$6:$C$505,$M89)="","",INDEX('Line Detail'!$C$6:$C$505,$M89))) | D89: =IF($M89=0,"",IF(INDEX('Line Detail'!$D$6:$D$505,$M89)="","",INDEX('Line Detail'!$D$6:$D$505,$M89))) | E89: =IF($M89=0,"",IF(INDEX('Line Detail'!$E$6:$E$505,$M89)="","",INDEX('Line Detail'!$E$6:$E$505,$M89))) | F89: =IF($M89=0,"",IF(INDEX('Line Detail'!$F$6:$F$505,$M89)="","",INDEX('Line Detail'!$F$6:$F$505,$M89))) | G89: =IF($M89=0,"",IF(INDEX('Line Detail'!$G$6:$G$505,$M89)="","",INDEX('Line Detail'!$G$6:$G$505,$M89))) | H89: =IF($M89=0,"",IF(INDEX('Line Detail'!$H$6:$H$505,$M89)="","",INDEX('Line Detail'!$H$6:$H$505,$M89))) | I89: =IF($M89=0,"",IF(INDEX('Line Detail'!$O$6:$O$505,$M89)="","",INDEX('Line Detail'!$O$6:$O$505,$M89))) | J89: =IF($M89=0,"",IF(INDEX('Line Detail'!$R$6:$R$505,$M89)="","",INDEX('Line Detail'!$R$6:$R$505,$M89))) | K89: =IF($M89=0,"",IF(INDEX('Line Detail'!$S$6:$S$505,$M89)="","",INDEX('Line Detail'!$S$6:$S$505,$M89))) | M89: =IFERROR(MATCH(84,'Line Detail'!$W$6:$W$505,0),0) -> 0
